Workbook

Sheet Cover
B2: TEST REPORT DOCUMENT
A4: Project Name | B4: FSCM – Short Shelf-Life FMCG Supply Chain Management and Distribution Coordination | E4: Creator | F4: Tran Ngoc Khiet, Doan Duc Hai
A5: Project Code | B5: FA26SE083 | E5: Issue Date | F5: 28/10/2026
A6: Document Code | B6: FA26SE083_Test_Report_v1.3 | E6: Version | F6: 1.3
A9: Record of change
A10: Effective Date | B10: Version | C10: Change Item | D10: *A,D,M | E10: Change description | F10: Reference
A11: 27/10/2026 | B11: 1.0 | C11: Initial FSCM test design | D11: A | E11: Initial FSCM test case inventory and test execution plan. | F11: FSCM_Report5_Test_Report.xlsx
A12: 27/10/2026 | B12: 1.1 | C12: Example-format rebuild | D12: M | E12: Reformatted all 24 module sheets using example’s Round 1–3 structure. Added master list, scenario steps, preconditions, expected results and live summary formulas. No fabricated results. | F12: SRS v1.5; SDD v1.1; GitHub main
A13: 28/10/2026 | B13: 1.2 | C13: Updated FSCM v1.2 test design aligned with approved R5 requirements | D13: M | E13: Update prepaid/deferred, discount, 00:00 cutoff, manual offline Send, delivery, loyalty and NFR tests; preserve 271 cases and evidence status. | F13: Test Documentation v1.2; Unit Test v1.2; SRS v1.8; SDD v1.8
A14: 28/10/2026 | B14: 1.3 | C14: Five Main Flows F1–F5 and seven approved business decisions | D14: M | E14: Align cutoff 00:00 ICT; percentage-only shelf-life discount; 1 point per 10,000 VND; full actual receipt before Completed; positive net price; Admin/Operator product authority; staff-completed gifts. Detail group promotion, tie-break, late verification, P1/C1/P2/SHORT and F1–F5 traceability. Preserve all cases as Not Run. | F14: Five Main Flows F1–F5; SRS/SDD v1.8; Unit Test v1.3; Test Documentation v1.3

Sheet Test Statistics
B1: TEST STATISTICS
B3: Project Name | C3: FSCM – Short Shelf-Life FMCG Supply Chain Management and Distribution Coordination | E3: Creator | H3: Doan Duc Hai
B4: Project Code | C4: FA26SE083 | E4: Reviewer/Approver
B5: Document Code | C5: FA26SE083_Test_Report_v1.3 | E5: Issue Date | H5: 28/10/2026
B6: Notes | C6: 271 planned test cases; Round 1 Not Run. Main Flows F1–F5 aligned: 00:00 ICT, percentage-only discount, full receipt, 1 point/10,000 VND, Admin/Operator SKU permissions and staff gift completion. Record actual/evidence for Pass.
B10: No | C10: Module code | D10: Passed | E10: Failed | F10: Pending | G10: N/A | H10: Number of test cases
B11: 1 | C11: Authentication | D11: =Authentication!B6 -> 0 | E11: =Authentication!C6 -> 0 | F11: =Authentication!D6 -> 11 | G11: =Authentication!E6 -> 0 | H11: =Authentication!B4 -> 11
B12: 2 | C12: User Management | D12: ='User Management'!B6 -> 0 | E12: ='User Management'!C6 -> 0 | F12: ='User Management'!D6 -> 3 | G12: ='User Management'!E6 -> 0 | H12: ='User Management'!B4 -> 3
B13: 3 | C13: Retailer Registration | D13: ='Retailer Registration'!B6 -> 0 | E13: ='Retailer Registration'!C6 -> 0 | F13: ='Retailer Registration'!D6 -> 8 | G13: ='Retailer Registration'!E6 -> 0 | H13: ='Retailer Registration'!B4 -> 8
B14: 4 | C14: Retailer Profiles | D14: ='Retailer Profiles'!B6 -> 0 | E14: ='Retailer Profiles'!C6 -> 0 | F14: ='Retailer Profiles'!D6 -> 3 | G14: ='Retailer Profiles'!E6 -> 0 | H14: ='Retailer Profiles'!B4 -> 3
B15: 5 | C15: Product & Categories | D15: ='Product & Categories'!B6 -> 0 | E15: ='Product & Categories'!C6 -> 0 | F15: ='Product & Categories'!D6 -> 10 | G15: ='Product & Categories'!E6 -> 0 | H15: ='Product & Categories'!B4 -> 10
B16: 6 | C16: Promotion Management | D16: ='Promotion Management'!B6 -> 0 | E16: ='Promotion Management'!C6 -> 0 | F16: ='Promotion Management'!D6 -> 4 | G16: ='Promotion Management'!E6 -> 0 | H16: ='Promotion Management'!B4 -> 4
B17: 7 | C17: Shelf-Life Pricing | D17: ='Shelf-Life Pricing'!B6 -> 0 | E17: ='Shelf-Life Pricing'!C6 -> 0 | F17: ='Shelf-Life Pricing'!D6 -> 9 | G17: ='Shelf-Life Pricing'!E6 -> 0 | H17: ='Shelf-Life Pricing'!B4 -> 9
B18: 8 | C18: Order Management | D18: ='Order Management'!B6 -> 0 | E18: ='Order Management'!C6 -> 0 | F18: ='Order Management'!D6 -> 20 | G18: ='Order Management'!E6 -> 0 | H18: ='Order Management'!B4 -> 20
B19: 9 | C19: Offline Synchronization | D19: ='Offline Synchronization'!B6 -> 0 | E19: ='Offline Synchronization'!C6 -> 0 | F19: ='Offline Synchronization'!D6 -> 16 | G19: ='Offline Synchronization'!E6 -> 0 | H19: ='Offline Synchronization'!B4 -> 16
B20: 10 | C20: Allocation Engine | D20: ='Allocation Engine'!B6 -> 0 | E20: ='Allocation Engine'!C6 -> 0 | F20: ='Allocation Engine'!D6 -> 29 | G20: ='Allocation Engine'!E6 -> 0 | H20: ='Allocation Engine'!B4 -> 29
B21: 11 | C21: Allocation Approval | D21: ='Allocation Approval'!B6 -> 0 | E21: ='Allocation Approval'!C6 -> 0 | F21: ='Allocation Approval'!D6 -> 6 | G21: ='Allocation Approval'!E6 -> 0 | H21: ='Allocation Approval'!B4 -> 6
B22: 12 | C22: Goods Receipts | D22: ='Goods Receipts'!B6 -> 0 | E22: ='Goods Receipts'!C6 -> 0 | F22: ='Goods Receipts'!D6 -> 3 | G22: ='Goods Receipts'!E6 -> 0 | H22: ='Goods Receipts'!B4 -> 3
B23: 13 | C23: Warehouse Inventory | D23: ='Warehouse Inventory'!B6 -> 0 | E23: ='Warehouse Inventory'!C6 -> 0 | F23: ='Warehouse Inventory'!D6 -> 12 | G23: ='Warehouse Inventory'!E6 -> 0 | H23: ='Warehouse Inventory'!B4 -> 12
B24: 14 | C24: Picking & QR | D24: ='Picking & QR'!B6 -> 0 | E24: ='Picking & QR'!C6 -> 0 | F24: ='Picking & QR'!D6 -> 14 | G24: ='Picking & QR'!E6 -> 0 | H24: ='Picking & QR'!B4 -> 14
B25: 15 | C25: Delivery & Receipt | D25: ='Delivery & Receipt'!B6 -> 0 | E25: ='Delivery & Receipt'!C6 -> 0 | F25: ='Delivery & Receipt'!D6 -> 13 | G25: ='Delivery & Receipt'!E6 -> 0 | H25: ='Delivery & Receipt'!B4 -> 13
B26: 16 | C26: Complaints & Refunds | D26: ='Complaints & Refunds'!B6 -> 0 | E26: ='Complaints & Refunds'!C6 -> 0 | F26: ='Complaints & Refunds'!D6 -> 15 | G26: ='Complaints & Refunds'!E6 -> 0 | H26: ='Complaints & Refunds'!B4 -> 15
B27: 17 | C27: Payments & Receivables | D27: ='Payments & Receivables'!B6 -> 0 | E27: ='Payments & Receivables'!C6 -> 0 | F27: ='Payments & Receivables'!D6 -> 14 | G27: ='Payments & Receivables'!E6 -> 0 | H27: ='Payments & Receivables'!B4 -> 14
B28: 18 | C28: Loyalty Management | D28: ='Loyalty Management'!B6 -> 0 | E28: ='Loyalty Management'!C6 -> 0 | F28: ='Loyalty Management'!D6 -> 15 | G28: ='Loyalty Management'!E6 -> 0 | H28: ='Loyalty Management'!B4 -> 15
B29: 19 | C29: Territory & Sales Groups | D29: ='Territory & Sales Groups'!B6 -> 0 | E29: ='Territory & Sales Groups'!C6 -> 0 | F29: ='Territory & Sales Groups'!D6 -> 3 | G29: ='Territory & Sales Groups'!E6 -> 0 | H29: ='Territory & Sales Groups'!B4 -> 3
B30: 20 | C30: Sales Reporting | D30: ='Sales Reporting'!B6 -> 0 | E30: ='Sales Reporting'!C6 -> 0 | F30: ='Sales Reporting'!D6 -> 6 | G30: ='Sales Reporting'!E6 -> 0 | H30: ='Sales Reporting'!B4 -> 6
B31: 21 | C31: Configuration & Notifications | D31: ='Configuration & Notifications'!B6 -> 0 | E31: ='Configuration & Notifications'!C6 -> 0 | F31: ='Configuration & Notifications'!D6 -> 9 | G31: ='Configuration & Notifications'!E6 -> 0 | H31: ='Configuration & Notifications'!B4 -> 9
B32: 22 | C32: Main Workflows | D32: ='Main Workflows'!B6 -> 0 | E32: ='Main Workflows'!C6 -> 0 | F32: ='Main Workflows'!D6 -> 8 | G32: ='Main Workflows'!E6 -> 0 | H32: ='Main Workflows'!B4 -> 8
B33: 23 | C33: State Transitions | D33: ='State Transitions'!B6 -> 0 | E33: ='State Transitions'!C6 -> 0 | F33: ='State Transitions'!D6 -> 20 | G33: ='State Transitions'!E6 -> 0 | H33: ='State Transitions'!B4 -> 20
B34: 24 | C34: Non-Functional Tests | D34: ='Non-Functional Tests'!B6 -> 0 | E34: ='Non-Functional Tests'!C6 -> 0 | F34: ='Non-Functional Tests'!D6 -> 20 | G34: ='Non-Functional Tests'!E6 -> 0 | H34: ='Non-Functional Tests'!B4 -> 20
C35: Sub total | D35: =SUM(D11:D34) -> 0 | E35: =SUM(E11:E34) -> 0 | F35: =SUM(F11:F34) -> 271 | G35: =SUM(G11:G34) -> 0 | H35: =SUM(H11:H34) -> 271
C37: Test coverage | E37: =IFERROR((D35+E35)/(H35-G35)*100,0) -> 0 | F37: %
C38: Test successful coverage | E38: =IFERROR(D35/(H35-G35)*100,0) -> 0 | F38: %

Sheet Test Cases
D1: TEST CASE LIST — FSCM v1.3
B3: Project Name | D3: FSCM – Short Shelf-Life FMCG Supply Chain Management and Distribution Coordination
B4: Project Code | D4: FA26SE083
B5: Test Environment Setup Description | D5: ASP.NET Core .NET 10, React, Flutter, approved API contracts, PostgreSQL staging. Main Flows F1–F5 reference fixtures (P1/C1/P2/SHORT); no fake execution results. Cutoff 00:00 ICT; percentage-only tiers; 1 point per 10,000 VND.
B8: No | C8: Function Name | D8: Sheet Name | E8: Description | F8: Pre-Condition
B9: 1 | C9: Login with system account | D9: Authentication | E9: 3 test case(s): Boundary, Negative, Positive. Example expected outcome: Issue access/refresh tokens and return authorized scope | F9: Test environment seeded; authorized All roles; transaction isolated and resettable.
B10: 2 | C10: Refresh and revoke session | D10: Authentication | E10: 3 test case(s): Boundary, Negative, Positive. Example expected outcome: Rotate token and revoke predecessor | F10: Test environment seeded; authorized All roles; transaction isolated and resettable.
B11: 3 | C11: Role and data-scope authorization | D11: Authentication | E11: 3 test case(s): Boundary, Negative, Positive. Example expected outcome: Return authorized records only | F11: Test environment seeded; authorized All roles; transaction isolated and resettable.
B12: 4 | C12: Administrator user management | D12: User Management | E12: 3 test case(s): Boundary, Negative, Positive. Example expected outcome: Create a non-admin account with traceability | F12: Test environment seeded; authorized Administrator; transaction isolated and resettable.
B13: 5 | C13: Declare retailer and assessment | D13: Retailer Registration | E13: 3 test case(s): Boundary, Negative, Positive. Example expected outcome: Create pending retailer declaration | F13: Test environment seeded; authorized Sales; Operator; transaction isolated and resettable.
B14: 6 | C14: Review retailer activation | D14: Retailer Registration | E14: 3 test case(s): Boundary, Negative, Positive. Example expected outcome: Assign active status and business code | F14: Test environment seeded; authorized Administrator; transaction isolated and resettable.
B15: 7 | C15: Manage retailer profile and MLOR | D15: Retailer Profiles | E15: 3 test case(s): Boundary, Negative, Positive. Example expected outcome: Save new version and retain history | F15: Test environment seeded; authorized Administrator; transaction isolated and resettable.
B16: 8 | C16: Manage category hierarchy | D16: Product & Categories | E16: 3 test case(s): Boundary, Negative, Positive. Example expected outcome: Persist valid non-cyclic hierarchy | F16: Test environment seeded; authorized Administrator; transaction isolated and resettable.
B17: 9 | C17: Create and publish product | D17: Product & Categories | E17: Administrator AND Operator create Draft, price, publish SKU; Published data immutable; Sales cannot write. | F17: Test environment seeded; authorized Administrator; transaction isolated and resettable.
B18: 10 | C18: Product search and catalog visibility | D18: Product & Categories | E18: 3 test case(s): Boundary, Negative, Positive. Example expected outcome: Return only permitted published products | F18: Test environment seeded; authorized Sales; Retailer; Administrator; transaction isolated and resettable.
B19: 11 | C19: Manage ordinary promotion | D19: Promotion Management | E19: 3 test case(s): Boundary, Negative, Positive. Example expected outcome: Persist promotion/version with eligibility | F19: Test environment seeded; authorized Administrator; transaction isolated and resettable.
B20: 12 | C20: Calculate shelf-life discount tier | D20: Shelf-Life Pricing | E20: Percentage-only tiers (<100%); reject fixed/zero net price; MLOR before discount; preserve batch snapshot. | F20: Test environment seeded; authorized Administrator; System; transaction isolated and resettable.
... B180: 172 | C180: R5-TC-NFR-08 — Algorithm evaluation validity | D180: Non-Functional Tests | E180: Priority P1 | SRS v1.8 §4 NFR-D06; R5-11; M12/WF04/TS02 Expected: Report complete/short, near-expiry quantity, mean distance, warehouses/order, runtime; zero invalid allocations; no optimality claim. | F180: Two evaluators consume exact same eligible snapshot and priority. Data: Seeds with close-to-expiry units, different distances.

Sheet Authentication
A2: Feature | B2: Authentication | R2: Passed
A3: Test requirement | B3: Verify account login and refresh-token lifecycle for FSCM roles: valid credentials issue scoped sessions; repeated invalid attempts trigger lockout; revoked or reused tokens cannot create extra sessions; deactivated users and cross-territory requests are denied. | R3: Failed
A4: Number of TCs | B4: =COUNTA(A12:A22) -> 11 | R4: Pending
A5: Testing Round | B5: Passed | C5: Failed | D5: Pending | E5: N/A | R5: N/A
A6: Round 1 | B6: =COUNTIF(F12:F22,"Passed")+COUNTIF(F12:F22,"Pass") -> 0 | C6: =COUNTIF(F12:F22,"Failed")+COUNTIF(F12:F22,"Fail") -> 0 | D6: =COUNTIF(F12:F22,"Not Run")+COUNTIF(F12:F22,"Blocked")+COUNTIF(F12:F22,"Pending")+COUNTBLANK(F12:F22) -> 11 | E6: =COUNTIF(F12:F22,"N/A") -> 0
A7: Round 2 | B7: =COUNTIF(I12:I22,"Passed")+COUNTIF(I12:I22,"Pass") -> 0 | C7: =COUNTIF(I12:I22,"Failed")+COUNTIF(I12:I22,"Fail") -> 0 | D7: =COUNTIF(I12:I22,"Not Run")+COUNTIF(I12:I22,"Blocked")+COUNTIF(I12:I22,"Pending") -> 0 | E7: =COUNTIF(I12:I22,"N/A") -> 0
A8: Round 3 | B8: =COUNTIF(L12:L22,"Passed")+COUNTIF(L12:L22,"Pass") -> 0 | C8: =COUNTIF(L12:L22,"Failed")+COUNTIF(L12:L22,"Fail") -> 0 | D8: =COUNTIF(L12:L22,"Not Run")+COUNTIF(L12:L22,"Blocked")+COUNTIF(L12:L22,"Pending") -> 0 | E8: =COUNTIF(L12:L22,"N/A") -> 0
A10: Test Case ID | B10: Test Case Description | C10: Test Case Procedure | D10: Expected Results | E10: Pre-conditions | F10: Round 1 | G10: Test date | H10: Tester | I10: Round 2 | J10: Test date | K10: Tester | L10: Round 3 | M10: Test date | N10: Tester | O10: Note
A11: Authentication — FSCM scenarios
A12: FT-001-P | B12: Login with system account Positive — Active user and valid password | C12: 1. Seed isolated FSCM fixture with required SKU, retailer, warehouse, roles and state; record starting stock/payment/ledger snapshots. 2. Sign in as All roles; perform scenario: Active user and valid password. 3. Submit both the valid operation and the specified invalid/boundary input. 4. Compare response, persisted state, actor audit, once-only effects and unchanged records against the expected result. | D12: Issue access/refresh tokens and return authorized scope | E12: Test environment seeded; authorized All roles; transaction isolated and resettable. | F12: Not Run | O12: Type: Positive; Role: All roles; Level: System / Integration SRS v1.8 / BR: 3.2.1; BR-01–03 Test data: Active user and valid password Source: https://github.com/GFA26SE63/FSCM-Backend/blob/0f56f7099f07aa60d76673e6b6a57a2b606fb833/src/FSCM.API/Controllers/AuthController.cs Automation: Manual / candidate Version: 1.3; Actual result: —; Evidence: —
A13: FT-001-N | B13: Login with system account Negative — Incorrect password, five attempts | C13: 1. Seed isolated FSCM fixture with required SKU, retailer, warehouse, roles and state; record starting stock/payment/ledger snapshots. 2. Sign in as All roles; perform scenario: Incorrect password, five attempts. 3. Submit both the valid operation and the specified invalid/boundary input. 4. Compare response, persisted state, actor audit, once-only effects and unchanged records against the expected result. | D13: Reject credentials without session and enforce lockout | E13: Test environment seeded; authorized All roles; transaction isolated and resettable. | F13: Not Run | O13: Type: Negative; Role: All roles; Level: System / Integration SRS v1.8 / BR: 3.2.1; BR-01–03 Test data: Incorrect password, five attempts Source: https://github.com/GFA26SE63/FSCM-Backend/blob/0f56f7099f07aa60d76673e6b6a57a2b606fb833/src/FSCM.API/Controllers/AuthController.cs Automation: Manual / candidate Version: 1.3; Actual result: —; Evidence: —
A14: FT-001-B | B14: Login with system account Boundary — Account locked until expiry | C14: 1. Seed isolated FSCM fixture with required SKU, retailer, warehouse, roles and state; record starting stock/payment/ledger snapshots. 2. Sign in as All roles; perform scenario: Account locked until expiry. 3. Submit both the valid operation and the specified invalid/boundary input. 4. Compare response, persisted state, actor audit, once-only effects and unchanged records against the expected result. | D14: Do not allow login while locked; allow only after expiry | E14: Test environment seeded; authorized All roles; transaction isolated and resettable. | F14: Not Run | O14: Type: Boundary; Role: All roles; Level: System / Integration SRS v1.8 / BR: 3.2.1; BR-01–03 Test data: Account locked until expiry Source: https://github.com/GFA26SE63/FSCM-Backend/blob/0f56f7099f07aa60d76673e6b6a57a2b606fb833/src/FSCM.API/Controllers/AuthController.cs Automation: Manual / candidate Version: 1.3; Actual result: —; Evidence: —
A15: FT-002-P | B15: Refresh and revoke session Positive — Valid active refresh token | C15: 1. Seed isolated FSCM fixture with required SKU, retailer, warehouse, roles and state; record starting stock/payment/ledger snapshots. 2. Sign in as All roles; perform scenario: Valid active refresh token. 3. Submit both the valid operation and the specified invalid/boundary input. 4. Compare response, persisted state, actor audit, once-only effects and unchanged records against the expected result. | D15: Rotate token and revoke predecessor | E15: Test environment seeded; authorized All roles; transaction isolated and resettable. | F15: Not Run | O15: Type: Positive; Role: All roles; Level: System / Integration SRS v1.8 / BR: 3.2.1; NFR Security Test data: Valid active refresh token Source: https://github.com/GFA26SE63/FSCM-Backend/blob/0f56f7099f07aa60d76673e6b6a57a2b606fb833/src/FSCM.Application/Features/Identity/IdentityService.cs Automation: Manual / candidate Version: 1.3; Actual result: —; Evidence: —
A16: FT-002-N | B16: Refresh and revoke session Negative — Revoked refresh token | C16: 1. Seed isolated FSCM fixture with required SKU, retailer, warehouse, roles and state; record starting stock/payment/ledger snapshots. 2. Sign in as All roles; perform scenario: Revoked refresh token. 3. Submit both the valid operation and the specified invalid/boundary input. 4. Compare response, persisted state, actor audit, once-only effects and unchanged records against the expected result. | D16: Deny invalid/revoked token | E16: Test environment seeded; authorized All roles; transaction isolated and resettable. | F16: Not Run | O16: Type: Negative; Role: All roles; Level: System / Integration SRS v1.8 / BR: 3.2.1; NFR Security Test data: Revoked refresh token Source: https://github.com/GFA26SE63/FSCM-Backend/blob/0f56f7099f07aa60d76673e6b6a57a2b606fb833/src/FSCM.Application/Features/Identity/IdentityService.cs Automation: Manual / candidate Version: 1.3; Actual result: —; Evidence: —
A17: FT-002-B | B17: Refresh and revoke session Boundary — Reuse recently rotated refresh token | C17: 1. Seed isolated FSCM fixture with required SKU, retailer, warehouse, roles and state; record starting stock/payment/ledger snapshots. 2. Sign in as All roles; perform scenario: Reuse recently rotated refresh token. 3. Submit both the valid operation and the specified invalid/boundary input. 4. Compare response, persisted state, actor audit, once-only effects and unchanged records against the expected result. | D17: Never issue second active session from a revoked predecessor | E17: Test environment seeded; authorized All roles; transaction isolated and resettable. | F17: Not Run | O17: Type: Boundary; Role: All roles; Level: System / Integration SRS v1.8 / BR: 3.2.1; NFR Security Test data: Reuse recently rotated refresh token Source: https://github.com/GFA26SE63/FSCM-Backend/blob/0f56f7099f07aa60d76673e6b6a57a2b606fb833/src/FSCM.Application/Features/Identity/IdentityService.cs Automation: Manual / candidate Version: 1.3; Actual result: —; Evidence: —
A18: FT-003-P | B18: Role and data-scope authorization Positive — Sales reads assigned retailer orders | C18: 1. Seed isolated FSCM fixture with required SKU, retailer, warehouse, roles and state; record starting stock/payment/ledger snapshots. 2. Sign in as All roles; perform scenario: Sales reads assigned retailer orders. 3. Submit both the valid operation and the specified invalid/boundary input. 4. Compare response, persisted state, actor audit, once-only effects and unchanged records against the expected result. | D18: Return authorized records only | E18: Test environment seeded; authorized All roles; transaction isolated and resettable. | F18: Not Run | O18: Type: Positive; Role: All roles; Level: System / Integration SRS v1.8 / BR: BR-01–04 Test data: Sales reads assigned retailer orders Source: https://github.com/GFA26SE63/FSCM-Backend/blob/0f56f7099f07aa60d76673e6b6a57a2b606fb833/src/FSCM.API/Security/ActiveAccountClaimsTransformation.cs Automation: Manual / candidate Version: 1.3; Actual result: —; Evidence: —
A19: FT-003-N | B19: Role and data-scope authorization Negative — Sales reads another territory's order | C19: 1. Seed isolated FSCM fixture with required SKU, retailer, warehouse, roles and state; record starting stock/payment/ledger snapshots. 2. Sign in as All roles; perform scenario: Sales reads another territory's order. 3. Submit both the valid operation and the specified invalid/boundary input. 4. Compare response, persisted state, actor audit, once-only effects and unchanged records against the expected result. | D19: Return forbidden/not-found without leaking data | E19: Test environment seeded; authorized All roles; transaction isolated and resettable. | F19: Not Run | O19: Type: Negative; Role: All roles; Level: System / Integration SRS v1.8 / BR: BR-01–04 Test data: Sales reads another territory's order Source: https://github.com/GFA26SE63/FSCM-Backend/blob/0f56f7099f07aa60d76673e6b6a57a2b606fb833/src/FSCM.API/Security/ActiveAccountClaimsTransformation.cs Automation: Manual / candidate Version: 1.3; Actual result: —; Evidence: —
A20: FT-003-B | B20: Role and data-scope authorization Boundary — Deactivated account uses existing JWT | C20: 1. Seed isolated FSCM fixture with required SKU, retailer, warehouse, roles and state; record starting stock/payment/ledger snapshots. 2. Sign in as All roles; perform scenario: Deactivated account uses existing JWT. 3. Submit both the valid operation and the specified invalid/boundary input. 4. Compare response, persisted state, actor audit, once-only effects and unchanged records against the expected result. | D20: Re-evaluate active status and scope per request | E20: Test environment seeded; authorized All roles; transaction isolated and resettable. | F20: Not Run | O20: Type: Boundary; Role: All roles; Level: System / Integration SRS v1.8 / BR: BR-01–04 Test data: Deactivated account uses existing JWT Source: https://github.com/GFA26SE63/FSCM-Backend/blob/0f56f7099f07aa60d76673e6b6a57a2b606fb833/src/FSCM.API/Security/ActiveAccountClaimsTransformation.cs Automation: Manual / candidate Version: 1.3; Actual result: —; Evidence: —
A21: R5-TC-AUTH-01 | B21: Valid account and scoped role | C21: 1. Login; 2. Query own orders; 3. Query another group. | D21: Token carries active scope; own read succeeds; cross-scope query forbidden. | E21: Active user in assigned area; seeded role. Test data: Sales account, valid password, other-group retailer. | F21: Not Run | O21: Requirement/Traceability: SRS v1.8 §3.2.1; BR-01/03; AC-3.2.1-01; M01/WF01/TS01 Priority: P1; Level: Integration / System / Acceptance Version: 1.3; Actual result: —; Evidence: —
A22: R5-TC-AUTH-02 | B22: Invalid credentials and session reuse | C22: 1. Attempt invalid login; 2. Reuse rotated token; 3. Retry protected read. | D22: Invalid login denied; reuse rejected/revoked per policy; no data leak. | E22: Account and refresh tokens exist. Test data: Wrong password; revoked/rotated refresh token. | F22: Not Run | O22: Requirement/Traceability: SRS v1.8 §3.2.1; AC-3.2.1-02; M01/WF01/TS02 Priority: P1; Level: Integration / System / Acceptance Version: 1.3; Actual result: —; Evidence: —

Sheet User Management
A2: Feature | B2: User Management | R2: Passed
A3: Test requirement | B3: Verify Administrator user management permits creation of authorized non-admin accounts with audit history, while blocking creation of additional Administrator accounts and unauthorized promotion of existing users to Administrator. | R3: Failed
A4: Number of TCs | B4: =COUNTA(A12:A14) -> 3 | R4: Pending
A5: Testing Round | B5: Passed | C5: Failed | D5: Pending | E5: N/A | R5: N/A
A6: Round 1 | B6: =COUNTIF(F12:F14,"Passed")+COUNTIF(F12:F14,"Pass") -> 0 | C6: =COUNTIF(F12:F14,"Failed")+COUNTIF(F12:F14,"Fail") -> 0 | D6: =COUNTIF(F12:F14,"Not Run")+COUNTIF(F12:F14,"Blocked")+COUNTIF(F12:F14,"Pending")+COUNTBLANK(F12:F14) -> 3 | E6: =COUNTIF(F12:F14,"N/A") -> 0
A7: Round 2 | B7: =COUNTIF(I12:I14,"Passed")+COUNTIF(I12:I14,"Pass") -> 0 | C7: =COUNTIF(I12:I14,"Failed")+COUNTIF(I12:I14,"Fail") -> 0 | D7: =COUNTIF(I12:I14,"Not Run")+COUNTIF(I12:I14,"Blocked")+COUNTIF(I12:I14,"Pending") -> 0 | E7: =COUNTIF(I12:I14,"N/A") -> 0
A8: Round 3 | B8: =COUNTIF(L12:L14,"Passed")+COUNTIF(L12:L14,"Pass") -> 0 | C8: =COUNTIF(L12:L14,"Failed")+COUNTIF(L12:L14,"Fail") -> 0 | D8: =COUNTIF(L12:L14,"Not Run")+COUNTIF(L12:L14,"Blocked")+COUNTIF(L12:L14,"Pending") -> 0 | E8: =COUNTIF(L12:L14,"N/A") -> 0
A10: Test Case ID | B10: Test Case Description | C10: Test Case Procedure | D10: Expected Results | E10: Pre-conditions | F10: Round 1 | G10: Test date | H10: Tester | I10: Round 2 | J10: Test date | K10: Tester | L10: Round 3 | M10: Test date | N10: Tester | O10: Note
A11: User Management — FSCM scenarios
A12: FT-004-P | B12: Administrator user management Positive — Create permitted Sales user | C12: 1. Seed isolated FSCM fixture with required SKU, retailer, warehouse, roles and state; record starting stock/payment/ledger snapshots. 2. Sign in as Administrator; perform scenario: Create permitted Sales user. 3. Submit both the valid operation and the specified invalid/boundary input. 4. Compare response, persisted state, actor audit, once-only effects and unchanged records against the expected result. | D12: Create a non-admin account with traceability | E12: Test environment seeded; authorized Administrator; transaction isolated and resettable. | F12: Not Run | O12: Type: Positive; Role: Administrator; Level: System / Integration SRS v1.8 / BR: 3.2.3; BR-02 Test data: Create permitted Sales user Source: https://github.com/GFA26SE63/FSCM-Backend/blob/0f56f7099f07aa60d76673e6b6a57a2b606fb833/src/FSCM.API/Controllers/UsersController.cs Automation: Manual / candidate Version: 1.3; Actual result: —; Evidence: —
A13: FT-004-N | B13: Administrator user management Negative — Create an Administrator through UI/API | C13: 1. Seed isolated FSCM fixture with required SKU, retailer, warehouse, roles and state; record starting stock/payment/ledger snapshots. 2. Sign in as Administrator; perform scenario: Create an Administrator through UI/API. 3. Submit both the valid operation and the specified invalid/boundary input. 4. Compare response, persisted state, actor audit, once-only effects and unchanged records against the expected result. | D13: Deny prohibited privileged account creation | E13: Test environment seeded; authorized Administrator; transaction isolated and resettable. | F13: Not Run | O13: Type: Negative; Role: Administrator; Level: System / Integration SRS v1.8 / BR: 3.2.3; BR-02 Test data: Create an Administrator through UI/API Source: https://github.com/GFA26SE63/FSCM-Backend/blob/0f56f7099f07aa60d76673e6b6a57a2b606fb833/src/FSCM.API/Controllers/UsersController.cs Automation: Manual / candidate Version: 1.3; Actual result: —; Evidence: —
A14: FT-004-B | B14: Administrator user management Boundary — Promote existing user to Administrator | C14: 1. Seed isolated FSCM fixture with required SKU, retailer, warehouse, roles and state; record starting stock/payment/ledger snapshots. 2. Sign in as Administrator; perform scenario: Promote existing user to Administrator. 3. Submit both the valid operation and the specified invalid/boundary input. 4. Compare response, persisted state, actor audit, once-only effects and unchanged records against the expected result. | D14: Deny administrator-role escalation even through update | E14: Test environment seeded; authorized Administrator; transaction isolated and resettable. | F14: Not Run | O14: Type: Boundary; Role: Administrator; Level: System / Integration SRS v1.8 / BR: 3.2.3; BR-02 Test data: Promote existing user to Administrator Source: https://github.com/GFA26SE63/FSCM-Backend/blob/0f56f7099f07aa60d76673e6b6a57a2b606fb833/src/FSCM.API/Controllers/UsersController.cs Automation: Manual / candidate Version: 1.3; Actual result: —; Evidence: —

Sheet Retailer Registration
A2: Feature | B2: Retailer Registration | R2: Passed
A3: Test requirement | B3: Verify retailer declarations capture mandatory assessment data and remain Pending until authorized review. Detect duplicate stores, require review reasons, issue an 8-digit code on approval, and permit deferred terms only when currently approved. | R3: Failed
A4: Number of TCs | B4: =COUNTA(A12:A19) -> 8 | R4: Pending
A5: Testing Round | B5: Passed | C5: Failed | D5: Pending | E5: N/A | R5: N/A
A6: Round 1 | B6: =COUNTIF(F12:F19,"Passed")+COUNTIF(F12:F19,"Pass") -> 0 | C6: =COUNTIF(F12:F19,"Failed")+COUNTIF(F12:F19,"Fail") -> 0 | D6: =COUNTIF(F12:F19,"Not Run")+COUNTIF(F12:F19,"Blocked")+COUNTIF(F12:F19,"Pending")+COUNTBLANK(F12:F19) -> 8 | E6: =COUNTIF(F12:F19,"N/A") -> 0
A7: Round 2 | B7: =COUNTIF(I12:I19,"Passed")+COUNTIF(I12:I19,"Pass") -> 0 | C7: =COUNTIF(I12:I19,"Failed")+COUNTIF(I12:I19,"Fail") -> 0 | D7: =COUNTIF(I12:I19,"Not Run")+COUNTIF(I12:I19,"Blocked")+COUNTIF(I12:I19,"Pending") -> 0 | E7: =COUNTIF(I12:I19,"N/A") -> 0
A8: Round 3 | B8: =COUNTIF(L12:L19,"Passed")+COUNTIF(L12:L19,"Pass") -> 0 | C8: =COUNTIF(L12:L19,"Failed")+COUNTIF(L12:L19,"Fail") -> 0 | D8: =COUNTIF(L12:L19,"Not Run")+COUNTIF(L12:L19,"Blocked")+COUNTIF(L12:L19,"Pending") -> 0 | E8: =COUNTIF(L12:L19,"N/A") -> 0
A10: Test Case ID | B10: Test Case Description | C10: Test Case Procedure | D10: Expected Results | E10: Pre-conditions | F10: Round 1 | G10: Test date | H10: Tester | I10: Round 2 | J10: Test date | K10: Tester | L10: Round 3 | M10: Test date | N10: Tester | O10: Note
A11: Retailer Registration — FSCM scenarios
A12: FT-005-P | B12: Declare retailer and assessment Positive — Complete prospect data and assessment | C12: 1. Seed isolated FSCM fixture with required SKU, retailer, warehouse, roles and state; record starting stock/payment/ledger snapshots. 2. Sign in as Sales; Operator; perform scenario: Complete prospect data and assessment. 3. Submit both the valid operation and the specified invalid/boundary input. 4. Compare response, persisted state, actor audit, once-only effects and unchanged records against the expected result. | D12: Create pending retailer declaration | E12: Test environment seeded; authorized Sales; Operator; transaction isolated and resettable. | F12: Not Run | O12: Type: Positive; Role: Sales; Operator; Level: System / Integration SRS v1.8 / BR: 3.3.1; BR-12 Test data: Complete prospect data and assessment Source: https://github.com/GFA26SE63/FSCM-Backend/blob/0f56f7099f07aa60d76673e6b6a57a2b606fb833/src/FSCM.API/Controllers/RetailersController.cs Automation: Manual / candidate Version: 1.3; Actual result: —; Evidence: —
A13: FT-005-N | B13: Declare retailer and assessment Negative — Duplicate store declaration | C13: 1. Seed isolated FSCM fixture with required SKU, retailer, warehouse, roles and state; record starting stock/payment/ledger snapshots. 2. Sign in as Sales; Operator; perform scenario: Duplicate store declaration. 3. Submit both the valid operation and the specified invalid/boundary input. 4. Compare response, persisted state, actor audit, once-only effects and unchanged records against the expected result. | D13: Detect duplicate and avoid new retailer | E13: Test environment seeded; authorized Sales; Operator; transaction isolated and resettable. | F13: Not Run | O13: Type: Negative; Role: Sales; Operator; Level: System / Integration SRS v1.8 / BR: 3.3.1; BR-12 Test data: Duplicate store declaration Source: https://github.com/GFA26SE63/FSCM-Backend/blob/0f56f7099f07aa60d76673e6b6a57a2b606fb833/src/FSCM.API/Controllers/RetailersController.cs Automation: Manual / candidate Version: 1.3; Actual result: —; Evidence: —
A14: FT-005-B | B14: Declare retailer and assessment Boundary — Missing mandatory assessment field | C14: 1. Seed isolated FSCM fixture with required SKU, retailer, warehouse, roles and state; record starting stock/payment/ledger snapshots. 2. Sign in as Sales; Operator; perform scenario: Missing mandatory assessment field. 3. Submit both the valid operation and the specified invalid/boundary input. 4. Compare response, persisted state, actor audit, once-only effects and unchanged records against the expected result. | D14: Validate required fields; do not silently activate | E14: Test environment seeded; authorized Sales; Operator; transaction isolated and resettable. | F14: Not Run | O14: Type: Boundary; Role: Sales; Operator; Level: System / Integration SRS v1.8 / BR: 3.3.1; BR-12 Test data: Missing mandatory assessment field Source: https://github.com/GFA26SE63/FSCM-Backend/blob/0f56f7099f07aa60d76673e6b6a57a2b606fb833/src/FSCM.API/Controllers/RetailersController.cs Automation: Manual / candidate Version: 1.3; Actual result: —; Evidence: —
A15: FT-006-P | B15: Review retailer activation Positive — Approve pending retailer with reason | C15: 1. Seed isolated FSCM fixture with required SKU, retailer, warehouse, roles and state; record starting stock/payment/ledger snapshots. 2. Sign in as Administrator; perform scenario: Approve pending retailer with reason. 3. Submit both the valid operation and the specified invalid/boundary input. 4. Compare response, persisted state, actor audit, once-only effects and unchanged records against the expected result. | D15: Assign active status and business code | E15: Test environment seeded; authorized Administrator; transaction isolated and resettable. | F15: Not Run | O15: Type: Positive; Role: Administrator; Level: System / Integration SRS v1.8 / BR: 3.3.2; BR-12 Test data: Approve pending retailer with reason Source: https://github.com/GFA26SE63/FSCM-Backend/blob/0f56f7099f07aa60d76673e6b6a57a2b606fb833/src/FSCM.Application/Features/Retailers/RetailerService.cs Automation: Manual / candidate Version: 1.3; Actual result: —; Evidence: —
A16: FT-006-N | B16: Review retailer activation Negative — Unauthorized reviewer attempts approval | C16: 1. Seed isolated FSCM fixture with required SKU, retailer, warehouse, roles and state; record starting stock/payment/ledger snapshots. 2. Sign in as Administrator; perform scenario: Unauthorized reviewer attempts approval. 3. Submit both the valid operation and the specified invalid/boundary input. 4. Compare response, persisted state, actor audit, once-only effects and unchanged records against the expected result. | D16: Reject unauthorized approval | E16: Test environment seeded; authorized Administrator; transaction isolated and resettable. | F16: Not Run | O16: Type: Negative; Role: Administrator; Level: System / Integration SRS v1.8 / BR: 3.3.2; BR-12 Test data: Unauthorized reviewer attempts approval Source: https://github.com/GFA26SE63/FSCM-Backend/blob/0f56f7099f07aa60d76673e6b6a57a2b606fb833/src/FSCM.Application/Features/Retailers/RetailerService.cs Automation: Manual / candidate Version: 1.3; Actual result: —; Evidence: —
A17: FT-006-B | B17: Review retailer activation Boundary — Rejection without reason | C17: 1. Seed isolated FSCM fixture with required SKU, retailer, warehouse, roles and state; record starting stock/payment/ledger snapshots. 2. Sign in as Administrator; perform scenario: Rejection without reason. 3. Submit both the valid operation and the specified invalid/boundary input. 4. Compare response, persisted state, actor audit, once-only effects and unchanged records against the expected result. | D17: Keep rejection reason mandatory and preserve review trail | E17: Test environment seeded; authorized Administrator; transaction isolated and resettable. | F17: Not Run | O17: Type: Boundary; Role: Administrator; Level: System / Integration SRS v1.8 / BR: 3.3.2; BR-12 Test data: Rejection without reason Source: https://github.com/GFA26SE63/FSCM-Backend/blob/0f56f7099f07aa60d76673e6b6a57a2b606fb833/src/FSCM.Application/Features/Retailers/RetailerService.cs Automation: Manual / candidate Version: 1.3; Actual result: —; Evidence: —
A18: R5-TC-RET-01 | B18: Retailer declared and approved | C18: 1. Submit declaration; 2. Admin approves; 3. Inspect code and scope. | D18: Pending→Active only under Admin approval; assigned 8-digit code and scoped account. | E18: Assigned Sales; pending Retailer. Test data: Store identity, MLOR and evidence, approval actor. | F18: Not Run | O18: Requirement/Traceability: SRS v1.8 §3.3.1–3.3.2; AC-3.3.2-01; M02/WF01/TS01 Priority: P1; Level: Integration / System / Acceptance Version: 1.3; Actual result: —; Evidence: —
A19: R5-TC-RET-02 | B19: Retailer term scope and validation | C19: 1. Request Deferred; 2. Change term version; 3. Attempt with invalid term. | D19: Only approved, currently valid term allows Deferred; otherwise rejected. | E19: Retailers with/without approved versioned credit terms. Test data: Term valid/expired/unapproved. | F19: Not Run | O19: Requirement/Traceability: SRS v1.8 §3.3.3, §3.10.1; BR-51/73; M02/WF02/TS01 Priority: P1; Level: Integration / System / Acceptance Version: 1.3; Actual result: —; Evidence: —

Sheet Retailer Profiles
A2: Feature | B2: Retailer Profiles | R2: Passed
A3: Test requirement | B3: Verify authorized retailer profile and versioned shelf-life requirement updates. Reject invalid MLOR ratios and resolve the effective requirement in order of SKU, Category, then product default without losing prior policy history. | R3: Failed
A4: Number of TCs | B4: =COUNTA(A12:A14) -> 3 | R4: Pending
A5: Testing Round | B5: Passed | C5: Failed | D5: Pending | E5: N/A | R5: N/A
A6: Round 1 | B6: =COUNTIF(F12:F14,"Passed")+COUNTIF(F12:F14,"Pass") -> 0 | C6: =COUNTIF(F12:F14,"Failed")+COUNTIF(F12:F14,"Fail") -> 0 | D6: =COUNTIF(F12:F14,"Not Run")+COUNTIF(F12:F14,"Blocked")+COUNTIF(F12:F14,"Pending")+COUNTBLANK(F12:F14) -> 3 | E6: =COUNTIF(F12:F14,"N/A") -> 0
A7: Round 2 | B7: =COUNTIF(I12:I14,"Passed")+COUNTIF(I12:I14,"Pass") -> 0 | C7: =COUNTIF(I12:I14,"Failed")+COUNTIF(I12:I14,"Fail") -> 0 | D7: =COUNTIF(I12:I14,"Not Run")+COUNTIF(I12:I14,"Blocked")+COUNTIF(I12:I14,"Pending") -> 0 | E7: =COUNTIF(I12:I14,"N/A") -> 0
A8: Round 3 | B8: =COUNTIF(L12:L14,"Passed")+COUNTIF(L12:L14,"Pass") -> 0 | C8: =COUNTIF(L12:L14,"Failed")+COUNTIF(L12:L14,"Fail") -> 0 | D8: =COUNTIF(L12:L14,"Not Run")+COUNTIF(L12:L14,"Blocked")+COUNTIF(L12:L14,"Pending") -> 0 | E8: =COUNTIF(L12:L14,"N/A") -> 0
A10: Test Case ID | B10: Test Case Description | C10: Test Case Procedure | D10: Expected Results | E10: Pre-conditions | F10: Round 1 | G10: Test date | H10: Tester | I10: Round 2 | J10: Test date | K10: Tester | L10: Round 3 | M10: Test date | N10: Tester | O10: Note
A11: Retailer Profiles — FSCM scenarios
A12: FT-007-P | B12: Manage retailer profile and MLOR Positive — Update permitted retailer/category/SKU MLOR | C12: 1. Seed isolated FSCM fixture with required SKU, retailer, warehouse, roles and state; record starting stock/payment/ledger snapshots. 2. Sign in as Administrator; perform scenario: Update permitted retailer/category/SKU MLOR. 3. Submit both the valid operation and the specified invalid/boundary input. 4. Compare response, persisted state, actor audit, once-only effects and unchanged records against the expected result. | D12: Save new version and retain history | E12: Test environment seeded; authorized Administrator; transaction isolated and resettable. | F12: Not Run | O12: Type: Positive; Role: Administrator; Level: System / Integration SRS v1.8 / BR: 3.3.3; 3.7.4 Test data: Update permitted retailer/category/SKU MLOR Source: https://github.com/GFA26SE63/FSCM-Backend/blob/0f56f7099f07aa60d76673e6b6a57a2b606fb833/src/FSCM.API/Controllers/MlorConfigurationsController.cs Automation: Manual / candidate Version: 1.3; Actual result: —; Evidence: —
A13: FT-007-N | B13: Manage retailer profile and MLOR Negative — Ratio less than or equal to zero | C13: 1. Seed isolated FSCM fixture with required SKU, retailer, warehouse, roles and state; record starting stock/payment/ledger snapshots. 2. Sign in as Administrator; perform scenario: Ratio less than or equal to zero. 3. Submit both the valid operation and the specified invalid/boundary input. 4. Compare response, persisted state, actor audit, once-only effects and unchanged records against the expected result. | D13: Reject invalid ratio | E13: Test environment seeded; authorized Administrator; transaction isolated and resettable. | F13: Not Run | O13: Type: Negative; Role: Administrator; Level: System / Integration SRS v1.8 / BR: 3.3.3; 3.7.4 Test data: Ratio less than or equal to zero Source: https://github.com/GFA26SE63/FSCM-Backend/blob/0f56f7099f07aa60d76673e6b6a57a2b606fb833/src/FSCM.API/Controllers/MlorConfigurationsController.cs Automation: Manual / candidate Version: 1.3; Actual result: —; Evidence: —
A14: FT-007-B | B14: Manage retailer profile and MLOR Boundary — SKU override and category fallback | C14: 1. Seed isolated FSCM fixture with required SKU, retailer, warehouse, roles and state; record starting stock/payment/ledger snapshots. 2. Sign in as Administrator; perform scenario: SKU override and category fallback. 3. Submit both the valid operation and the specified invalid/boundary input. 4. Compare response, persisted state, actor audit, once-only effects and unchanged records against the expected result. | D14: Use configured precedence and effective version for standard line | E14: Test environment seeded; authorized Administrator; transaction isolated and resettable. | F14: Not Run | O14: Type: Boundary; Role: Administrator; Level: System / Integration SRS v1.8 / BR: 3.3.3; 3.7.4 Test data: SKU override and category fallback Source: https://github.com/GFA26SE63/FSCM-Backend/blob/0f56f7099f07aa60d76673e6b6a57a2b606fb833/src/FSCM.API/Controllers/MlorConfigurationsController.cs Automation: Manual / candidate Version: 1.3; Actual result: —; Evidence: —

Sheet Product & Categories
A2: Feature | B2: Product & Categories | R2: Passed
A3: Test requirement | B3: Confirm Administrator AND Operator can create, price, edit Draft and publish SKU_A / SKU_B, using 100,000/50,000 VND list prices; reject unauthorized edits and modification of Published records. Replacements retain prior batch and sales history. | R3: Failed
A4: Number of TCs | B4: =COUNTA(A12:A21) -> 10 | R4: Pending
A5: Testing Round | B5: Passed | C5: Failed | D5: Pending | E5: N/A | R5: N/A
A6: Round 1 | B6: =COUNTIF(F12:F21,"Passed")+COUNTIF(F12:F21,"Pass") -> 0 | C6: =COUNTIF(F12:F21,"Failed")+COUNTIF(F12:F21,"Fail") -> 0 | D6: =COUNTIF(F12:F21,"Not Run")+COUNTIF(F12:F21,"Blocked")+COUNTIF(F12:F21,"Pending")+COUNTBLANK(F12:F21) -> 10 | E6: =COUNTIF(F12:F21,"N/A") -> 0
A7: Round 2 | B7: =COUNTIF(I12:I21,"Passed")+COUNTIF(I12:I21,"Pass") -> 0 | C7: =COUNTIF(I12:I21,"Failed")+COUNTIF(I12:I21,"Fail") -> 0 | D7: =COUNTIF(I12:I21,"Not Run")+COUNTIF(I12:I21,"Blocked")+COUNTIF(I12:I21,"Pending") -> 0 | E7: =COUNTIF(I12:I21,"N/A") -> 0
A8: Round 3 | B8: =COUNTIF(L12:L21,"Passed")+COUNTIF(L12:L21,"Pass") -> 0 | C8: =COUNTIF(L12:L21,"Failed")+COUNTIF(L12:L21,"Fail") -> 0 | D8: =COUNTIF(L12:L21,"Not Run")+COUNTIF(L12:L21,"Blocked")+COUNTIF(L12:L21,"Pending") -> 0 | E8: =COUNTIF(L12:L21,"N/A") -> 0
A10: Test Case ID | B10: Test Case Description | C10: Test Case Procedure | D10: Expected Results | E10: Pre-conditions | F10: Round 1 | G10: Test date | H10: Tester | I10: Round 2 | J10: Test date | K10: Tester | L10: Round 3 | M10: Test date | N10: Tester | O10: Note
A11: Product & Categories — FSCM scenarios
A12: FT-008-P | B12: Manage category hierarchy Positive — Create child category under parent | C12: 1. Seed isolated FSCM fixture with required SKU, retailer, warehouse, roles and state; record starting stock/payment/ledger snapshots. 2. Sign in as Administrator; perform scenario: Create child category under parent. 3. Submit both the valid operation and the specified invalid/boundary input. 4. Compare response, persisted state, actor audit, once-only effects and unchanged records against the expected result. | D12: Persist valid non-cyclic hierarchy | E12: Test environment seeded; authorized Administrator; transaction isolated and resettable. | F12: Not Run | O12: Type: Positive; Role: Administrator; Level: System / Integration SRS v1.8 / BR: 3.4.1 Test data: Create child category under parent Source: https://github.com/GFA26SE63/FSCM-Backend/blob/0f56f7099f07aa60d76673e6b6a57a2b606fb833/src/FSCM.API/Controllers/CategoriesController.cs Automation: Manual / candidate Version: 1.3; Actual result: —; Evidence: —
A13: FT-008-N | B13: Manage category hierarchy Negative — Select descendant as parent | C13: 1. Seed isolated FSCM fixture with required SKU, retailer, warehouse, roles and state; record starting stock/payment/ledger snapshots. 2. Sign in as Administrator; perform scenario: Select descendant as parent. 3. Submit both the valid operation and the specified invalid/boundary input. 4. Compare response, persisted state, actor audit, once-only effects and unchanged records against the expected result. | D13: Block parent-child cycles | E13: Test environment seeded; authorized Administrator; transaction isolated and resettable. | F13: Not Run | O13: Type: Negative; Role: Administrator; Level: System / Integration SRS v1.8 / BR: 3.4.1 Test data: Select descendant as parent Source: https://github.com/GFA26SE63/FSCM-Backend/blob/0f56f7099f07aa60d76673e6b6a57a2b606fb833/src/FSCM.API/Controllers/CategoriesController.cs Automation: Manual / candidate Version: 1.3; Actual result: —; Evidence: —
A14: FT-008-B | B14: Manage category hierarchy Boundary — Delete parent with active children/products | C14: 1. Seed isolated FSCM fixture with required SKU, retailer, warehouse, roles and state; record starting stock/payment/ledger snapshots. 2. Sign in as Administrator; perform scenario: Delete parent with active children/products. 3. Submit both the valid operation and the specified invalid/boundary input. 4. Compare response, persisted state, actor audit, once-only effects and unchanged records against the expected result. | D14: Preserve dependent children/products on prohibited delete | E14: Test environment seeded; authorized Administrator; transaction isolated and resettable. | F14: Not Run | O14: Type: Boundary; Role: Administrator; Level: System / Integration SRS v1.8 / BR: 3.4.1 Test data: Delete parent with active children/products Source: https://github.com/GFA26SE63/FSCM-Backend/blob/0f56f7099f07aa60d76673e6b6a57a2b606fb833/src/FSCM.API/Controllers/CategoriesController.cs Automation: Manual / candidate Version: 1.3; Actual result: —; Evidence: —
A15: FT-009-P | B15: Admin/Operator publishes SKU_A and SKU_B with approved effective prices | C15: 1. Sign in as Administrator; create SKU_A at 100,000 VND/carton and SKU_B at 50,000 VND/carton as Draft. 2. Publish both, verify Catalog. 3. Repeat on independent Draft with authorized Operator role. 4. Inspect effective price and audit. | D15: Both authorized roles can publish eligible Draft products; SKU_A/B visible and prices versioned; no duplicate SKU. | E15: F1 source fixture: Admin and Operator with product permissions; Draft SKU_A/SKU_B; price effective date. | F15: Not Run | O15: Type: Positive; Role: Administrator; Level: System / Integration SRS v1.8 / BR: 3.4.2; BR-07–08 Test data: Create Draft and publish valid SKU Source: https://github.com/GFA26SE63/FSCM-Backend/blob/0f56f7099f07aa60d76673e6b6a57a2b606fb833/src/FSCM.API/Controllers/ProductsController.cs Automation: Manual / candidate Version: 1.3; Actual result: —; Evidence: —
A16: FT-009-N | B16: Published SKU price locked; unauthorized non-product role cannot modify | C16: 1. Publish SKU_A. 2. Attempt edit price as Admin/Operator; must use new Draft/version. 3. Attempt any change as Sales. 4. Verify historical price and stock untouched. | D16: Published record immutable for both authorized roles; new Draft replacement allowed; Sales write forbidden; historical batch/transaction links unchanged. | E16: Test environment seeded; authorized Administrator; transaction isolated and resettable. | F16: Not Run | O16: Type: Negative; Role: Administrator; Level: System / Integration SRS v1.8 / BR: 3.4.2; BR-07–08 Test data: Edit published SKU price Source: https://github.com/GFA26SE63/FSCM-Backend/blob/0f56f7099f07aa60d76673e6b6a57a2b606fb833/src/FSCM.API/Controllers/ProductsController.cs Automation: Manual / candidate Version: 1.3; Actual result: —; Evidence: —
A17: FT-009-B | B17: Create and publish product Boundary — Clone already used SKU | C17: 1. Seed isolated FSCM fixture with required SKU, retailer, warehouse, roles and state; record starting stock/payment/ledger snapshots. 2. Sign in as Administrator; perform scenario: Clone already used SKU. 3. Submit both the valid operation and the specified invalid/boundary input. 4. Compare response, persisted state, actor audit, once-only effects and unchanged records against the expected result. | D17: Reject duplicate SKU without side effects | E17: Test environment seeded; authorized Administrator; transaction isolated and resettable. | F17: Not Run | O17: Type: Boundary; Role: Administrator; Level: System / Integration SRS v1.8 / BR: 3.4.2; BR-07–08 Test data: Clone already used SKU Source: https://github.com/GFA26SE63/FSCM-Backend/blob/0f56f7099f07aa60d76673e6b6a57a2b606fb833/src/FSCM.API/Controllers/ProductsController.cs Automation: Manual / candidate Version: 1.3; Actual result: —; Evidence: —
A18: FT-010-P | B18: Product search and catalog visibility Positive — Search published SKU in eligible catalog | C18: 1. Seed isolated FSCM fixture with required SKU, retailer, warehouse, roles and state; record starting stock/payment/ledger snapshots. 2. Sign in as Sales; Retailer; Administrator; perform scenario: Search published SKU in eligible catalog. 3. Submit both the valid operation and the specified invalid/boundary input. 4. Compare response, persisted state, actor audit, once-only effects and unchanged records against the expected result. | D18: Return only permitted published products | E18: Test environment seeded; authorized Sales; Retailer; Administrator; transaction isolated and resettable. | F18: Not Run | O18: Type: Positive; Role: Sales; Retailer; Administrator; Level: System / Integration SRS v1.8 / BR: 3.4.3 Test data: Search published SKU in eligible catalog Source: https://github.com/GFA26SE63/FSCM-Backend/blob/0f56f7099f07aa60d76673e6b6a57a2b606fb833/src/FSCM.Application/Features/Catalog/CatalogService.cs Automation: Manual / candidate Version: 1.3; Actual result: —; Evidence: —
A19: FT-010-N | B19: Product search and catalog visibility Negative — Access Draft product as purchasable | C19: 1. Seed isolated FSCM fixture with required SKU, retailer, warehouse, roles and state; record starting stock/payment/ledger snapshots. 2. Sign in as Sales; Retailer; Administrator; perform scenario: Access Draft product as purchasable. 3. Submit both the valid operation and the specified invalid/boundary input. 4. Compare response, persisted state, actor audit, once-only effects and unchanged records against the expected result. | D19: Never expose Draft/Inactive as orderable | E19: Test environment seeded; authorized Sales; Retailer; Administrator; transaction isolated and resettable. | F19: Not Run | O19: Type: Negative; Role: Sales; Retailer; Administrator; Level: System / Integration SRS v1.8 / BR: 3.4.3 Test data: Access Draft product as purchasable Source: https://github.com/GFA26SE63/FSCM-Backend/blob/0f56f7099f07aa60d76673e6b6a57a2b606fb833/src/FSCM.Application/Features/Catalog/CatalogService.cs Automation: Manual / candidate Version: 1.3; Actual result: —; Evidence: —
A20: FT-010-B | B20: Product search and catalog visibility Boundary — Empty search / paginated result | C20: 1. Seed isolated FSCM fixture with required SKU, retailer, warehouse, roles and state; record starting stock/payment/ledger snapshots. 2. Sign in as Sales; Retailer; Administrator; perform scenario: Empty search / paginated result. 3. Submit both the valid operation and the specified invalid/boundary input. 4. Compare response, persisted state, actor audit, once-only effects and unchanged records against the expected result. | D20: Return stable paged results or empty state | E20: Test environment seeded; authorized Sales; Retailer; Administrator; transaction isolated and resettable. | F20: Not Run | O20: Type: Boundary; Role: Sales; Retailer; Administrator; Level: System / Integration SRS v1.8 / BR: 3.4.3 Test data: Empty search / paginated result Source: https://github.com/GFA26SE63/FSCM-Backend/blob/0f56f7099f07aa60d76673e6b6a57a2b606fb833/src/FSCM.Application/Features/Catalog/CatalogService.cs Automation: Manual / candidate Version: 1.3; Actual result: —; Evidence: —
A21: R5-TC-CAT-01 | B21: F1 catalog, product authority and independent replacement Draft | C21: 1. Admin/Operator creates Category, SKU_A/B Draft and price effective versions. 2. Publish, query catalog as Sales. 3. Clone SKU_A for replacement, verify unique code and no migrated batches. 4. Test unauthorized writer. | D21: Admin and Operator permitted on catalog operations; Sales read-only; old SKU, inventory and historical orders unchanged; replacement has independent new Draft state. | E21: Draft/published SKU and parent category. Test data: Valid SKU, cycle-forming parent, inactive SKU. | F21: Not Run | O21: Requirement/Traceability: SRS v1.8 §3.4.1–3.4.2; AC-3.4.2-01; M03/WF01/TS01 Priority: P2; Level: Integration / System / Acceptance Version: 1.3; Actual result: —; Evidence: —

Sheet Promotion Management
A2: Feature | B2: Promotion Management | R2: Passed
A3: Test requirement | B3: Verify group promotion threshold sums eligible SKU quantities within one Sales Order: SKU_A6+SKU_B4 and SKU_A10 qualify; SKU_A6+SKU_B3 or external SKU4 do not. Apply 10% ordinary discount once, choose best valid campaign, then only percentage shelf-life tiers <100%. | R3: Failed
A4: Number of TCs | B4: =COUNTA(A12:A15) -> 4 | R4: Pending
A5: Testing Round | B5: Passed | C5: Failed | D5: Pending | E5: N/A | R5: N/A
A6: Round 1 | B6: =COUNTIF(F12:F15,"Passed")+COUNTIF(F12:F15,"Pass") -> 0 | C6: =COUNTIF(F12:F15,"Failed")+COUNTIF(F12:F15,"Fail") -> 0 | D6: =COUNTIF(F12:F15,"Not Run")+COUNTIF(F12:F15,"Blocked")+COUNTIF(F12:F15,"Pending")+COUNTBLANK(F12:F15) -> 4 | E6: =COUNTIF(F12:F15,"N/A") -> 0
A7: Round 2 | B7: =COUNTIF(I12:I15,"Passed")+COUNTIF(I12:I15,"Pass") -> 0 | C7: =COUNTIF(I12:I15,"Failed")+COUNTIF(I12:I15,"Fail") -> 0 | D7: =COUNTIF(I12:I15,"Not Run")+COUNTIF(I12:I15,"Blocked")+COUNTIF(I12:I15,"Pending") -> 0 | E7: =COUNTIF(I12:I15,"N/A") -> 0
A8: Round 3 | B8: =COUNTIF(L12:L15,"Passed")+COUNTIF(L12:L15,"Pass") -> 0 | C8: =COUNTIF(L12:L15,"Failed")+COUNTIF(L12:L15,"Fail") -> 0 | D8: =COUNTIF(L12:L15,"Not Run")+COUNTIF(L12:L15,"Blocked")+COUNTIF(L12:L15,"Pending") -> 0 | E8: =COUNTIF(L12:L15,"N/A") -> 0
A10: Test Case ID | B10: Test Case Description | C10: Test Case Procedure | D10: Expected Results | E10: Pre-conditions | F10: Round 1 | G10: Test date | H10: Tester | I10: Round 2 | J10: Test date | K10: Tester | L10: Round 3 | M10: Test date | N10: Tester | O10: Note
A11: Promotion Management — FSCM scenarios
A12: FT-011-P | B12: Group promotion applies to sum SKU_A6 + SKU_B4 | C12: 1. Admin creates eligible group {SKU_A,SKU_B}, threshold 10 cartons and 10% discount. 2. Sales creates R1 SO with A6 at 100,000 and B4 at 50,000. 3. Verify promotion eligibility and amounts before allocation. | D12: Eligible quantity=10; gross 800,000 VND; group discount=80,000; post-promotion base=720,000; applies once within this SO. | E12: F2 group SKU_A,SKU_B, active eligible retailer R1; list prices A100,000/B50,000; discount tier under applicable MLOR. | F12: Not Run | O12: Type: Positive; Role: Administrator; Level: System / Integration SRS v1.8 / BR: 3.5.1; BR-14–19 Test data: Create valid scoped promotion Source: https://github.com/GFA26SE63/FSCM-Backend/blob/0f56f7099f07aa60d76673e6b6a57a2b606fb833/src/FSCM.Application/Features/Promotions/PromotionService.cs Automation: Manual / candidate Version: 1.3; Actual result: —; Evidence: —
A13: FT-011-N | B13: Group promotion rejects under-threshold and foreign SKU quantities | C13: 1. Quote A6+B3 in one SO. 2. Quote A6+foreignSKU4 in a second SO. 3. Create two separate SOs whose combined quantity is 10. 4. Check eligible counted units. | D13: None qualifies for the 10-carton group; foreign SKU and quantities from other orders do not contribute. | E13: F2 group SKU_A,SKU_B, active eligible retailer R1; list prices A100,000/B50,000; discount tier under applicable MLOR. | F13: Not Run | O13: Type: Negative; Role: Administrator; Level: System / Integration SRS v1.8 / BR: 3.5.1; BR-14–19 Test data: Overlapping invalid period or unauthorized role Source: https://github.com/GFA26SE63/FSCM-Backend/blob/0f56f7099f07aa60d76673e6b6a57a2b606fb833/src/FSCM.Application/Features/Promotions/PromotionService.cs Automation: Manual / candidate Version: 1.3; Actual result: —; Evidence: —
A14: FT-011-B | B14: Group threshold boundary and active-campaign tie-break | C14: 1. Submit A10 and A6+B4 (valid), then A6+B3 (invalid). 2. Create two active group campaigns with equal VND discounts. 3. Set one campaign paused and repeat. | D14: Exactly 10 eligible cartons qualifies, 9 does not. Highest discount chosen per line; equal amount breaks by ascending campaign code; paused ignored. | E14: F2 group SKU_A,SKU_B, active eligible retailer R1; list prices A100,000/B50,000; discount tier under applicable MLOR. | F14: Not Run | O14: Type: Boundary; Role: Administrator; Level: System / Integration SRS v1.8 / BR: 3.5.1; BR-14–19 Test data: Paused/expired promotion evaluated for price Source: https://github.com/GFA26SE63/FSCM-Backend/blob/0f56f7099f07aa60d76673e6b6a57a2b606fb833/src/FSCM.Application/Features/Promotions/PromotionService.cs Automation: Manual / candidate Version: 1.3; Actual result: —; Evidence: —
A15: R5-TC-PROM-01 | B15: F2 promotion non-stacking, group threshold and percentage-only tiers | C15: 1. Seed SKU_A6+B4, 10-carton group promotion 10% and two overlapping valid ordinary campaigns. 2. Select largest VND benefit with deterministic code tie. 3. Apply valid percent-only batch tier after allocation. 4. Attempt fixed shelf-life tier and 100% tier. | D15: Only one ordinary discount per line; 80,000 VND off 800,000 total. Shelf-life percent tier applied to the remaining batch-specific net basis; fixed/100% rejected. | E15: F2 group SKU_A,SKU_B, active eligible retailer R1; list prices A100,000/B50,000; discount tier under applicable MLOR. | F15: Not Run | O15: Requirement/Traceability: SRS v1.8 §3.5.1; AC-3.5.1-01; M04/WF01/TS01 Priority: P2; Level: Integration / System / Acceptance Version: 1.3; Actual result: —; Evidence: —

Sheet Shelf-Life Pricing
A2: Feature | B2: Shelf-Life Pricing | R2: Passed
A3: Test requirement | B3: Validate percentage-only shelf-life tiers after batch eligibility and ordinary group promotion; fixed-amount and 100% tiers are rejected. Check SKU>Category tier precedence, 20%/<40%, 10%/40–<70%, 0%/>=70% demo bands, rounding >0, split-batch snapshots and exact-batch net-price adjustments. | R3: Failed
A4: Number of TCs | B4: =COUNTA(A12:A20) -> 9 | R4: Pending
A5: Testing Round | B5: Passed | C5: Failed | D5: Pending | E5: N/A | R5: N/A
A6: Round 1 | B6: =COUNTIF(F12:F20,"Passed")+COUNTIF(F12:F20,"Pass") -> 0 | C6: =COUNTIF(F12:F20,"Failed")+COUNTIF(F12:F20,"Fail") -> 0 | D6: =COUNTIF(F12:F20,"Not Run")+COUNTIF(F12:F20,"Blocked")+COUNTIF(F12:F20,"Pending")+COUNTBLANK(F12:F20) -> 9 | E6: =COUNTIF(F12:F20,"N/A") -> 0
A7: Round 2 | B7: =COUNTIF(I12:I20,"Passed")+COUNTIF(I12:I20,"Pass") -> 0 | C7: =COUNTIF(I12:I20,"Failed")+COUNTIF(I12:I20,"Fail") -> 0 | D7: =COUNTIF(I12:I20,"Not Run")+COUNTIF(I12:I20,"Blocked")+COUNTIF(I12:I20,"Pending") -> 0 | E7: =COUNTIF(I12:I20,"N/A") -> 0
A8: Round 3 | B8: =COUNTIF(L12:L20,"Passed")+COUNTIF(L12:L20,"Pass") -> 0 | C8: =COUNTIF(L12:L20,"Failed")+COUNTIF(L12:L20,"Fail") -> 0 | D8: =COUNTIF(L12:L20,"Not Run")+COUNTIF(L12:L20,"Blocked")+COUNTIF(L12:L20,"Pending") -> 0 | E8: =COUNTIF(L12:L20,"N/A") -> 0
A10: Test Case ID | B10: Test Case Description | C10: Test Case Procedure | D10: Expected Results | E10: Pre-conditions | F10: Round 1 | G10: Test date | H10: Tester | I10: Round 2 | J10: Test date | K10: Tester | L10: Round 3 | M10: Test date | N10: Tester | O10: Note
A11: Shelf-Life Pricing — FSCM scenarios
A12: FT-012-P | B12: Percentage tier chosen after eligibility and group promotion | C12: 1. Configure shelf-life bands (<40%=20%, 40%-<70%=10%, >=70%=0%), with SKU-specific higher priority than Category. 2. Allocate eligible batch only. 3. Apply percent to post-group-promotion base and capture batch price trace. | D12: Percentage shelf-life discount only; correct SKU precedence; no tier applied before eligibility; positive VND-rounded net price. | E12: F2/F3 tier demo, SKU_A and SKU_B in two warehouses; ordinary group discount applied first. | F12: Not Run | O12: Type: Positive; Role: Administrator; System; Level: System / Integration SRS v1.8 / BR: Registration price rules; SRS 3.5 Test data: Valid SKU tier covers remaining-life band Source: https://github.com/GFA26SE63/FSCM-Backend/blob/0f56f7099f07aa60d76673e6b6a57a2b606fb833/src/FSCM.Application/Features/ShelfLifeDiscounts/ShelfLifeDiscountService.cs Automation: Manual / candidate Version: 1.3; Actual result: —; Evidence: —
A13: FT-012-N | B13: Reject fixed, 100% and non-positive rounded final price | C13: 1. Submit fixed amount 3,500 VND/unit as a shelf-life tier. 2. Submit 100% tier. 3. Submit percentage tier whose rounded net unit price is 0. 4. Compare saved rules and totals. | D13: All invalid cases rejected without storing active tier/zero-price quotation; only percentage <100% and rounded net unit price >0 valid. | E13: Test environment seeded; authorized Administrator; System; transaction isolated and resettable. | F13: Not Run | O13: Type: Negative; Role: Administrator; System; Level: System / Integration SRS v1.8 / BR: Registration price rules; SRS 3.5 Test data: Overlapping tier or unsupported discount Source: https://github.com/GFA26SE63/FSCM-Backend/blob/0f56f7099f07aa60d76673e6b6a57a2b606fb833/src/FSCM.Application/Features/ShelfLifeDiscounts/ShelfLifeDiscountService.cs Automation: Manual / candidate Version: 1.3; Actual result: —; Evidence: —
A14: FT-012-B | B14: Percentage tier band boundaries and VND rounding | C14: 1. Evaluate 39.9999%, 40%, 69.9999%, 70% remaining shelf life. 2. Apply 20%,10%,10%,0% respectively where MLOR allows. 3. Reconcile split fragments in whole VND. | D14: Boundary follows [0,40),[40,70),[70,100]; no fixed tier, no 100% discount or final rounded price of zero. | E14: Test environment seeded; authorized Administrator; System; transaction isolated and resettable. | F14: Not Run | O14: Type: Boundary; Role: Administrator; System; Level: System / Integration SRS v1.8 / BR: Registration price rules; SRS 3.5 Test data: Tier upper-bound exact equality Source: https://github.com/GFA26SE63/FSCM-Backend/blob/0f56f7099f07aa60d76673e6b6a57a2b606fb833/src/FSCM.Application/Features/ShelfLifeDiscounts/ShelfLifeDiscountService.cs Automation: Manual / candidate Version: 1.3; Actual result: —; Evidence: —
A15: R5-TC-DISC-01 | B15: Percentage shelf-life tier | C15: Configure 12% SKU tier; allocate eligible 6-unit line; inspect versioned batch price and rounded amount. | D15: 12% discount = 9,000/unit, 54,000 total; net = 396,000 VND; one recorded tier/version; no change to MLOR. | E15: SKU 12% tier; one eligible batch; base price 75,000 VND/unit; qty=6. | F15: Not Run | O15: Requirement/Traceability: SRS v1.8 §3.5.4; BR-79/80; AC-3.5.4-01; M04/WF02/TS01 Priority: P1; Level: Integration / System / Acceptance Version: 1.3; Actual result: —; Evidence: —
A16: R5-TC-DISC-02 | B16: Reject fixed shelf-life discount configuration | C16: 1. Admin/Operator submits a fixed-amount-per-unit tier 3,500 VND on SKU_A. 2. Attempt publish and pricing. 3. Compare stored tier list, batch quote and audit. | D16: Fixed tier rejected; no price snapshot or sale uses fixed reduction; percentage-only tiers remain accepted. | E16: Active product and eligible batch; percentage-only approved shelf-life tier schedule. | F16: Not Run | O16: Requirement/Traceability: Registration §3.2; SRS v1.8 §3.5.4; R5-02; R5-02; M04/WF02/TS02 Priority: P1; Level: Integration / System / Acceptance Version: 1.3; Actual result: —; Evidence: —
A17: R5-TC-DISC-03 | B17: Reject zero final unit price after rounding | C17: 1. Seed valid small base unit price. 2. Apply eligible percentage tier <100% whose whole-VND final price rounds to 0. 3. Compare validation result and snapshot. | D17: Price rejected, not clamped/accepted at zero; no approved quotation, payment or dispatch uses zero final unit price. | E17: Tier bounds 20%-40%; at 20%, 40%; fractional final price; approved rounding rule. | F17: Not Run | O17: Requirement/Traceability: SRS v1.8 §3.5.4, §4 NFR-D01; BR-79; M04/WF02/TS03 Priority: P1; Level: Integration / System / Acceptance Version: 1.3; Actual result: —; Evidence: —
A18: R5-TC-DISC-04 | B18: F3 P1 612,000 VND immutable split-batch price snapshot | C18: 1. Seed F3 P1: SKU_A6 + SKU_B4 with group 10% ordinary discount. 2. Allocate across A1/A2/B1; calculate respective percentage shelf-life tiers. 3. Check fragments and overall final quote. 4. Edit tier afterward. | D18: P1 final quote 612,000 VND. Each batch/warehouse fragment keeps original list, group discount, remaining-life percent tier and net value; changing tier does not rewrite quote. | E18: F3 fixture sheet 03 and sheet 04 from Five Main Flows; P1 eligible A1/A2/B1 batches. | F18: Not Run | O18: Requirement/Traceability: Registration §3.2; SRS v1.8 §3.7.2/§3.5.4; NFR-D02; M04/WF02/TS04 Priority: P1; Level: Integration / System / Acceptance Version: 1.3; Actual result: —; Evidence: —
A19: R5-TC-DISC-05 | B19: MLOR restriction survives near-expiry discount | C19: Apply eligibility B1/B2 to near-expiry batch failing effective MLOR; configure high discount; rerun same candidate. | D19: Batch rejected before discount calculation; no offer/discount may relax effective MLOR or override hard eligibility. | E19: Retailer effective MLOR=0.80; batch remaining ratio at ETA=0.79; 50% discount eligible. | F19: Not Run | O19: Requirement/Traceability: Registration §3.2; R5-03; SRS v1.8 §3.7.4; M04/WF03/TS01 Priority: P1; Level: Integration / System / Acceptance Version: 1.3; Actual result: —; Evidence: —
A20: R5-TC-DISC-06 | B20: Effective MLOR precedence | C20: Resolve SKU-specific, Category and product-default MLOR for three otherwise identical lines; filter candidate at ETA. | D20: Choose SKU then Category then product default; candidate fails SKU rule but passes category/default; source and version snapshotted. | E20: SKU rule 0.80; Category 0.65; product default 0.50; candidate at ETA=0.70. | F20: Not Run | O20: Requirement/Traceability: Registration §3.2; SRS v1.8 §3.7.4; AC-3.7.4-01; M04/WF03/TS02 Priority: P1; Level: Integration / System / Acceptance Version: 1.3; Actual result: —; Evidence: —

Sheet Order Management
A2: Feature | B2: Order Management | R2: Passed
A3: Test requirement | B3: Verify Sales captures Sales Orders (SO), not POs; authorized Operator reviews before 00:00 ICT cutoff. Only after approved allocation price, Retailer quotation acceptance and valid prepaid/deferred method can a Purchase Order (PO) be issued. Rejected SO has reason; no reservation on capture/review. | R3: Failed
A4: Number of TCs | B4: =COUNTA(A12:A31) -> 20 | R4: Pending
A5: Testing Round | B5: Passed | C5: Failed | D5: Pending | E5: N/A | R5: N/A
A6: Round 1 | B6: =COUNTIF(F12:F31,"Passed")+COUNTIF(F12:F31,"Pass") -> 0 | C6: =COUNTIF(F12:F31,"Failed")+COUNTIF(F12:F31,"Fail") -> 0 | D6: =COUNTIF(F12:F31,"Not Run")+COUNTIF(F12:F31,"Blocked")+COUNTIF(F12:F31,"Pending")+COUNTBLANK(F12:F31) -> 20 | E6: =COUNTIF(F12:F31,"N/A") -> 0
A7: Round 2 | B7: =COUNTIF(I12:I31,"Passed")+COUNTIF(I12:I31,"Pass") -> 0 | C7: =COUNTIF(I12:I31,"Failed")+COUNTIF(I12:I31,"Fail") -> 0 | D7: =COUNTIF(I12:I31,"Not Run")+COUNTIF(I12:I31,"Blocked")+COUNTIF(I12:I31,"Pending") -> 0 | E7: =COUNTIF(I12:I31,"N/A") -> 0
A8: Round 3 | B8: =COUNTIF(L12:L31,"Passed")+COUNTIF(L12:L31,"Pass") -> 0 | C8: =COUNTIF(L12:L31,"Failed")+COUNTIF(L12:L31,"Fail") -> 0 | D8: =COUNTIF(L12:L31,"Not Run")+COUNTIF(L12:L31,"Blocked")+COUNTIF(L12:L31,"Pending") -> 0 | E8: =COUNTIF(L12:L31,"N/A") -> 0
A10: Test Case ID | B10: Test Case Description | C10: Test Case Procedure | D10: Expected Results | E10: Pre-conditions | F10: Round 1 | G10: Test date | H10: Tester | I10: Round 2 | J10: Test date | K10: Tester | L10: Round 3 | M10: Test date | N10: Tester | O10: Note
A11: Order Management — FSCM scenarios
A12: FT-014-P | B12: Create online order for assigned retailer Positive — Valid retailer and SKU/quantity | C12: 1. Seed isolated FSCM fixture with required SKU, retailer, warehouse, roles and state; record starting stock/payment/ledger snapshots. 2. Sign in as Sales; perform scenario: Valid retailer and SKU/quantity. 3. Submit both the valid operation and the specified invalid/boundary input. 4. Compare response, persisted state, actor audit, once-only effects and unchanged records against the expected result. | D12: Create Pending review; no hold/reservation | E12: Test environment seeded; authorized Sales; transaction isolated and resettable. | F12: Not Run | O12: Type: Positive; Role: Sales; Level: System / Integration SRS v1.8 / BR: 3.6.1; BR-20–22 Test data: Valid retailer and SKU/quantity Source: https://github.com/GFA26SE63/FSCM-Backend/blob/0f56f7099f07aa60d76673e6b6a57a2b606fb833/src/FSCM.Application/Features/Orders/OrderService.cs Automation: Manual / candidate Version: 1.3; Actual result: —; Evidence: —
A13: FT-014-N | B13: Create online order for assigned retailer Negative — Retailer outside Sales territory | C13: 1. Seed isolated FSCM fixture with required SKU, retailer, warehouse, roles and state; record starting stock/payment/ledger snapshots. 2. Sign in as Sales; perform scenario: Retailer outside Sales territory. 3. Submit both the valid operation and the specified invalid/boundary input. 4. Compare response, persisted state, actor audit, once-only effects and unchanged records against the expected result. | D13: Block out-of-scope retailer | E13: Test environment seeded; authorized Sales; transaction isolated and resettable. | F13: Not Run | O13: Type: Negative; Role: Sales; Level: System / Integration SRS v1.8 / BR: 3.6.1; BR-20–22 Test data: Retailer outside Sales territory Source: https://github.com/GFA26SE63/FSCM-Backend/blob/0f56f7099f07aa60d76673e6b6a57a2b606fb833/src/FSCM.Application/Features/Orders/OrderService.cs Automation: Manual / candidate Version: 1.3; Actual result: —; Evidence: —
A14: FT-014-B | B14: Create online order for assigned retailer Boundary — Current stock below requested quantity | C14: 1. Seed isolated FSCM fixture with required SKU, retailer, warehouse, roles and state; record starting stock/payment/ledger snapshots. 2. Sign in as Sales; perform scenario: Current stock below requested quantity. 3. Submit both the valid operation and the specified invalid/boundary input. 4. Compare response, persisted state, actor audit, once-only effects and unchanged records against the expected result. | D14: Accept valid request without promising stock; run later decides shortage | E14: Test environment seeded; authorized Sales; transaction isolated and resettable. | F14: Not Run | O14: Type: Boundary; Role: Sales; Level: System / Integration SRS v1.8 / BR: 3.6.1; BR-20–22 Test data: Current stock below requested quantity Source: https://github.com/GFA26SE63/FSCM-Backend/blob/0f56f7099f07aa60d76673e6b6a57a2b606fb833/src/FSCM.Application/Features/Orders/OrderService.cs Automation: Manual / candidate Version: 1.3; Actual result: —; Evidence: —
A15: FT-015-P | B15: Create order with step quantity validation Positive — Quantity is configured multiple | C15: 1. Seed isolated FSCM fixture with required SKU, retailer, warehouse, roles and state; record starting stock/payment/ledger snapshots. 2. Sign in as Sales; perform scenario: Quantity is configured multiple. 3. Submit both the valid operation and the specified invalid/boundary input. 4. Compare response, persisted state, actor audit, once-only effects and unchanged records against the expected result. | D15: Persist compliant order lines | E15: Test environment seeded; authorized Sales; transaction isolated and resettable. | F15: Not Run | O15: Type: Positive; Role: Sales; Level: System / Integration SRS v1.8 / BR: 3.6.1; configuration Test data: Quantity is configured multiple Source: https://github.com/GFA26SE63/FSCM-Backend/blob/0f56f7099f07aa60d76673e6b6a57a2b606fb833/src/FSCM.Application/Features/Orders/OrderService.cs Automation: Manual / candidate Version: 1.3; Actual result: —; Evidence: —
A16: FT-015-N | B16: Create order with step quantity validation Negative — Quantity violates configured step | C16: 1. Seed isolated FSCM fixture with required SKU, retailer, warehouse, roles and state; record starting stock/payment/ledger snapshots. 2. Sign in as Sales; perform scenario: Quantity violates configured step. 3. Submit both the valid operation and the specified invalid/boundary input. 4. Compare response, persisted state, actor audit, once-only effects and unchanged records against the expected result. | D16: Return validation error without order | E16: Test environment seeded; authorized Sales; transaction isolated and resettable. | F16: Not Run | O16: Type: Negative; Role: Sales; Level: System / Integration SRS v1.8 / BR: 3.6.1; configuration Test data: Quantity violates configured step Source: https://github.com/GFA26SE63/FSCM-Backend/blob/0f56f7099f07aa60d76673e6b6a57a2b606fb833/src/FSCM.Application/Features/Orders/OrderService.cs Automation: Manual / candidate Version: 1.3; Actual result: —; Evidence: —
A17: FT-015-B | B17: Create order with step quantity validation Boundary — Quantity exactly one order step | C17: 1. Seed isolated FSCM fixture with required SKU, retailer, warehouse, roles and state; record starting stock/payment/ledger snapshots. 2. Sign in as Sales; perform scenario: Quantity exactly one order step. 3. Submit both the valid operation and the specified invalid/boundary input. 4. Compare response, persisted state, actor audit, once-only effects and unchanged records against the expected result. | D17: Accept exactly one step | E17: Test environment seeded; authorized Sales; transaction isolated and resettable. | F17: Not Run | O17: Type: Boundary; Role: Sales; Level: System / Integration SRS v1.8 / BR: 3.6.1; configuration Test data: Quantity exactly one order step Source: https://github.com/GFA26SE63/FSCM-Backend/blob/0f56f7099f07aa60d76673e6b6a57a2b606fb833/src/FSCM.Application/Features/Orders/OrderService.cs Automation: Manual / candidate Version: 1.3; Actual result: —; Evidence: —
A18: FT-016-P | B18: Review Sales Order before 00:00 ICT cutoff | C18: 1. Capture a Sales Order. 2. Operator reviews it before 00:00 Asia/Ho_Chi_Minh. 3. Inspect acceptance/review timestamps. 4. Confirm no physical stock change. | D18: Commercial review moves Sales Order to awaiting daily run; no PO, picking list, stock reservation, or final batch price yet. | E18: Test environment seeded; authorized Operator; Administrator; transaction isolated and resettable. | F18: Not Run | O18: Type: Positive; Role: Operator; Administrator; Level: System / Integration SRS v1.8 / BR: 3.6.3; BR-25 Test data: Approve eligible order before cutoff Source: https://github.com/GFA26SE63/FSCM-Backend/blob/0f56f7099f07aa60d76673e6b6a57a2b606fb833/src/FSCM.API/Controllers/OrdersController.cs Automation: Manual / candidate Version: 1.3; Actual result: —; Evidence: —
A19: FT-016-N | B19: Review and reject purchase order Negative — Unauthorized review actor | C19: 1. Seed isolated FSCM fixture with required SKU, retailer, warehouse, roles and state; record starting stock/payment/ledger snapshots. 2. Sign in as Operator; Administrator; perform scenario: Unauthorized review actor. 3. Submit both the valid operation and the specified invalid/boundary input. 4. Compare response, persisted state, actor audit, once-only effects and unchanged records against the expected result. | D19: Reject unauthorized decision | E19: Test environment seeded; authorized Operator; Administrator; transaction isolated and resettable. | F19: Not Run | O19: Type: Negative; Role: Operator; Administrator; Level: System / Integration SRS v1.8 / BR: 3.6.3; BR-25 Test data: Unauthorized review actor Source: https://github.com/GFA26SE63/FSCM-Backend/blob/0f56f7099f07aa60d76673e6b6a57a2b606fb833/src/FSCM.API/Controllers/OrdersController.cs Automation: Manual / candidate Version: 1.3; Actual result: —; Evidence: —
A20: FT-016-B | B20: Reject inclusion when either cutoff timestamp is late | C20: 1. Set server acceptance and Operator review on opposite sides of 00:00 ICT. 2. Attempt today run. 3. Repeat at exact boundary. | D20: Both server acceptance and approval must be strictly before 00:00 ICT; otherwise defer to next run. Device time cannot override server ordering. | E20: Test environment seeded; authorized Operator; Administrator; transaction isolated and resettable. | F20: Not Run | O20: Type: Boundary; Role: Operator; Administrator; Level: System / Integration SRS v1.8 / BR: 3.6.3; BR-25 Test data: Order received at/after cutoff Source: https://github.com/GFA26SE63/FSCM-Backend/blob/0f56f7099f07aa60d76673e6b6a57a2b606fb833/src/FSCM.API/Controllers/OrdersController.cs Automation: Manual / candidate Version: 1.3; Actual result: —; Evidence: —
A21: FT-017-P | B21: Cancel order with evidence Positive — Cancel eligible pre-dispatch order with reason | C21: 1. Seed isolated FSCM fixture with required SKU, retailer, warehouse, roles and state; record starting stock/payment/ledger snapshots. 2. Sign in as Sales; Administrator; perform scenario: Cancel eligible pre-dispatch order with reason. 3. Submit both the valid operation and the specified invalid/boundary input. 4. Compare response, persisted state, actor audit, once-only effects and unchanged records against the expected result. | D21: Cancel and release reservations where applicable | E21: Test environment seeded; authorized Sales; Administrator; transaction isolated and resettable. | F21: Not Run | O21: Type: Positive; Role: Sales; Administrator; Level: System / Integration SRS v1.8 / BR: 3.6.4; BR-26 Test data: Cancel eligible pre-dispatch order with reason Source: https://github.com/GFA26SE63/FSCM-Backend/blob/0f56f7099f07aa60d76673e6b6a57a2b606fb833/src/FSCM.API/Controllers/OrdersController.cs Automation: Manual / candidate Version: 1.3; Actual result: —; Evidence: —
A22: FT-017-N | B22: Cancel order with evidence Negative — Cancel already dispatched order | C22: 1. Seed isolated FSCM fixture with required SKU, retailer, warehouse, roles and state; record starting stock/payment/ledger snapshots. 2. Sign in as Sales; Administrator; perform scenario: Cancel already dispatched order. 3. Submit both the valid operation and the specified invalid/boundary input. 4. Compare response, persisted state, actor audit, once-only effects and unchanged records against the expected result. | D22: Block cancellation after any dispatch | E22: Test environment seeded; authorized Sales; Administrator; transaction isolated and resettable. | F22: Not Run | O22: Type: Negative; Role: Sales; Administrator; Level: System / Integration SRS v1.8 / BR: 3.6.4; BR-26 Test data: Cancel already dispatched order Source: https://github.com/GFA26SE63/FSCM-Backend/blob/0f56f7099f07aa60d76673e6b6a57a2b606fb833/src/FSCM.API/Controllers/OrdersController.cs Automation: Manual / candidate Version: 1.3; Actual result: —; Evidence: —
A23: FT-017-B | B23: Cancel order with evidence Boundary — Attempt cancellation without attachment | C23: 1. Seed isolated FSCM fixture with required SKU, retailer, warehouse, roles and state; record starting stock/payment/ledger snapshots. 2. Sign in as Sales; Administrator; perform scenario: Attempt cancellation without attachment. 3. Submit both the valid operation and the specified invalid/boundary input. 4. Compare response, persisted state, actor audit, once-only effects and unchanged records against the expected result. | D23: Require cancellation evidence and audit trail | E23: Test environment seeded; authorized Sales; Administrator; transaction isolated and resettable. | F23: Not Run | O23: Type: Boundary; Role: Sales; Administrator; Level: System / Integration SRS v1.8 / BR: 3.6.4; BR-26 Test data: Attempt cancellation without attachment Source: https://github.com/GFA26SE63/FSCM-Backend/blob/0f56f7099f07aa60d76673e6b6a57a2b606fb833/src/FSCM.API/Controllers/OrdersController.cs Automation: Manual / candidate Version: 1.3; Actual result: —; Evidence: —
... A31: R5-TC-ORD-05 | B31: Cancel Sales Order with evidence | C31: 1. Cancel permitted state; 2. Repeat; 3. Test after dispatch. | D31: Permitted cancellation releases held stock once and creates refund obligation if paid; invalid state rejected. | E31: Cancelable order or approved quotation. Test data: Attachment, cancellation reason and idempotency key. | F31: Not Run | O31: Requirement/Traceability: SRS v1.8 §3.6.4; AC-3.6.4-01; M05/WF03/TS01 Priority: P1; Level: Integration / System / Acceptance Version: 1.3; Actual result: —; Evidence: —

Sheet Offline Synchronization
A2: Feature | B2: Offline Synchronization | R2: Passed
A3: Test requirement | B3: Verify Sales offline orders remain local drafts after reconnect and are sent only by explicit Send. Validate server rechecks of price, MLOR and retailer scope; safe idempotent technical retries; and a new request key after changing the payload. | R3: Failed
A4: Number of TCs | B4: =COUNTA(A12:A27) -> 16 | R4: Pending
A5: Testing Round | B5: Passed | C5: Failed | D5: Pending | E5: N/A | R5: N/A
A6: Round 1 | B6: =COUNTIF(F12:F27,"Passed")+COUNTIF(F12:F27,"Pass") -> 0 | C6: =COUNTIF(F12:F27,"Failed")+COUNTIF(F12:F27,"Fail") -> 0 | D6: =COUNTIF(F12:F27,"Not Run")+COUNTIF(F12:F27,"Blocked")+COUNTIF(F12:F27,"Pending")+COUNTBLANK(F12:F27) -> 16 | E6: =COUNTIF(F12:F27,"N/A") -> 0
A7: Round 2 | B7: =COUNTIF(I12:I27,"Passed")+COUNTIF(I12:I27,"Pass") -> 0 | C7: =COUNTIF(I12:I27,"Failed")+COUNTIF(I12:I27,"Fail") -> 0 | D7: =COUNTIF(I12:I27,"Not Run")+COUNTIF(I12:I27,"Blocked")+COUNTIF(I12:I27,"Pending") -> 0 | E7: =COUNTIF(I12:I27,"N/A") -> 0
A8: Round 3 | B8: =COUNTIF(L12:L27,"Passed")+COUNTIF(L12:L27,"Pass") -> 0 | C8: =COUNTIF(L12:L27,"Failed")+COUNTIF(L12:L27,"Fail") -> 0 | D8: =COUNTIF(L12:L27,"Not Run")+COUNTIF(L12:L27,"Blocked")+COUNTIF(L12:L27,"Pending") -> 0 | E8: =COUNTIF(L12:L27,"N/A") -> 0
A10: Test Case ID | B10: Test Case Description | C10: Test Case Procedure | D10: Expected Results | E10: Pre-conditions | F10: Round 1 | G10: Test date | H10: Tester | I10: Round 2 | J10: Test date | K10: Tester | L10: Round 3 | M10: Test date | N10: Tester | O10: Note
A11: Offline Synchronization — FSCM scenarios
A12: FT-019-P | B12: Save offline order to local queue Positive — No network, valid cached draft | C12: 1. Seed isolated FSCM fixture with required SKU, retailer, warehouse, roles and state; record starting stock/payment/ledger snapshots. 2. Sign in as Sales; perform scenario: No network, valid cached draft. 3. Submit both the valid operation and the specified invalid/boundary input. 4. Compare response, persisted state, actor audit, once-only effects and unchanged records against the expected result. | D12: Keep pending local draft visibly unsynced | E12: Test environment seeded; authorized Sales; transaction isolated and resettable. | F12: Not Run | O12: Type: Positive; Role: Sales; Level: System / Integration SRS v1.8 / BR: 3.6.2; BR-23 Test data: No network, valid cached draft Source: https://github.com/GFA26SE63/FSCM-Mobile/blob/2b5c4aa6591e1b2be65567964480df070100fbeb/lib/data/local/daos/offline_order_dao.dart Automation: Manual / candidate Version: 1.3; Actual result: —; Evidence: —
A13: FT-019-N | B13: Save offline order to local queue Negative — No local storage permission/corrupted payload | C13: 1. Seed isolated FSCM fixture with required SKU, retailer, warehouse, roles and state; record starting stock/payment/ledger snapshots. 2. Sign in as Sales; perform scenario: No local storage permission/corrupted payload. 3. Submit both the valid operation and the specified invalid/boundary input. 4. Compare response, persisted state, actor audit, once-only effects and unchanged records against the expected result. | D13: Show local persistence failure, not server success | E13: Test environment seeded; authorized Sales; transaction isolated and resettable. | F13: Not Run | O13: Type: Negative; Role: Sales; Level: System / Integration SRS v1.8 / BR: 3.6.2; BR-23 Test data: No local storage permission/corrupted payload Source: https://github.com/GFA26SE63/FSCM-Mobile/blob/2b5c4aa6591e1b2be65567964480df070100fbeb/lib/data/local/daos/offline_order_dao.dart Automation: Manual / candidate Version: 1.3; Actual result: —; Evidence: —
A14: FT-019-B | B14: Save offline order to local queue Boundary — Duplicate device request identifier | C14: 1. Seed isolated FSCM fixture with required SKU, retailer, warehouse, roles and state; record starting stock/payment/ledger snapshots. 2. Sign in as Sales; perform scenario: Duplicate device request identifier. 3. Submit both the valid operation and the specified invalid/boundary input. 4. Compare response, persisted state, actor audit, once-only effects and unchanged records against the expected result. | D14: Reuse same client key and avoid duplicate queue entries | E14: Test environment seeded; authorized Sales; transaction isolated and resettable. | F14: Not Run | O14: Type: Boundary; Role: Sales; Level: System / Integration SRS v1.8 / BR: 3.6.2; BR-23 Test data: Duplicate device request identifier Source: https://github.com/GFA26SE63/FSCM-Mobile/blob/2b5c4aa6591e1b2be65567964480df070100fbeb/lib/data/local/daos/offline_order_dao.dart Automation: Manual / candidate Version: 1.3; Actual result: —; Evidence: —
A15: FT-020-P | B15: Manual Send is required for locally saved offline order | C15: 1. Save offline draft; 2. Reconnect without action; 3. Confirm no server order; 4. Sales taps Send. | D15: Reconnection does not auto-submit drafts; explicit Sales Send validates current terms and creates one server order. | E15: Test environment seeded; authorized Sales; transaction isolated and resettable. | F15: Not Run | O15: Type: Positive; Role: Sales; Level: System / Integration SRS v1.8 / BR: 3.6.2; BR-23–24 Test data: Reconnect with compatible cached price Source: https://github.com/GFA26SE63/FSCM-Mobile/blob/2b5c4aa6591e1b2be65567964480df070100fbeb/lib/sync/sync_service.dart Automation: Manual / candidate Version: 1.3; Actual result: —; Evidence: —
A16: FT-020-N | B16: Changed price/MLOR/scope requires server conflict handling | C16: 1. Save draft; 2. Change base price, SKU MLOR or retailer assignment; 3. Tap Send. | D16: Price/MLOR changes require explicit confirmation; revoked retailer scope is rejected; no silent order acceptance. | E16: Test environment seeded; authorized Sales; transaction isolated and resettable. | F16: Not Run | O16: Type: Negative; Role: Sales; Level: System / Integration SRS v1.8 / BR: 3.6.2; BR-23–24 Test data: Server price or MLOR differs Source: https://github.com/GFA26SE63/FSCM-Mobile/blob/2b5c4aa6591e1b2be65567964480df070100fbeb/lib/sync/sync_service.dart Automation: Manual / candidate Version: 1.3; Actual result: —; Evidence: —
A17: FT-020-B | B17: Replay identical payload; new key required after edit | C17: 1. Send draft twice with same UUID/payload; 2. Edit payload and replay old key; 3. Send with new UUID. | D17: One server order for same key/payload; altered payload is rejected with old key and requires new key and revalidation. | E17: Test environment seeded; authorized Sales; transaction isolated and resettable. | F17: Not Run | O17: Type: Boundary; Role: Sales; Level: System / Integration SRS v1.8 / BR: 3.6.2; BR-23–24 Test data: Re-submit same UUID after timeout Source: https://github.com/GFA26SE63/FSCM-Mobile/blob/2b5c4aa6591e1b2be65567964480df070100fbeb/lib/sync/sync_service.dart Automation: Manual / candidate Version: 1.3; Actual result: —; Evidence: —
A18: FT-021-P | B18: Technical retry begins only after Sales initiates Send | C18: 1. Reconnect and wait; 2. Tap Send; 3. Simulate timeout and technical retry. | D18: No draft sent on reconnect. Retries for already-initiated sends use same key/payload only. | E18: Test environment seeded; authorized Sales; transaction isolated and resettable. | F18: Not Run | O18: Type: Positive; Role: Sales; Level: System / Integration SRS v1.8 / BR: 3.6.2; NFR Reliability Test data: Automatic retry after backoff Source: https://github.com/GFA26SE63/FSCM-Mobile/blob/2b5c4aa6591e1b2be65567964480df070100fbeb/lib/sync/sync_queue_logic.dart Automation: Manual / candidate Version: 1.3; Actual result: —; Evidence: —
A19: FT-021-N | B19: Retry failure preserves server-accepted conditions | C19: 1. Start manual Send; simulate intermittent failures. 2. Change server price after acceptance. 3. Retry unchanged accepted payload/key. | D19: Retries use same key and confirmed payload, do not reset acceptance or create duplicate orders; hard conflicts require user action. | E19: Test environment seeded; authorized Sales; transaction isolated and resettable. | F19: Not Run | O19: Type: Negative; Role: Sales; Level: System / Integration SRS v1.8 / BR: 3.6.2; NFR Reliability Test data: Retry during offline period Source: https://github.com/GFA26SE63/FSCM-Mobile/blob/2b5c4aa6591e1b2be65567964480df070100fbeb/lib/sync/sync_queue_logic.dart Automation: Manual / candidate Version: 1.3; Actual result: —; Evidence: —
A20: FT-021-B | B20: Manual retry when automated attempts exhausted | C20: 1. Exhaust bounded technical retries of explicitly submitted item. 2. Reconnect. 3. User taps Retry. 4. Inspect sequence and idempotency. | D20: Manual retry remains available, with exactly-once server effect; untouched drafts remain local. | E20: Test environment seeded; authorized Sales; transaction isolated and resettable. | F20: Not Run | O20: Type: Boundary; Role: Sales; Level: System / Integration SRS v1.8 / BR: 3.6.2; NFR Reliability Test data: Manual retry after automatic limit Source: https://github.com/GFA26SE63/FSCM-Mobile/blob/2b5c4aa6591e1b2be65567964480df070100fbeb/lib/sync/sync_queue_logic.dart Automation: Manual / candidate Version: 1.3; Actual result: —; Evidence: —
A21: R5-TC-OFF-01 | B21: Reconnect does not send local drafts | C21: 1. Reconnect; 2. Wait; 3. Inspect server/queue. | D21: Zero drafts uploaded until explicit Sales Send; local drafts remain Pending. | E21: 3 drafts cached offline. Test data: Connectivity toggled from offline to online. | F21: Not Run | O21: Requirement/Traceability: SRS v1.8 §3.6.2; AC-3.6.2-01; R5-06; M06/WF01/TS01 Priority: P1; Level: Integration / System / Acceptance Version: 1.3; Actual result: —; Evidence: —
A22: R5-TC-OFF-02 | B22: Sales manually sends unchanged draft | C22: 1. Tap Send; 2. Replay same UUID and payload 10 times. | D22: Exactly one accepted server order, same order code on replay; no duplicates or priority changes. | E22: Draft cached and reconnect completed. Test data: Valid draft and stable UUID. | F22: Not Run | O22: Requirement/Traceability: SRS v1.8 §3.6.2; BR-23; R5-06; M06/WF01/TS02 Priority: P1; Level: Integration / System / Acceptance Version: 1.3; Actual result: —; Evidence: —
A23: R5-TC-OFF-03 | B23: Base price changes before manual Send | C23: 1. Tap Send; 2. Review conflict; 3. Confirm updated conditions. | D23: No silent submit; Sales explicitly accepts current price before server order created. | E23: Cached price outdated. Test data: Old 100,000 vs server 110,000. | F23: Not Run | O23: Requirement/Traceability: SRS v1.8 §3.6.2; AC-3.6.2-02; NFR-O04; M06/WF02/TS01 Priority: P1; Level: Integration / System / Acceptance Version: 1.3; Actual result: —; Evidence: —
... A27: R5-TC-OFF-07 | B27: Edited draft requires new request key | C27: 1. Reuse UUID-A with edited payload; 2. Generate UUID-B; 3. Send. | D27: Old key/payload mismatch rejected; edited action must use new UUID-B and fresh server validation. | E27: Earlier draft key used; user edits quantity. Test data: UUID-A for old hash; UUID-B for edited payload. | F27: Not Run | O27: Requirement/Traceability: R5-06; SDD v1.8 Table 3.0 ID-2; R5-06; M06/WF03/TS02 Priority: P1; Level: Integration / System / Acceptance Version: 1.3; Actual result: —; Evidence: —

Sheet Allocation Engine
A2: Feature | B2: Allocation Engine | R2: Passed
A3: Test requirement | B3: Run one daily allocation snapshot at 00:00 Asia/Ho_Chi_Minh using server acceptance + review strictly before cutoff. Use weighted fE/fD/fQ and all-or-nothing priority; equal-score tie-break is earliest expiry, shortest distance, lowest batch code; never swap earlier allocations. Validate P1/C1/P2 complete and SHORT returns pool. | R3: Failed
A4: Number of TCs | B4: =COUNTA(A12:A40) -> 29 | R4: Pending
A5: Testing Round | B5: Passed | C5: Failed | D5: Pending | E5: N/A | R5: N/A
A6: Round 1 | B6: =COUNTIF(F12:F40,"Passed")+COUNTIF(F12:F40,"Pass") -> 0 | C6: =COUNTIF(F12:F40,"Failed")+COUNTIF(F12:F40,"Fail") -> 0 | D6: =COUNTIF(F12:F40,"Not Run")+COUNTIF(F12:F40,"Blocked")+COUNTIF(F12:F40,"Pending")+COUNTBLANK(F12:F40) -> 29 | E6: =COUNTIF(F12:F40,"N/A") -> 0
A7: Round 2 | B7: =COUNTIF(I12:I40,"Passed")+COUNTIF(I12:I40,"Pass") -> 0 | C7: =COUNTIF(I12:I40,"Failed")+COUNTIF(I12:I40,"Fail") -> 0 | D7: =COUNTIF(I12:I40,"Not Run")+COUNTIF(I12:I40,"Blocked")+COUNTIF(I12:I40,"Pending") -> 0 | E7: =COUNTIF(I12:I40,"N/A") -> 0
A8: Round 3 | B8: =COUNTIF(L12:L40,"Passed")+COUNTIF(L12:L40,"Pass") -> 0 | C8: =COUNTIF(L12:L40,"Failed")+COUNTIF(L12:L40,"Fail") -> 0 | D8: =COUNTIF(L12:L40,"Not Run")+COUNTIF(L12:L40,"Blocked")+COUNTIF(L12:L40,"Pending") -> 0 | E8: =COUNTIF(L12:L40,"N/A") -> 0
A10: Test Case ID | B10: Test Case Description | C10: Test Case Procedure | D10: Expected Results | E10: Pre-conditions | F10: Round 1 | G10: Test date | H10: Tester | I10: Round 2 | J10: Test date | K10: Tester | L10: Round 3 | M10: Test date | N10: Tester | O10: Note
A11: Allocation Engine — FSCM scenarios
A12: FT-022-P | B12: Daily allocation at 00:00 ICT with server timestamps | C12: 1. Seed accepted/reviewed orders at 23:59:59 ICT. 2. Trigger run at 00:00. 3. Inspect snapshot and run business date. | D12: Include only orders both server-accepted and reviewed before 00:00 ICT; one immutable run snapshot per local business day. | E12: Test environment seeded; authorized System Scheduler; transaction isolated and resettable. | F12: Not Run | O12: Type: Positive; Role: System Scheduler; Level: System / Integration SRS v1.8 / BR: 3.7.1; BR-27–30 Test data: Eligible approved orders before 00:00 VN Source: https://github.com/GFA26SE63/FSCM-Backend/blob/0f56f7099f07aa60d76673e6b6a57a2b606fb833/src/FSCM.Application/Features/AllocationRuns/AllocationRunService.cs Automation: Manual / candidate Version: 1.3; Actual result: —; Evidence: —
A13: FT-022-N | B13: Create daily allocation run Negative — Execute same daily run twice | C13: 1. Seed isolated FSCM fixture with required SKU, retailer, warehouse, roles and state; record starting stock/payment/ledger snapshots. 2. Sign in as System Scheduler; perform scenario: Execute same daily run twice. 3. Submit both the valid operation and the specified invalid/boundary input. 4. Compare response, persisted state, actor audit, once-only effects and unchanged records against the expected result. | D13: Return existing run without duplicate | E13: Test environment seeded; authorized System Scheduler; transaction isolated and resettable. | F13: Not Run | O13: Type: Negative; Role: System Scheduler; Level: System / Integration SRS v1.8 / BR: 3.7.1; BR-27–30 Test data: Execute same daily run twice Source: https://github.com/GFA26SE63/FSCM-Backend/blob/0f56f7099f07aa60d76673e6b6a57a2b606fb833/src/FSCM.Application/Features/AllocationRuns/AllocationRunService.cs Automation: Manual / candidate Version: 1.3; Actual result: —; Evidence: —
A14: FT-022-B | B14: At-cutoff equality and month/year rollover | C14: 1. Test acceptance/review at 23:59:59, 00:00:00 and 00:00:01 ICT. 2. Repeat at 31 Dec→1 Jan and month-end. 3. Vary device clocks. | D14: Strictly-before cutoff admits orders; equality/after and either late timestamp defer. ICT calendar and server times govern priority. | E14: Test environment seeded; authorized System Scheduler; transaction isolated and resettable. | F14: Not Run | O14: Type: Boundary; Role: System Scheduler; Level: System / Integration SRS v1.8 / BR: 3.7.1; BR-27–30 Test data: Order at exactly midnight VN Source: https://github.com/GFA26SE63/FSCM-Backend/blob/0f56f7099f07aa60d76673e6b6a57a2b606fb833/src/FSCM.Application/Features/AllocationRuns/AllocationRunService.cs Automation: Manual / candidate Version: 1.3; Actual result: —; Evidence: —
A15: FT-023-P | B15: Apply FEFO–MLOR hard eligibility Positive — Batch meets SKU/distance/expiry/MLOR | C15: 1. Seed isolated FSCM fixture with required SKU, retailer, warehouse, roles and state; record starting stock/payment/ledger snapshots. 2. Sign in as System; perform scenario: Batch meets SKU/distance/expiry/MLOR. 3. Submit both the valid operation and the specified invalid/boundary input. 4. Compare response, persisted state, actor audit, once-only effects and unchanged records against the expected result. | D15: Keep eligible batch for scoring | E15: Test environment seeded; authorized System; transaction isolated and resettable. | F15: Not Run | O15: Type: Positive; Role: System; Level: System / Integration SRS v1.8 / BR: 3.7.1; BR-31–32,61 Test data: Batch meets SKU/distance/expiry/MLOR Source: https://github.com/GFA26SE63/FSCM-Backend/blob/0f56f7099f07aa60d76673e6b6a57a2b606fb833/src/FSCM.Application/Features/AllocationRuns/AllocationPlanner.cs Automation: Manual / candidate Version: 1.3; Actual result: —; Evidence: —
A16: FT-023-N | B16: Apply FEFO–MLOR hard eligibility Negative — Batch expired or outside Dmax | C16: 1. Seed isolated FSCM fixture with required SKU, retailer, warehouse, roles and state; record starting stock/payment/ledger snapshots. 2. Sign in as System; perform scenario: Batch expired or outside Dmax. 3. Submit both the valid operation and the specified invalid/boundary input. 4. Compare response, persisted state, actor audit, once-only effects and unchanged records against the expected result. | D16: Exclude ineligible batch and log reason | E16: Test environment seeded; authorized System; transaction isolated and resettable. | F16: Not Run | O16: Type: Negative; Role: System; Level: System / Integration SRS v1.8 / BR: 3.7.1; BR-31–32,61 Test data: Batch expired or outside Dmax Source: https://github.com/GFA26SE63/FSCM-Backend/blob/0f56f7099f07aa60d76673e6b6a57a2b606fb833/src/FSCM.Application/Features/AllocationRuns/AllocationPlanner.cs Automation: Manual / candidate Version: 1.3; Actual result: —; Evidence: —
A17: FT-023-B | B17: Apply FEFO–MLOR hard eligibility Boundary — EXP−ETA exactly effective MLOR * shelf life | C17: 1. Seed isolated FSCM fixture with required SKU, retailer, warehouse, roles and state; record starting stock/payment/ledger snapshots. 2. Sign in as System; perform scenario: EXP−ETA exactly effective MLOR * shelf life. 3. Submit both the valid operation and the specified invalid/boundary input. 4. Compare response, persisted state, actor audit, once-only effects and unchanged records against the expected result. | D17: Treat equality as eligible | E17: Test environment seeded; authorized System; transaction isolated and resettable. | F17: Not Run | O17: Type: Boundary; Role: System; Level: System / Integration SRS v1.8 / BR: 3.7.1; BR-31–32,61 Test data: EXP−ETA exactly effective MLOR * shelf life Source: https://github.com/GFA26SE63/FSCM-Backend/blob/0f56f7099f07aa60d76673e6b6a57a2b606fb833/src/FSCM.Application/Features/AllocationRuns/AllocationPlanner.cs Automation: Manual / candidate Version: 1.3; Actual result: —; Evidence: —
A18: FT-024-P | B18: No later-order batch swap after earlier order is satisfied | C18: 1. Admit two ordered orders; 2. Allocate scarce batch; 3. Compare earlier allocations after later order. | D18: Earlier complete order retains allocation; later order becomes Short if pool exhausted; no batch reassignment. | E18: Test environment seeded; authorized System; transaction isolated and resettable. | F18: Not Run | O18: Type: Positive; Role: System; Level: System / Integration SRS v1.8 / BR: 3.7.1; BR-33–34 Test data: Eligible near/far batches with quantities Source: https://github.com/GFA26SE63/FSCM-Backend/blob/0f56f7099f07aa60d76673e6b6a57a2b606fb833/src/FSCM.Domain/Allocation/AllocationEngine.cs Automation: Manual / candidate Version: 1.3; Actual result: —; Evidence: —
A19: FT-024-N | B19: Score weighted batches and allocate Negative — Candidate set empty | C19: 1. Seed isolated FSCM fixture with required SKU, retailer, warehouse, roles and state; record starting stock/payment/ledger snapshots. 2. Sign in as System; perform scenario: Candidate set empty. 3. Submit both the valid operation and the specified invalid/boundary input. 4. Compare response, persisted state, actor audit, once-only effects and unchanged records against the expected result. | D19: Return shortage explanation | E19: Test environment seeded; authorized System; transaction isolated and resettable. | F19: Not Run | O19: Type: Negative; Role: System; Level: System / Integration SRS v1.8 / BR: 3.7.1; BR-33–34 Test data: Candidate set empty Source: https://github.com/GFA26SE63/FSCM-Backend/blob/0f56f7099f07aa60d76673e6b6a57a2b606fb833/src/FSCM.Domain/Allocation/AllocationEngine.cs Automation: Manual / candidate Version: 1.3; Actual result: —; Evidence: —
A20: FT-024-B | B20: Equal-score tie-break: expiry, distance, batch code | C20: 1. Seed candidates with identical weighted scores but different expiry dates. 2. Equalize expiry and vary W1=5 km/W2=10 km. 3. Equalize both and vary batch code. 4. Re-run with same frozen seed. | D20: Apply tie-break ONLY after equal score: earliest expiry, then nearer warehouse, then ascending batch code; stable across reruns. | E20: Test environment seeded; authorized System; transaction isolated and resettable. | F20: Not Run | O20: Type: Boundary; Role: System; Level: System / Integration SRS v1.8 / BR: 3.7.1; BR-33–34 Test data: Identical scores for two batches Source: https://github.com/GFA26SE63/FSCM-Backend/blob/0f56f7099f07aa60d76673e6b6a57a2b606fb833/src/FSCM.Domain/Allocation/AllocationEngine.cs Automation: Manual / candidate Version: 1.3; Actual result: —; Evidence: —
A21: FT-025-P | B21: Reject partial fulfillment and return pool Positive — Multiple lines fully fulfillable | C21: 1. Seed isolated FSCM fixture with required SKU, retailer, warehouse, roles and state; record starting stock/payment/ledger snapshots. 2. Sign in as System; perform scenario: Multiple lines fully fulfillable. 3. Submit both the valid operation and the specified invalid/boundary input. 4. Compare response, persisted state, actor audit, once-only effects and unchanged records against the expected result. | D21: Keep complete order tentatively allocated | E21: Test environment seeded; authorized System; transaction isolated and resettable. | F21: Not Run | O21: Type: Positive; Role: System; Level: System / Integration SRS v1.8 / BR: 3.7.1; BR-36 Test data: Multiple lines fully fulfillable Source: https://github.com/GFA26SE63/FSCM-Backend/blob/0f56f7099f07aa60d76673e6b6a57a2b606fb833/src/FSCM.Application/Features/AllocationRuns/AllocationPlanner.cs Automation: Manual / candidate Version: 1.3; Actual result: —; Evidence: —
A22: FT-025-N | B22: Short order receives no allocation or retained resubmission priority | C22: 1. Submit multi-line order with insufficient second SKU; 2. Inspect rollback; 3. Create new order. | D22: Return all tentative stock to shared pool; new order has new server timestamp/code and no reserved priority. | E22: Test environment seeded; authorized System; transaction isolated and resettable. | F22: Not Run | O22: Type: Negative; Role: System; Level: System / Integration SRS v1.8 / BR: 3.7.1; BR-36 Test data: One required SKU insufficient Source: https://github.com/GFA26SE63/FSCM-Backend/blob/0f56f7099f07aa60d76673e6b6a57a2b606fb833/src/FSCM.Application/Features/AllocationRuns/AllocationPlanner.cs Automation: Manual / candidate Version: 1.3; Actual result: —; Evidence: —
A23: FT-025-B | B23: Reject partial fulfillment and return pool Boundary — Stock exactly equals order total | C23: 1. Seed isolated FSCM fixture with required SKU, retailer, warehouse, roles and state; record starting stock/payment/ledger snapshots. 2. Sign in as System; perform scenario: Stock exactly equals order total. 3. Submit both the valid operation and the specified invalid/boundary input. 4. Compare response, persisted state, actor audit, once-only effects and unchanged records against the expected result. | D23: Allow exact total with zero remainder | E23: Test environment seeded; authorized System; transaction isolated and resettable. | F23: Not Run | O23: Type: Boundary; Role: System; Level: System / Integration SRS v1.8 / BR: 3.7.1; BR-36 Test data: Stock exactly equals order total Source: https://github.com/GFA26SE63/FSCM-Backend/blob/0f56f7099f07aa60d76673e6b6a57a2b606fb833/src/FSCM.Application/Features/AllocationRuns/AllocationPlanner.cs Automation: Manual / candidate Version: 1.3; Actual result: —; Evidence: —
... A40: R5-TC-ALLOC-09 | B40: Reject run repeat and stale plan | C40: Invoke same daily run twice; replay approval using stale proposal; verify immutable version and stock ledger. | D40: Second trigger joins existing business-day run; no double reservation, extra order priority or duplicate posting. | E40: Previously closed approved run for one ICT date. | F40: Not Run | O40: Requirement/Traceability: SRS v1.8 §3.7.2; BR-38; M07/WF03/TS03 Priority: P1; Level: Integration / System / Acceptance Version: 1.3; Actual result: —; Evidence: —

Sheet Allocation Approval
A2: Feature | B2: Allocation Approval | R2: Passed
A3: Test requirement | B3: Verify Administrator approval or reasoned recalculation of the current priced allocation proposal. Reject stale versions and stock conflicts, reserve inventory atomically exactly once, and issue a versioned quotation without releasing PO/picking before acceptance and valid payment. | R3: Failed
A4: Number of TCs | B4: =COUNTA(A12:A17) -> 6 | R4: Pending
A5: Testing Round | B5: Passed | C5: Failed | D5: Pending | E5: N/A | R5: N/A
A6: Round 1 | B6: =COUNTIF(F12:F17,"Passed")+COUNTIF(F12:F17,"Pass") -> 0 | C6: =COUNTIF(F12:F17,"Failed")+COUNTIF(F12:F17,"Fail") -> 0 | D6: =COUNTIF(F12:F17,"Not Run")+COUNTIF(F12:F17,"Blocked")+COUNTIF(F12:F17,"Pending")+COUNTBLANK(F12:F17) -> 6 | E6: =COUNTIF(F12:F17,"N/A") -> 0
A7: Round 2 | B7: =COUNTIF(I12:I17,"Passed")+COUNTIF(I12:I17,"Pass") -> 0 | C7: =COUNTIF(I12:I17,"Failed")+COUNTIF(I12:I17,"Fail") -> 0 | D7: =COUNTIF(I12:I17,"Not Run")+COUNTIF(I12:I17,"Blocked")+COUNTIF(I12:I17,"Pending") -> 0 | E7: =COUNTIF(I12:I17,"N/A") -> 0
A8: Round 3 | B8: =COUNTIF(L12:L17,"Passed")+COUNTIF(L12:L17,"Pass") -> 0 | C8: =COUNTIF(L12:L17,"Failed")+COUNTIF(L12:L17,"Fail") -> 0 | D8: =COUNTIF(L12:L17,"Not Run")+COUNTIF(L12:L17,"Blocked")+COUNTIF(L12:L17,"Pending") -> 0 | E8: =COUNTIF(L12:L17,"N/A") -> 0
A10: Test Case ID | B10: Test Case Description | C10: Test Case Procedure | D10: Expected Results | E10: Pre-conditions | F10: Round 1 | G10: Test date | H10: Tester | I10: Round 2 | J10: Test date | K10: Tester | L10: Round 3 | M10: Test date | N10: Tester | O10: Note
A11: Allocation Approval — FSCM scenarios
A12: FT-026-P | B12: Review proposal and recalculate Positive — Review current proposal revision | C12: 1. Seed isolated FSCM fixture with required SKU, retailer, warehouse, roles and state; record starting stock/payment/ledger snapshots. 2. Sign in as Administrator; perform scenario: Review current proposal revision. 3. Submit both the valid operation and the specified invalid/boundary input. 4. Compare response, persisted state, actor audit, once-only effects and unchanged records against the expected result. | D12: Record approval or reasoned recalculation | E12: Test environment seeded; authorized Administrator; transaction isolated and resettable. | F12: Not Run | O12: Type: Positive; Role: Administrator; Level: System / Integration SRS v1.8 / BR: 3.7.2; BR-37–40 Test data: Review current proposal revision Source: https://github.com/GFA26SE63/FSCM-Backend/blob/0f56f7099f07aa60d76673e6b6a57a2b606fb833/src/FSCM.Application/Features/AllocationRuns/AllocationPlanApprovalService.cs Automation: Manual / candidate Version: 1.3; Actual result: —; Evidence: —
A13: FT-026-N | B13: Review proposal and recalculate Negative — Approve stale proposal version | C13: 1. Seed isolated FSCM fixture with required SKU, retailer, warehouse, roles and state; record starting stock/payment/ledger snapshots. 2. Sign in as Administrator; perform scenario: Approve stale proposal version. 3. Submit both the valid operation and the specified invalid/boundary input. 4. Compare response, persisted state, actor audit, once-only effects and unchanged records against the expected result. | D13: Refuse stale version | E13: Test environment seeded; authorized Administrator; transaction isolated and resettable. | F13: Not Run | O13: Type: Negative; Role: Administrator; Level: System / Integration SRS v1.8 / BR: 3.7.2; BR-37–40 Test data: Approve stale proposal version Source: https://github.com/GFA26SE63/FSCM-Backend/blob/0f56f7099f07aa60d76673e6b6a57a2b606fb833/src/FSCM.Application/Features/AllocationRuns/AllocationPlanApprovalService.cs Automation: Manual / candidate Version: 1.3; Actual result: —; Evidence: —
A14: FT-026-B | B14: Review proposal and recalculate Boundary — Request recalculation without reason | C14: 1. Seed isolated FSCM fixture with required SKU, retailer, warehouse, roles and state; record starting stock/payment/ledger snapshots. 2. Sign in as Administrator; perform scenario: Request recalculation without reason. 3. Submit both the valid operation and the specified invalid/boundary input. 4. Compare response, persisted state, actor audit, once-only effects and unchanged records against the expected result. | D14: Require rationale and preserve revision chain | E14: Test environment seeded; authorized Administrator; transaction isolated and resettable. | F14: Not Run | O14: Type: Boundary; Role: Administrator; Level: System / Integration SRS v1.8 / BR: 3.7.2; BR-37–40 Test data: Request recalculation without reason Source: https://github.com/GFA26SE63/FSCM-Backend/blob/0f56f7099f07aa60d76673e6b6a57a2b606fb833/src/FSCM.Application/Features/AllocationRuns/AllocationPlanApprovalService.cs Automation: Manual / candidate Version: 1.3; Actual result: —; Evidence: —
A15: FT-027-P | B15: Admin plan and final batch price approval reserves once | C15: 1. Plan and approve allocation price version. 2. Verify atomic reservation. 3. Inspect quotation lifecycle before Retailer acceptance/payment. | D15: Approval only reserves stock and publishes versioned quotation; PO and picking release wait for retailer quotation acceptance and valid prepaid/deferred conversion. | E15: Test environment seeded; authorized Administrator; System; transaction isolated and resettable. | F15: Not Run | O15: Type: Positive; Role: Administrator; System; Level: System / Integration SRS v1.8 / BR: 3.7.2; BR-38,41 Test data: Approve unchanged eligible proposal Source: https://github.com/GFA26SE63/FSCM-Backend/blob/0f56f7099f07aa60d76673e6b6a57a2b606fb833/src/FSCM.Application/Features/AllocationRuns/AllocationReservationService.cs Automation: Manual / candidate Version: 1.3; Actual result: —; Evidence: —
A16: FT-027-N | B16: Commit reservation transactionally Negative — Inventory altered since snapshot | C16: 1. Seed isolated FSCM fixture with required SKU, retailer, warehouse, roles and state; record starting stock/payment/ledger snapshots. 2. Sign in as Administrator; System; perform scenario: Inventory altered since snapshot. 3. Submit both the valid operation and the specified invalid/boundary input. 4. Compare response, persisted state, actor audit, once-only effects and unchanged records against the expected result. | D16: Rollback full commit on conflict | E16: Test environment seeded; authorized Administrator; System; transaction isolated and resettable. | F16: Not Run | O16: Type: Negative; Role: Administrator; System; Level: System / Integration SRS v1.8 / BR: 3.7.2; BR-38,41 Test data: Inventory altered since snapshot Source: https://github.com/GFA26SE63/FSCM-Backend/blob/0f56f7099f07aa60d76673e6b6a57a2b606fb833/src/FSCM.Application/Features/AllocationRuns/AllocationReservationService.cs Automation: Manual / candidate Version: 1.3; Actual result: —; Evidence: —
A17: FT-027-B | B17: Retry approval is idempotent without PO/picking | C17: 1. Re-send same plan approval. 2. Inspect ledger/reservations/quotes/PO/picking counts. | D17: One reservation and one approved quote version; no PO or picking before payment-method/PO gate. | E17: Test environment seeded; authorized Administrator; System; transaction isolated and resettable. | F17: Not Run | O17: Type: Boundary; Role: Administrator; System; Level: System / Integration SRS v1.8 / BR: 3.7.2; BR-38,41 Test data: Repeat identical approval request Source: https://github.com/GFA26SE63/FSCM-Backend/blob/0f56f7099f07aa60d76673e6b6a57a2b606fb833/src/FSCM.Application/Features/AllocationRuns/AllocationReservationService.cs Automation: Manual / candidate Version: 1.3; Actual result: —; Evidence: —

Sheet Goods Receipts
A2: Feature | B2: Goods Receipts | R2: Passed
A3: Test requirement | B3: Verify warehouse goods receipts record valid SKU, lot, production/expiry and quantity data; inventory increases only after authorized approval. Reject ineligible products and merge matching warehouse/SKU/expiry stock without duplicate ledger effects. | R3: Failed
A4: Number of TCs | B4: =COUNTA(A12:A14) -> 3 | R4: Pending
A5: Testing Round | B5: Passed | C5: Failed | D5: Pending | E5: N/A | R5: N/A
A6: Round 1 | B6: =COUNTIF(F12:F14,"Passed")+COUNTIF(F12:F14,"Pass") -> 0 | C6: =COUNTIF(F12:F14,"Failed")+COUNTIF(F12:F14,"Fail") -> 0 | D6: =COUNTIF(F12:F14,"Not Run")+COUNTIF(F12:F14,"Blocked")+COUNTIF(F12:F14,"Pending")+COUNTBLANK(F12:F14) -> 3 | E6: =COUNTIF(F12:F14,"N/A") -> 0
A7: Round 2 | B7: =COUNTIF(I12:I14,"Passed")+COUNTIF(I12:I14,"Pass") -> 0 | C7: =COUNTIF(I12:I14,"Failed")+COUNTIF(I12:I14,"Fail") -> 0 | D7: =COUNTIF(I12:I14,"Not Run")+COUNTIF(I12:I14,"Blocked")+COUNTIF(I12:I14,"Pending") -> 0 | E7: =COUNTIF(I12:I14,"N/A") -> 0
A8: Round 3 | B8: =COUNTIF(L12:L14,"Passed")+COUNTIF(L12:L14,"Pass") -> 0 | C8: =COUNTIF(L12:L14,"Failed")+COUNTIF(L12:L14,"Fail") -> 0 | D8: =COUNTIF(L12:L14,"Not Run")+COUNTIF(L12:L14,"Blocked")+COUNTIF(L12:L14,"Pending") -> 0 | E8: =COUNTIF(L12:L14,"N/A") -> 0
A10: Test Case ID | B10: Test Case Description | C10: Test Case Procedure | D10: Expected Results | E10: Pre-conditions | F10: Round 1 | G10: Test date | H10: Tester | I10: Round 2 | J10: Test date | K10: Tester | L10: Round 3 | M10: Test date | N10: Tester | O10: Note
A11: Goods Receipts — FSCM scenarios
A12: FT-028-P | B12: Create goods receipt and approve stock-in Positive — Valid product/batch/expiry and approved receipt | C12: 1. Seed isolated FSCM fixture with required SKU, retailer, warehouse, roles and state; record starting stock/payment/ledger snapshots. 2. Sign in as Warehouse Keeper; Administrator; perform scenario: Valid product/batch/expiry and approved receipt. 3. Submit both the valid operation and the specified invalid/boundary input. 4. Compare response, persisted state, actor audit, once-only effects and unchanged records against the expected result. | D12: Increase inventory only on approval | E12: Test environment seeded; authorized Warehouse Keeper; Administrator; transaction isolated and resettable. | F12: Not Run | O12: Type: Positive; Role: Warehouse Keeper; Administrator; Level: System / Integration SRS v1.8 / BR: 3.8.1; BR-09,42 Test data: Valid product/batch/expiry and approved receipt Source: https://github.com/GFA26SE63/FSCM-Backend/blob/0f56f7099f07aa60d76673e6b6a57a2b606fb833/src/FSCM.Application/Features/Inventory/InventoryService.cs Automation: Manual / candidate Version: 1.3; Actual result: —; Evidence: —
A13: FT-028-N | B13: Create goods receipt and approve stock-in Negative — Receive Draft/Inactive product | C13: 1. Seed isolated FSCM fixture with required SKU, retailer, warehouse, roles and state; record starting stock/payment/ledger snapshots. 2. Sign in as Warehouse Keeper; Administrator; perform scenario: Receive Draft/Inactive product. 3. Submit both the valid operation and the specified invalid/boundary input. 4. Compare response, persisted state, actor audit, once-only effects and unchanged records against the expected result. | D13: Block ineligible SKU / bad data | E13: Test environment seeded; authorized Warehouse Keeper; Administrator; transaction isolated and resettable. | F13: Not Run | O13: Type: Negative; Role: Warehouse Keeper; Administrator; Level: System / Integration SRS v1.8 / BR: 3.8.1; BR-09,42 Test data: Receive Draft/Inactive product Source: https://github.com/GFA26SE63/FSCM-Backend/blob/0f56f7099f07aa60d76673e6b6a57a2b606fb833/src/FSCM.Application/Features/Inventory/InventoryService.cs Automation: Manual / candidate Version: 1.3; Actual result: —; Evidence: —
A14: FT-028-B | B14: Create goods receipt and approve stock-in Boundary — Same warehouse+SKU+expiry already exists | C14: 1. Seed isolated FSCM fixture with required SKU, retailer, warehouse, roles and state; record starting stock/payment/ledger snapshots. 2. Sign in as Warehouse Keeper; Administrator; perform scenario: Same warehouse+SKU+expiry already exists. 3. Submit both the valid operation and the specified invalid/boundary input. 4. Compare response, persisted state, actor audit, once-only effects and unchanged records against the expected result. | D14: Merge stock into same batch identity | E14: Test environment seeded; authorized Warehouse Keeper; Administrator; transaction isolated and resettable. | F14: Not Run | O14: Type: Boundary; Role: Warehouse Keeper; Administrator; Level: System / Integration SRS v1.8 / BR: 3.8.1; BR-09,42 Test data: Same warehouse+SKU+expiry already exists Source: https://github.com/GFA26SE63/FSCM-Backend/blob/0f56f7099f07aa60d76673e6b6a57a2b606fb833/src/FSCM.Application/Features/Inventory/InventoryService.cs Automation: Manual / candidate Version: 1.3; Actual result: —; Evidence: —

Sheet Warehouse Inventory
A2: Feature | B2: Warehouse Inventory | R2: Passed
A3: Test requirement | B3: Verify warehouse-scoped OnHand, Reserved, Locked and Available balances, expiry detection, inventory locks and approved write-offs. Reject unauthorized reads, expired allocation, negative/over-limit movements and premature deductions; preserve QR-label quantity lineage. | R3: Failed
A4: Number of TCs | B4: =COUNTA(A12:A23) -> 12 | R4: Pending
A5: Testing Round | B5: Passed | C5: Failed | D5: Pending | E5: N/A | R5: N/A
A6: Round 1 | B6: =COUNTIF(F12:F23,"Passed")+COUNTIF(F12:F23,"Pass") -> 0 | C6: =COUNTIF(F12:F23,"Failed")+COUNTIF(F12:F23,"Fail") -> 0 | D6: =COUNTIF(F12:F23,"Not Run")+COUNTIF(F12:F23,"Blocked")+COUNTIF(F12:F23,"Pending")+COUNTBLANK(F12:F23) -> 12 | E6: =COUNTIF(F12:F23,"N/A") -> 0
A7: Round 2 | B7: =COUNTIF(I12:I23,"Passed")+COUNTIF(I12:I23,"Pass") -> 0 | C7: =COUNTIF(I12:I23,"Failed")+COUNTIF(I12:I23,"Fail") -> 0 | D7: =COUNTIF(I12:I23,"Not Run")+COUNTIF(I12:I23,"Blocked")+COUNTIF(I12:I23,"Pending") -> 0 | E7: =COUNTIF(I12:I23,"N/A") -> 0
A8: Round 3 | B8: =COUNTIF(L12:L23,"Passed")+COUNTIF(L12:L23,"Pass") -> 0 | C8: =COUNTIF(L12:L23,"Failed")+COUNTIF(L12:L23,"Fail") -> 0 | D8: =COUNTIF(L12:L23,"Not Run")+COUNTIF(L12:L23,"Blocked")+COUNTIF(L12:L23,"Pending") -> 0 | E8: =COUNTIF(L12:L23,"N/A") -> 0
A10: Test Case ID | B10: Test Case Description | C10: Test Case Procedure | D10: Expected Results | E10: Pre-conditions | F10: Round 1 | G10: Test date | H10: Tester | I10: Round 2 | J10: Test date | K10: Tester | L10: Round 3 | M10: Test date | N10: Tester | O10: Note
A11: Warehouse Inventory — FSCM scenarios
A12: FT-029-P | B12: View warehouse batch and stock Positive — Read own assigned warehouse | C12: 1. Seed isolated FSCM fixture with required SKU, retailer, warehouse, roles and state; record starting stock/payment/ledger snapshots. 2. Sign in as Warehouse Keeper; Administrator; perform scenario: Read own assigned warehouse. 3. Submit both the valid operation and the specified invalid/boundary input. 4. Compare response, persisted state, actor audit, once-only effects and unchanged records against the expected result. | D12: Return OnHand/Reserved/Available accurately | E12: Test environment seeded; authorized Warehouse Keeper; Administrator; transaction isolated and resettable. | F12: Not Run | O12: Type: Positive; Role: Warehouse Keeper; Administrator; Level: System / Integration SRS v1.8 / BR: 3.8.2; BR-41 Test data: Read own assigned warehouse Source: https://github.com/GFA26SE63/FSCM-Backend/blob/0f56f7099f07aa60d76673e6b6a57a2b606fb833/src/FSCM.API/Controllers/InventoryController.cs Automation: Manual / candidate Version: 1.3; Actual result: —; Evidence: —
A13: FT-029-N | B13: View warehouse batch and stock Negative — Warehouse Keeper queries unauthorized warehouse | C13: 1. Seed isolated FSCM fixture with required SKU, retailer, warehouse, roles and state; record starting stock/payment/ledger snapshots. 2. Sign in as Warehouse Keeper; Administrator; perform scenario: Warehouse Keeper queries unauthorized warehouse. 3. Submit both the valid operation and the specified invalid/boundary input. 4. Compare response, persisted state, actor audit, once-only effects and unchanged records against the expected result. | D13: Block access outside warehouse | E13: Test environment seeded; authorized Warehouse Keeper; Administrator; transaction isolated and resettable. | F13: Not Run | O13: Type: Negative; Role: Warehouse Keeper; Administrator; Level: System / Integration SRS v1.8 / BR: 3.8.2; BR-41 Test data: Warehouse Keeper queries unauthorized warehouse Source: https://github.com/GFA26SE63/FSCM-Backend/blob/0f56f7099f07aa60d76673e6b6a57a2b606fb833/src/FSCM.API/Controllers/InventoryController.cs Automation: Manual / candidate Version: 1.3; Actual result: —; Evidence: —
A14: FT-029-B | B14: View warehouse batch and stock Boundary — Reserved equals OnHand | C14: 1. Seed isolated FSCM fixture with required SKU, retailer, warehouse, roles and state; record starting stock/payment/ledger snapshots. 2. Sign in as Warehouse Keeper; Administrator; perform scenario: Reserved equals OnHand. 3. Submit both the valid operation and the specified invalid/boundary input. 4. Compare response, persisted state, actor audit, once-only effects and unchanged records against the expected result. | D14: Available is zero and not negative | E14: Test environment seeded; authorized Warehouse Keeper; Administrator; transaction isolated and resettable. | F14: Not Run | O14: Type: Boundary; Role: Warehouse Keeper; Administrator; Level: System / Integration SRS v1.8 / BR: 3.8.2; BR-41 Test data: Reserved equals OnHand Source: https://github.com/GFA26SE63/FSCM-Backend/blob/0f56f7099f07aa60d76673e6b6a57a2b606fb833/src/FSCM.API/Controllers/InventoryController.cs Automation: Manual / candidate Version: 1.3; Actual result: —; Evidence: —
A15: FT-030-P | B15: Detect expiry and inventory lock Positive — Nightly scan sees expired batch | C15: 1. Seed isolated FSCM fixture with required SKU, retailer, warehouse, roles and state; record starting stock/payment/ledger snapshots. 2. Sign in as System; perform scenario: Nightly scan sees expired batch. 3. Submit both the valid operation and the specified invalid/boundary input. 4. Compare response, persisted state, actor audit, once-only effects and unchanged records against the expected result. | D15: Mark expired and prevent issue | E15: Test environment seeded; authorized System; transaction isolated and resettable. | F15: Not Run | O15: Type: Positive; Role: System; Level: System / Integration SRS v1.8 / BR: 3.8.2; BR-43 Test data: Nightly scan sees expired batch Source: https://github.com/GFA26SE63/FSCM-Backend/blob/0f56f7099f07aa60d76673e6b6a57a2b606fb833/src/FSCM.Application/Features/Inventory/InventoryExpirySweepService.cs Automation: Manual / candidate Version: 1.3; Actual result: —; Evidence: —
A16: FT-030-N | B16: Detect expiry and inventory lock Negative — Expired batch offered to allocation | C16: 1. Seed isolated FSCM fixture with required SKU, retailer, warehouse, roles and state; record starting stock/payment/ledger snapshots. 2. Sign in as System; perform scenario: Expired batch offered to allocation. 3. Submit both the valid operation and the specified invalid/boundary input. 4. Compare response, persisted state, actor audit, once-only effects and unchanged records against the expected result. | D16: Reject expired stock candidate | E16: Test environment seeded; authorized System; transaction isolated and resettable. | F16: Not Run | O16: Type: Negative; Role: System; Level: System / Integration SRS v1.8 / BR: 3.8.2; BR-43 Test data: Expired batch offered to allocation Source: https://github.com/GFA26SE63/FSCM-Backend/blob/0f56f7099f07aa60d76673e6b6a57a2b606fb833/src/FSCM.Application/Features/Inventory/InventoryExpirySweepService.cs Automation: Manual / candidate Version: 1.3; Actual result: —; Evidence: —
A17: FT-030-B | B17: Detect expiry and inventory lock Boundary — Expiry exactly today | C17: 1. Seed isolated FSCM fixture with required SKU, retailer, warehouse, roles and state; record starting stock/payment/ledger snapshots. 2. Sign in as System; perform scenario: Expiry exactly today. 3. Submit both the valid operation and the specified invalid/boundary input. 4. Compare response, persisted state, actor audit, once-only effects and unchanged records against the expected result. | D17: Apply configured boundary rule with traceable status | E17: Test environment seeded; authorized System; transaction isolated and resettable. | F17: Not Run | O17: Type: Boundary; Role: System; Level: System / Integration SRS v1.8 / BR: 3.8.2; BR-43 Test data: Expiry exactly today Source: https://github.com/GFA26SE63/FSCM-Backend/blob/0f56f7099f07aa60d76673e6b6a57a2b606fb833/src/FSCM.Application/Features/Inventory/InventoryExpirySweepService.cs Automation: Manual / candidate Version: 1.3; Actual result: —; Evidence: —
A18: FT-031-P | B18: Write-off unusable quantity Positive — Authorized write-off with reason/evidence | C18: 1. Seed isolated FSCM fixture with required SKU, retailer, warehouse, roles and state; record starting stock/payment/ledger snapshots. 2. Sign in as Warehouse Keeper; Administrator; perform scenario: Authorized write-off with reason/evidence. 3. Submit both the valid operation and the specified invalid/boundary input. 4. Compare response, persisted state, actor audit, once-only effects and unchanged records against the expected result. | D18: Reduce only approved affected stock with audit | E18: Test environment seeded; authorized Warehouse Keeper; Administrator; transaction isolated and resettable. | F18: Not Run | O18: Type: Positive; Role: Warehouse Keeper; Administrator; Level: System / Integration SRS v1.8 / BR: 3.8.3; BR-44 Test data: Authorized write-off with reason/evidence Source: https://github.com/GFA26SE63/FSCM-Backend/blob/0f56f7099f07aa60d76673e6b6a57a2b606fb833/src/FSCM.Application/Features/Inventory/InventoryLockService.cs Automation: Manual / candidate Version: 1.3; Actual result: —; Evidence: —
A19: FT-031-N | B19: Write-off unusable quantity Negative — Remove stock before approval | C19: 1. Seed isolated FSCM fixture with required SKU, retailer, warehouse, roles and state; record starting stock/payment/ledger snapshots. 2. Sign in as Warehouse Keeper; Administrator; perform scenario: Remove stock before approval. 3. Submit both the valid operation and the specified invalid/boundary input. 4. Compare response, persisted state, actor audit, once-only effects and unchanged records against the expected result. | D19: Keep inventory unchanged while pending | E19: Test environment seeded; authorized Warehouse Keeper; Administrator; transaction isolated and resettable. | F19: Not Run | O19: Type: Negative; Role: Warehouse Keeper; Administrator; Level: System / Integration SRS v1.8 / BR: 3.8.3; BR-44 Test data: Remove stock before approval Source: https://github.com/GFA26SE63/FSCM-Backend/blob/0f56f7099f07aa60d76673e6b6a57a2b606fb833/src/FSCM.Application/Features/Inventory/InventoryLockService.cs Automation: Manual / candidate Version: 1.3; Actual result: —; Evidence: —
A20: FT-031-B | B20: Write-off unusable quantity Boundary — Write-off exceeds available quantity | C20: 1. Seed isolated FSCM fixture with required SKU, retailer, warehouse, roles and state; record starting stock/payment/ledger snapshots. 2. Sign in as Warehouse Keeper; Administrator; perform scenario: Write-off exceeds available quantity. 3. Submit both the valid operation and the specified invalid/boundary input. 4. Compare response, persisted state, actor audit, once-only effects and unchanged records against the expected result. | D20: Reject invalid or over-limit quantity | E20: Test environment seeded; authorized Warehouse Keeper; Administrator; transaction isolated and resettable. | F20: Not Run | O20: Type: Boundary; Role: Warehouse Keeper; Administrator; Level: System / Integration SRS v1.8 / BR: 3.8.3; BR-44 Test data: Write-off exceeds available quantity Source: https://github.com/GFA26SE63/FSCM-Backend/blob/0f56f7099f07aa60d76673e6b6a57a2b606fb833/src/FSCM.Application/Features/Inventory/InventoryLockService.cs Automation: Manual / candidate Version: 1.3; Actual result: —; Evidence: —
A21: FT-032-P | B21: Generate and split batch QR label Positive — Create and split eligible quantity label | C21: 1. Seed isolated FSCM fixture with required SKU, retailer, warehouse, roles and state; record starting stock/payment/ledger snapshots. 2. Sign in as Warehouse Keeper; perform scenario: Create and split eligible quantity label. 3. Submit both the valid operation and the specified invalid/boundary input. 4. Compare response, persisted state, actor audit, once-only effects and unchanged records against the expected result. | D21: Maintain traceable QR lineage | E21: Test environment seeded; authorized Warehouse Keeper; transaction isolated and resettable. | F21: Not Run | O21: Type: Positive; Role: Warehouse Keeper; Level: System / Integration SRS v1.8 / BR: 3.9.1; BR-10 Test data: Create and split eligible quantity label Source: https://github.com/GFA26SE63/FSCM-Backend/blob/0f56f7099f07aa60d76673e6b6a57a2b606fb833/src/FSCM.Application/Features/QrLabels/QrLabelService.cs Automation: Manual / candidate Version: 1.3; Actual result: —; Evidence: —
A22: FT-032-N | B22: Generate and split batch QR label Negative — Split quantity larger than parent | C22: 1. Seed isolated FSCM fixture with required SKU, retailer, warehouse, roles and state; record starting stock/payment/ledger snapshots. 2. Sign in as Warehouse Keeper; perform scenario: Split quantity larger than parent. 3. Submit both the valid operation and the specified invalid/boundary input. 4. Compare response, persisted state, actor audit, once-only effects and unchanged records against the expected result. | D22: Reject over-split | E22: Test environment seeded; authorized Warehouse Keeper; transaction isolated and resettable. | F22: Not Run | O22: Type: Negative; Role: Warehouse Keeper; Level: System / Integration SRS v1.8 / BR: 3.9.1; BR-10 Test data: Split quantity larger than parent Source: https://github.com/GFA26SE63/FSCM-Backend/blob/0f56f7099f07aa60d76673e6b6a57a2b606fb833/src/FSCM.Application/Features/QrLabels/QrLabelService.cs Automation: Manual / candidate Version: 1.3; Actual result: —; Evidence: —
A23: FT-032-B | B23: Generate and split batch QR label Boundary — Child quantities equal parent | C23: 1. Seed isolated FSCM fixture with required SKU, retailer, warehouse, roles and state; record starting stock/payment/ledger snapshots. 2. Sign in as Warehouse Keeper; perform scenario: Child quantities equal parent. 3. Submit both the valid operation and the specified invalid/boundary input. 4. Compare response, persisted state, actor audit, once-only effects and unchanged records against the expected result. | D23: Conserve quantity and preserve parent linkage | E23: Test environment seeded; authorized Warehouse Keeper; transaction isolated and resettable. | F23: Not Run | O23: Type: Boundary; Role: Warehouse Keeper; Level: System / Integration SRS v1.8 / BR: 3.9.1; BR-10 Test data: Child quantities equal parent Source: https://github.com/GFA26SE63/FSCM-Backend/blob/0f56f7099f07aa60d76673e6b6a57a2b606fb833/src/FSCM.Application/Features/QrLabels/QrLabelService.cs Automation: Manual / candidate Version: 1.3; Actual result: —; Evidence: —

Sheet Picking & QR
A2: Feature | B2: Picking & QR | R2: Passed
A3: Test requirement | B3: Verify picking lists are issued once per warehouse only after valid Purchase Order conversion. Validate QR batch/warehouse scans and order splits, complete readiness, and dispatch blocks for missing prepaid verification, open locks or picking exceptions despite Ready flags. | R3: Failed
A4: Number of TCs | B4: =COUNTA(A12:A25) -> 14 | R4: Pending
A5: Testing Round | B5: Passed | C5: Failed | D5: Pending | E5: N/A | R5: N/A
A6: Round 1 | B6: =COUNTIF(F12:F25,"Passed")+COUNTIF(F12:F25,"Pass") -> 0 | C6: =COUNTIF(F12:F25,"Failed")+COUNTIF(F12:F25,"Fail") -> 0 | D6: =COUNTIF(F12:F25,"Not Run")+COUNTIF(F12:F25,"Blocked")+COUNTIF(F12:F25,"Pending")+COUNTBLANK(F12:F25) -> 14 | E6: =COUNTIF(F12:F25,"N/A") -> 0
A7: Round 2 | B7: =COUNTIF(I12:I25,"Passed")+COUNTIF(I12:I25,"Pass") -> 0 | C7: =COUNTIF(I12:I25,"Failed")+COUNTIF(I12:I25,"Fail") -> 0 | D7: =COUNTIF(I12:I25,"Not Run")+COUNTIF(I12:I25,"Blocked")+COUNTIF(I12:I25,"Pending") -> 0 | E7: =COUNTIF(I12:I25,"N/A") -> 0
A8: Round 3 | B8: =COUNTIF(L12:L25,"Passed")+COUNTIF(L12:L25,"Pass") -> 0 | C8: =COUNTIF(L12:L25,"Failed")+COUNTIF(L12:L25,"Fail") -> 0 | D8: =COUNTIF(L12:L25,"Not Run")+COUNTIF(L12:L25,"Blocked")+COUNTIF(L12:L25,"Pending") -> 0 | E8: =COUNTIF(L12:L25,"N/A") -> 0
A10: Test Case ID | B10: Test Case Description | C10: Test Case Procedure | D10: Expected Results | E10: Pre-conditions | F10: Round 1 | G10: Test date | H10: Tester | I10: Round 2 | J10: Test date | K10: Tester | L10: Round 3 | M10: Test date | N10: Tester | O10: Note
A11: Picking & QR — FSCM scenarios
A12: FT-033-P | B12: Issue warehouse picking after Purchase Order conversion | C12: 1. Approve allocation price. 2. Retailer accepts quote. 3. Verify prepaid transfer or approved credit term. 4. Convert to PO. 5. Issue warehouse picking. | D12: Only a valid PO creates one picking list per warehouse with gather/split links to approved batch net price. | E12: Test environment seeded; authorized System; Warehouse Keeper; transaction isolated and resettable. | F12: Not Run | O12: Type: Positive; Role: System; Warehouse Keeper; Level: System / Integration SRS v1.8 / BR: 3.9.1; BR-45 Test data: Approved run with complete orders Source: https://github.com/GFA26SE63/FSCM-Backend/blob/0f56f7099f07aa60d76673e6b6a57a2b606fb833/src/FSCM.Application/Features/AllocationRuns/RunPickingIssueService.cs Automation: Manual / candidate Version: 1.3; Actual result: —; Evidence: —
A13: FT-033-N | B13: No picking before quotation acceptance or valid payment choice | C13: 1. Seed approved plan but unaccepted quote/unverified prepaid/ineligible credit term. 2. Request picking release. | D13: No picking list/PO released until accepted quote and compliant prepaid verification or approved deferred credit. | E13: Test environment seeded; authorized System; Warehouse Keeper; transaction isolated and resettable. | F13: Not Run | O13: Type: Negative; Role: System; Warehouse Keeper; Level: System / Integration SRS v1.8 / BR: 3.9.1; BR-45 Test data: Unapproved run requests picking Source: https://github.com/GFA26SE63/FSCM-Backend/blob/0f56f7099f07aa60d76673e6b6a57a2b606fb833/src/FSCM.Application/Features/AllocationRuns/RunPickingIssueService.cs Automation: Manual / candidate Version: 1.3; Actual result: —; Evidence: —
A14: FT-033-B | B14: Release approved warehouse picking list Boundary — One batch serves multiple orders | C14: 1. Seed isolated FSCM fixture with required SKU, retailer, warehouse, roles and state; record starting stock/payment/ledger snapshots. 2. Sign in as System; Warehouse Keeper; perform scenario: One batch serves multiple orders. 3. Submit both the valid operation and the specified invalid/boundary input. 4. Compare response, persisted state, actor audit, once-only effects and unchanged records against the expected result. | D14: Aggregate once while preserving order-line splits | E14: Test environment seeded; authorized System; Warehouse Keeper; transaction isolated and resettable. | F14: Not Run | O14: Type: Boundary; Role: System; Warehouse Keeper; Level: System / Integration SRS v1.8 / BR: 3.9.1; BR-45 Test data: One batch serves multiple orders Source: https://github.com/GFA26SE63/FSCM-Backend/blob/0f56f7099f07aa60d76673e6b6a57a2b606fb833/src/FSCM.Application/Features/AllocationRuns/RunPickingIssueService.cs Automation: Manual / candidate Version: 1.3; Actual result: —; Evidence: —
A15: FT-034-P | B15: Scan picking item and confirm readiness Positive — Scan correct warehouse/batch and quantity | C15: 1. Seed isolated FSCM fixture with required SKU, retailer, warehouse, roles and state; record starting stock/payment/ledger snapshots. 2. Sign in as Warehouse Keeper; perform scenario: Scan correct warehouse/batch and quantity. 3. Submit both the valid operation and the specified invalid/boundary input. 4. Compare response, persisted state, actor audit, once-only effects and unchanged records against the expected result. | D15: Record scan and mark ready without stock issue | E15: Test environment seeded; authorized Warehouse Keeper; transaction isolated and resettable. | F15: Not Run | O15: Type: Positive; Role: Warehouse Keeper; Level: System / Integration SRS v1.8 / BR: 3.9.1; BR-45–46 Test data: Scan correct warehouse/batch and quantity Source: https://github.com/GFA26SE63/FSCM-Backend/blob/0f56f7099f07aa60d76673e6b6a57a2b606fb833/src/FSCM.Application/Features/Picking/PickingService.cs Automation: Manual / candidate Version: 1.3; Actual result: —; Evidence: —
A16: FT-034-N | B16: Scan picking item and confirm readiness Negative — Scan wrong warehouse or batch | C16: 1. Seed isolated FSCM fixture with required SKU, retailer, warehouse, roles and state; record starting stock/payment/ledger snapshots. 2. Sign in as Warehouse Keeper; perform scenario: Scan wrong warehouse or batch. 3. Submit both the valid operation and the specified invalid/boundary input. 4. Compare response, persisted state, actor audit, once-only effects and unchanged records against the expected result. | D16: Reject inconsistent scan | E16: Test environment seeded; authorized Warehouse Keeper; transaction isolated and resettable. | F16: Not Run | O16: Type: Negative; Role: Warehouse Keeper; Level: System / Integration SRS v1.8 / BR: 3.9.1; BR-45–46 Test data: Scan wrong warehouse or batch Source: https://github.com/GFA26SE63/FSCM-Backend/blob/0f56f7099f07aa60d76673e6b6a57a2b606fb833/src/FSCM.Application/Features/Picking/PickingService.cs Automation: Manual / candidate Version: 1.3; Actual result: —; Evidence: —
A17: FT-034-B | B17: Scan picking item and confirm readiness Boundary — Duplicate scan with same idempotency key | C17: 1. Seed isolated FSCM fixture with required SKU, retailer, warehouse, roles and state; record starting stock/payment/ledger snapshots. 2. Sign in as Warehouse Keeper; perform scenario: Duplicate scan with same idempotency key. 3. Submit both the valid operation and the specified invalid/boundary input. 4. Compare response, persisted state, actor audit, once-only effects and unchanged records against the expected result. | D17: No double picked quantity when retried | E17: Test environment seeded; authorized Warehouse Keeper; transaction isolated and resettable. | F17: Not Run | O17: Type: Boundary; Role: Warehouse Keeper; Level: System / Integration SRS v1.8 / BR: 3.9.1; BR-45–46 Test data: Duplicate scan with same idempotency key Source: https://github.com/GFA26SE63/FSCM-Backend/blob/0f56f7099f07aa60d76673e6b6a57a2b606fb833/src/FSCM.Application/Features/Picking/PickingService.cs Automation: Manual / candidate Version: 1.3; Actual result: —; Evidence: —
A18: FT-035-P | B18: Confirm dispatch idempotently Positive — All warehouse portions ready and payment eligible | C18: 1. Seed isolated FSCM fixture with required SKU, retailer, warehouse, roles and state; record starting stock/payment/ledger snapshots. 2. Sign in as Operator; Warehouse Keeper; perform scenario: All warehouse portions ready and payment eligible. 3. Submit both the valid operation and the specified invalid/boundary input. 4. Compare response, persisted state, actor audit, once-only effects and unchanged records against the expected result. | D18: Move reserved and OnHand only once | E18: Test environment seeded; authorized Operator; Warehouse Keeper; transaction isolated and resettable. | F18: Not Run | O18: Type: Positive; Role: Operator; Warehouse Keeper; Level: System / Integration SRS v1.8 / BR: 3.9.1; BR-46–47 Test data: All warehouse portions ready and payment eligible Source: https://github.com/GFA26SE63/FSCM-Backend/blob/0f56f7099f07aa60d76673e6b6a57a2b606fb833/src/FSCM.Application/Features/Deliveries/DeliveryService.cs Automation: Manual / candidate Version: 1.3; Actual result: —; Evidence: —
A19: FT-035-N | B19: Dispatch requires all warehouses Ready and no blocking exception | C19: 1. Mark all picking lists Ready. 2. Keep one inventory lock or picking exception unresolved, or unpaid prepaid. 3. Attempt dispatch. | D19: Dispatch remains blocked by open stock lock, picking exception, or missing prepaid even when every warehouse is marked Ready. | E19: Test environment seeded; authorized Operator; Warehouse Keeper; transaction isolated and resettable. | F19: Not Run | O19: Type: Negative; Role: Operator; Warehouse Keeper; Level: System / Integration SRS v1.8 / BR: 3.9.1; BR-46–47 Test data: One portion not ready Source: https://github.com/GFA26SE63/FSCM-Backend/blob/0f56f7099f07aa60d76673e6b6a57a2b606fb833/src/FSCM.Application/Features/Deliveries/DeliveryService.cs Automation: Manual / candidate Version: 1.3; Actual result: —; Evidence: —
A20: FT-035-B | B20: Confirm dispatch idempotently Boundary — Send same dispatch confirmation twice | C20: 1. Seed isolated FSCM fixture with required SKU, retailer, warehouse, roles and state; record starting stock/payment/ledger snapshots. 2. Sign in as Operator; Warehouse Keeper; perform scenario: Send same dispatch confirmation twice. 3. Submit both the valid operation and the specified invalid/boundary input. 4. Compare response, persisted state, actor audit, once-only effects and unchanged records against the expected result. | D20: Second command is no-op with same result | E20: Test environment seeded; authorized Operator; Warehouse Keeper; transaction isolated and resettable. | F20: Not Run | O20: Type: Boundary; Role: Operator; Warehouse Keeper; Level: System / Integration SRS v1.8 / BR: 3.9.1; BR-46–47 Test data: Send same dispatch confirmation twice Source: https://github.com/GFA26SE63/FSCM-Backend/blob/0f56f7099f07aa60d76673e6b6a57a2b606fb833/src/FSCM.Application/Features/Deliveries/DeliveryService.cs Automation: Manual / candidate Version: 1.3; Actual result: —; Evidence: —
A21: R5-TC-PICK-01 | B21: PO conversion with verified prepaid | C21: 1. Verify transfer; 2. Create PO; 3. Issue warehouse picking. | D21: PO + warehouse slips created exactly once; no slips prior to verification. | E21: Approved quote accepted by retailer; Prepaid bank transfer verified. Test data: Valid bank proof, authorized Operator. | F21: Not Run | O21: Requirement/Traceability: SRS v1.8 §3.6.6/§3.9.1; BR-51/66/72; M08/WF01/TS01 Priority: P1; Level: Integration / System / Acceptance Version: 1.3; Actual result: —; Evidence: —
A22: R5-TC-PICK-02 | B22: PO conversion with approved Deferred | C22: 1. Choose Deferred; 2. Convert; 3. Issue slips. | D22: PO allowed without prepaid if term valid; due date later tied to actual receipt. | E22: Accepted approved quote and active term. Test data: Retailer term=14 days approved. | F22: Not Run | O22: Requirement/Traceability: SRS v1.8 §3.6.6/§3.9.1; BR-51/73; M08/WF01/TS02 Priority: P1; Level: Integration / System / Acceptance Version: 1.3; Actual result: —; Evidence: —
A23: R5-TC-PICK-03 | B23: Incomplete picking prevents dispatch | C23: 1. Complete W1; 2. Request dispatch. | D23: Dispatch blocked until every warehouse portion fully picked. | E23: PO with shipments from W1 and W2. Test data: W1 Ready, W2 not ready. | F23: Not Run | O23: Requirement/Traceability: SRS v1.8 §3.9.1; AC-3.9.1-01; M08/WF02/TS01 Priority: P1; Level: Integration / System / Acceptance Version: 1.3; Actual result: —; Evidence: —
... A25: R5-TC-PICK-05 | B25: Only Administrator resolves picking exception | C25: 1. Keeper attempts resolve; 2. Admin adjudicates; 3. Recheck readiness. | D25: Keeper cannot finalize exception decision; Admin action audited, recovery required before dispatch. | E25: Pick exception raised by Keeper. Test data: Keeper resolve attempt, Admin decision. | F25: Not Run | O25: Requirement/Traceability: R5-07; SDD PICKING_EXCEPTION; M08/WF02/TS03 Priority: P1; Level: Integration / System / Acceptance Version: 1.3; Actual result: —; Evidence: —

Sheet Delivery & Receipt
A2: Feature | B2: Delivery & Receipt | R2: Passed
A3: Test requirement | B3: Validate exact shipment quantities received across every warehouse, including zero/partial/damaged<=received; never mark Delivered or Completed for an order with missing physical units, even if complaint settled. Keep received discrepancy, no automatic stock restock or loyalty before full receipt. | R3: Failed
A4: Number of TCs | B4: =COUNTA(A12:A24) -> 13 | R4: Pending
A5: Testing Round | B5: Passed | C5: Failed | D5: Pending | E5: N/A | R5: N/A
A6: Round 1 | B6: =COUNTIF(F12:F24,"Passed")+COUNTIF(F12:F24,"Pass") -> 0 | C6: =COUNTIF(F12:F24,"Failed")+COUNTIF(F12:F24,"Fail") -> 0 | D6: =COUNTIF(F12:F24,"Not Run")+COUNTIF(F12:F24,"Blocked")+COUNTIF(F12:F24,"Pending")+COUNTBLANK(F12:F24) -> 13 | E6: =COUNTIF(F12:F24,"N/A") -> 0
A7: Round 2 | B7: =COUNTIF(I12:I24,"Passed")+COUNTIF(I12:I24,"Pass") -> 0 | C7: =COUNTIF(I12:I24,"Failed")+COUNTIF(I12:I24,"Fail") -> 0 | D7: =COUNTIF(I12:I24,"Not Run")+COUNTIF(I12:I24,"Blocked")+COUNTIF(I12:I24,"Pending") -> 0 | E7: =COUNTIF(I12:I24,"N/A") -> 0
A8: Round 3 | B8: =COUNTIF(L12:L24,"Passed")+COUNTIF(L12:L24,"Pass") -> 0 | C8: =COUNTIF(L12:L24,"Failed")+COUNTIF(L12:L24,"Fail") -> 0 | D8: =COUNTIF(L12:L24,"Not Run")+COUNTIF(L12:L24,"Blocked")+COUNTIF(L12:L24,"Pending") -> 0 | E8: =COUNTIF(L12:L24,"N/A") -> 0
A10: Test Case ID | B10: Test Case Description | C10: Test Case Procedure | D10: Expected Results | E10: Pre-conditions | F10: Round 1 | G10: Test date | H10: Tester | I10: Round 2 | J10: Test date | K10: Tester | L10: Round 3 | M10: Test date | N10: Tester | O10: Note
A11: Delivery & Receipt — FSCM scenarios
A12: FT-036-P | B12: Assign vehicle and driver Positive — Valid shipment and authorized master data | C12: 1. Seed isolated FSCM fixture with required SKU, retailer, warehouse, roles and state; record starting stock/payment/ledger snapshots. 2. Sign in as Operator; perform scenario: Valid shipment and authorized master data. 3. Submit both the valid operation and the specified invalid/boundary input. 4. Compare response, persisted state, actor audit, once-only effects and unchanged records against the expected result. | D12: Store assignment snapshot for one shipment | E12: Test environment seeded; authorized Operator; transaction isolated and resettable. | F12: Not Run | O12: Type: Positive; Role: Operator; Level: System / Integration SRS v1.8 / BR: 3.13.1; BR-48 Test data: Valid shipment and authorized master data Source: https://github.com/GFA26SE63/FSCM-Backend/blob/0f56f7099f07aa60d76673e6b6a57a2b606fb833/src/FSCM.API/Controllers/DeliveriesController.cs Automation: Manual / candidate Version: 1.3; Actual result: —; Evidence: —
A13: FT-036-N | B13: Assign vehicle and driver Negative — Select unavailable/nonexistent driver | C13: 1. Seed isolated FSCM fixture with required SKU, retailer, warehouse, roles and state; record starting stock/payment/ledger snapshots. 2. Sign in as Operator; perform scenario: Select unavailable/nonexistent driver. 3. Submit both the valid operation and the specified invalid/boundary input. 4. Compare response, persisted state, actor audit, once-only effects and unchanged records against the expected result. | D13: Reject invalid assignment | E13: Test environment seeded; authorized Operator; transaction isolated and resettable. | F13: Not Run | O13: Type: Negative; Role: Operator; Level: System / Integration SRS v1.8 / BR: 3.13.1; BR-48 Test data: Select unavailable/nonexistent driver Source: https://github.com/GFA26SE63/FSCM-Backend/blob/0f56f7099f07aa60d76673e6b6a57a2b606fb833/src/FSCM.API/Controllers/DeliveriesController.cs Automation: Manual / candidate Version: 1.3; Actual result: —; Evidence: —
A14: FT-036-B | B14: Assign vehicle and driver Boundary — Multi-warehouse order has separate shipment | C14: 1. Seed isolated FSCM fixture with required SKU, retailer, warehouse, roles and state; record starting stock/payment/ledger snapshots. 2. Sign in as Operator; perform scenario: Multi-warehouse order has separate shipment. 3. Submit both the valid operation and the specified invalid/boundary input. 4. Compare response, persisted state, actor audit, once-only effects and unchanged records against the expected result. | D14: Retain separate vehicle/person per warehouse shipment | E14: Test environment seeded; authorized Operator; transaction isolated and resettable. | F14: Not Run | O14: Type: Boundary; Role: Operator; Level: System / Integration SRS v1.8 / BR: 3.13.1; BR-48 Test data: Multi-warehouse order has separate shipment Source: https://github.com/GFA26SE63/FSCM-Backend/blob/0f56f7099f07aa60d76673e6b6a57a2b606fb833/src/FSCM.API/Controllers/DeliveriesController.cs Automation: Manual / candidate Version: 1.3; Actual result: —; Evidence: —
A15: FT-037-P | B15: Receipt records received, missing and damaged by shipment | C15: 1. Scan expected QR label. 2. Submit received=0, missing=all for a line; then submit partially received with damaged≤received. 3. Inspect state. | D15: Valid quantities are recorded per shipment. Partial/zero received remains discrepancy; no automatic return to inventory, Delivered status or loyalty award. | E15: Test environment seeded; authorized Retailer; transaction isolated and resettable. | F15: Not Run | O15: Type: Positive; Role: Retailer; Level: System / Integration SRS v1.8 / BR: 3.9.2; BR-49 Test data: Retailer scans assigned issued QR Source: https://github.com/GFA26SE63/FSCM-Backend/blob/0f56f7099f07aa60d76673e6b6a57a2b606fb833/src/FSCM.Application/Features/Deliveries/DeliveryService.cs Automation: Manual / candidate Version: 1.3; Actual result: —; Evidence: —
A16: FT-037-N | B16: Confirm retailer receipt by QR Negative — Scan QR for another retailer's order | C16: 1. Seed isolated FSCM fixture with required SKU, retailer, warehouse, roles and state; record starting stock/payment/ledger snapshots. 2. Sign in as Retailer; perform scenario: Scan QR for another retailer's order. 3. Submit both the valid operation and the specified invalid/boundary input. 4. Compare response, persisted state, actor audit, once-only effects and unchanged records against the expected result. | D16: Reject unrelated QR | E16: Test environment seeded; authorized Retailer; transaction isolated and resettable. | F16: Not Run | O16: Type: Negative; Role: Retailer; Level: System / Integration SRS v1.8 / BR: 3.9.2; BR-49 Test data: Scan QR for another retailer's order Source: https://github.com/GFA26SE63/FSCM-Backend/blob/0f56f7099f07aa60d76673e6b6a57a2b606fb833/src/FSCM.Application/Features/Deliveries/DeliveryService.cs Automation: Manual / candidate Version: 1.3; Actual result: —; Evidence: —
A17: FT-037-B | B17: All shipment confirmations do not imply full actual receipt | C17: 1. Confirm all shipment records but report one missing quantity; 2. Check status and loyalty. | D17: Order not Delivered and points blocked until complete actual quantity resolution; no automatic stock return. | E17: Test environment seeded; authorized Retailer; transaction isolated and resettable. | F17: Not Run | O17: Type: Boundary; Role: Retailer; Level: System / Integration SRS v1.8 / BR: 3.9.2; BR-49 Test data: Last outstanding shipment confirmed Source: https://github.com/GFA26SE63/FSCM-Backend/blob/0f56f7099f07aa60d76673e6b6a57a2b606fb833/src/FSCM.Application/Features/Deliveries/DeliveryService.cs Automation: Manual / candidate Version: 1.3; Actual result: —; Evidence: —
A18: R5-TC-DISP-01 | B18: No prepaid confirmation blocks dispatch | C18: Mark all picking lists Ready but leave prepaid unpaid, locked batch or open picking exception; attempt dispatch per blocker. | D18: Dispatch blocked for unpaid prepaid, active lock or unresolved exception regardless of Ready flags. | E18: Ready per warehouse, with each blocker seeded in isolation. | F18: Not Run | O18: Requirement/Traceability: R5-01/R5-05; SRS v1.8 §3.13.1; M08/WF03/TS01 Priority: P1; Level: Integration / System / Acceptance Version: 1.3; Actual result: —; Evidence: —
A19: R5-TC-DISP-02 | B19: Dispatch once and preserve stock ledger | C19: After all Ready and no blockers, dispatch twice with same operation key; inspect physical/reserved/label state. | D19: One dispatch per shipment; OnHand decreases once and reserved consumed once; stable repeated response. | E19: Paid prepaid PO or valid deferred PO; no lock/exception; all portions Ready. | F19: Not Run | O19: Requirement/Traceability: SRS v1.8 §3.9.1/§3.13.1; M08/WF03/TS02 Priority: P1; Level: Integration / System / Acceptance Version: 1.3; Actual result: —; Evidence: —
A20: R5-TC-DEL-01 | B20: Delivery retry with Administrator decision | C20: Record failed delivery with evidence; request retry by unauthorized actor, then by authorized decision maker. | D20: Only authorized settlement/retry action accepted; no Delivered, points or automatic stock return; audit both decisions. | E20: Shipment failed, ETA/MLOR/deadline still feasible; alternate invalid-feasibility fixture. | F20: Not Run | O20: Requirement/Traceability: SRS v1.8 §3.13.1; BR-76; R5-07; M09/WF01/TS01 Priority: P1; Level: Integration / System / Acceptance Version: 1.3; Actual result: —; Evidence: —
A21: R5-TC-REC-01 | B21: Receipt received zero | C21: Confirm shipment with expected=10, received=0, missing=10; inspect order, warehouse stock and points. | D21: Valid zero-receipt discrepancy recorded; order not Delivered and points not posted; no automatic inventory return. | E21: Issued QR for one shipment; Retailer actor; expected=10 cartons. | F21: Not Run | O21: Requirement/Traceability: R5-07; SRS v1.8 §3.9.2; M09/WF02/TS01 Priority: P1; Level: Integration / System / Acceptance Version: 1.3; Actual result: —; Evidence: —
A22: R5-TC-REC-02 | B22: Partial receipt with damaged bound | C22: Confirm received=7, missing=3, damaged=7; retry with damaged=8; compare validation. | D22: Damaged≤received is accepted; damaged=8 rejected; discrepancy/evidence retained; no unsanctioned stock effect. | E22: Shipment expected=10; actual received=7; missing=3. | F22: Not Run | O22: Requirement/Traceability: SRS v1.8 §3.9.2; R5-07; M09/WF02/TS02 Priority: P1; Level: Integration / System / Acceptance Version: 1.3; Actual result: —; Evidence: —
A23: R5-TC-REC-03 | B23: All shipments confirmed but incomplete total | C23: Confirm W1 fully and W2 with missing=2, even though both shipments are marked confirmed; inspect order. | D23: Order remains not Delivered and points blocked until all actual quantities settled by authorized flow. | E23: W1 expected=10 received=10; W2 expected=10 received=8 missing=2. | F23: Not Run | O23: Requirement/Traceability: R5-07; SRS v1.8 §3.9.2; M09/WF02/TS03 Priority: P1; Level: Integration / System / Acceptance Version: 1.3; Actual result: —; Evidence: —
A24: R5-TC-REC-04 | B24: Full receipt and idempotent confirmation | C24: Retailer confirms full QR receipts for both warehouse portions, then submits repeated confirmation. | D24: Exactly-once full receipt and Delivered only when all actual quantities satisfied; repeated scan cannot double-post. | E24: Two shipments; all labels belong to same retailer; expected=20 received=20. | F24: Not Run | O24: Requirement/Traceability: SRS v1.8 §3.9.2; AC-3.9.2-01; M09/WF02/TS04 Priority: P1; Level: Integration / System / Acceptance Version: 1.3; Actual result: —; Evidence: —

Sheet Complaints & Refunds
A2: Feature | B2: Complaints & Refunds | R2: Passed
A3: Test requirement | B3: Verify receipt complaints retain affected batch, shipment and evidence; only authorized actors decide adjustments or verify manual refunds. Cap adjustments/refunds by affected batch net price, reject duplicate/over-cap actions, and allow evidence supplementation without double loyalty deductions. | R3: Failed
A4: Number of TCs | B4: =COUNTA(A12:A26) -> 15 | R4: Pending
A5: Testing Round | B5: Passed | C5: Failed | D5: Pending | E5: N/A | R5: N/A
A6: Round 1 | B6: =COUNTIF(F12:F26,"Passed")+COUNTIF(F12:F26,"Pass") -> 0 | C6: =COUNTIF(F12:F26,"Failed")+COUNTIF(F12:F26,"Fail") -> 0 | D6: =COUNTIF(F12:F26,"Not Run")+COUNTIF(F12:F26,"Blocked")+COUNTIF(F12:F26,"Pending")+COUNTBLANK(F12:F26) -> 15 | E6: =COUNTIF(F12:F26,"N/A") -> 0
A7: Round 2 | B7: =COUNTIF(I12:I26,"Passed")+COUNTIF(I12:I26,"Pass") -> 0 | C7: =COUNTIF(I12:I26,"Failed")+COUNTIF(I12:I26,"Fail") -> 0 | D7: =COUNTIF(I12:I26,"Not Run")+COUNTIF(I12:I26,"Blocked")+COUNTIF(I12:I26,"Pending") -> 0 | E7: =COUNTIF(I12:I26,"N/A") -> 0
A8: Round 3 | B8: =COUNTIF(L12:L26,"Passed")+COUNTIF(L12:L26,"Pass") -> 0 | C8: =COUNTIF(L12:L26,"Failed")+COUNTIF(L12:L26,"Fail") -> 0 | D8: =COUNTIF(L12:L26,"Not Run")+COUNTIF(L12:L26,"Blocked")+COUNTIF(L12:L26,"Pending") -> 0 | E8: =COUNTIF(L12:L26,"N/A") -> 0
A10: Test Case ID | B10: Test Case Description | C10: Test Case Procedure | D10: Expected Results | E10: Pre-conditions | F10: Round 1 | G10: Test date | H10: Tester | I10: Round 2 | J10: Test date | K10: Tester | L10: Round 3 | M10: Test date | N10: Tester | O10: Note
A11: Complaints & Refunds — FSCM scenarios
A12: FT-038-P | B12: Report damaged/missing goods Positive — Complaint on received batch with evidence | C12: 1. Seed isolated FSCM fixture with required SKU, retailer, warehouse, roles and state; record starting stock/payment/ledger snapshots. 2. Sign in as Retailer; Operator; perform scenario: Complaint on received batch with evidence. 3. Submit both the valid operation and the specified invalid/boundary input. 4. Compare response, persisted state, actor audit, once-only effects and unchanged records against the expected result. | D12: Create independent complaint linked to batch/shipment | E12: Test environment seeded; authorized Retailer; Operator; transaction isolated and resettable. | F12: Not Run | O12: Type: Positive; Role: Retailer; Operator; Level: System / Integration SRS v1.8 / BR: 3.9.3; BR-50 Test data: Complaint on received batch with evidence Source: https://github.com/GFA26SE63/FSCM-Backend/blob/0f56f7099f07aa60d76673e6b6a57a2b606fb833/src/FSCM.API/Controllers/ComplaintsController.cs Automation: Manual / candidate Version: 1.3; Actual result: —; Evidence: —
A13: FT-038-N | B13: Report damaged/missing goods Negative — Complaint on someone else's order | C13: 1. Seed isolated FSCM fixture with required SKU, retailer, warehouse, roles and state; record starting stock/payment/ledger snapshots. 2. Sign in as Retailer; Operator; perform scenario: Complaint on someone else's order. 3. Submit both the valid operation and the specified invalid/boundary input. 4. Compare response, persisted state, actor audit, once-only effects and unchanged records against the expected result. | D13: Block unauthorized complaint | E13: Test environment seeded; authorized Retailer; Operator; transaction isolated and resettable. | F13: Not Run | O13: Type: Negative; Role: Retailer; Operator; Level: System / Integration SRS v1.8 / BR: 3.9.3; BR-50 Test data: Complaint on someone else's order Source: https://github.com/GFA26SE63/FSCM-Backend/blob/0f56f7099f07aa60d76673e6b6a57a2b606fb833/src/FSCM.API/Controllers/ComplaintsController.cs Automation: Manual / candidate Version: 1.3; Actual result: —; Evidence: —
A14: FT-038-B | B14: Report damaged/missing goods Boundary — Issue submitted after already delivered status | C14: 1. Seed isolated FSCM fixture with required SKU, retailer, warehouse, roles and state; record starting stock/payment/ledger snapshots. 2. Sign in as Retailer; Operator; perform scenario: Issue submitted after already delivered status. 3. Submit both the valid operation and the specified invalid/boundary input. 4. Compare response, persisted state, actor audit, once-only effects and unchanged records against the expected result. | D14: Do not automatically reverse Delivered or stock | E14: Test environment seeded; authorized Retailer; Operator; transaction isolated and resettable. | F14: Not Run | O14: Type: Boundary; Role: Retailer; Operator; Level: System / Integration SRS v1.8 / BR: 3.9.3; BR-50 Test data: Issue submitted after already delivered status Source: https://github.com/GFA26SE63/FSCM-Backend/blob/0f56f7099f07aa60d76673e6b6a57a2b606fb833/src/FSCM.API/Controllers/ComplaintsController.cs Automation: Manual / candidate Version: 1.3; Actual result: —; Evidence: —
A15: FT-041-P | B15: Handle manual refund and evidence Positive — Submit refund with external proof and independent verifier | C15: 1. Seed isolated FSCM fixture with required SKU, retailer, warehouse, roles and state; record starting stock/payment/ledger snapshots. 2. Sign in as Operator; Administrator; perform scenario: Submit refund with external proof and independent verifier. 3. Submit both the valid operation and the specified invalid/boundary input. 4. Compare response, persisted state, actor audit, once-only effects and unchanged records against the expected result. | D15: Keep pending until independent Admin verification | E15: Test environment seeded; authorized Operator; Administrator; transaction isolated and resettable. | F15: Not Run | O15: Type: Positive; Role: Operator; Administrator; Level: System / Integration SRS v1.8 / BR: 3.10.4; BR-66–70 Test data: Submit refund with external proof and independent verifier Source: https://github.com/GFA26SE63/FSCM-Backend/blob/0f56f7099f07aa60d76673e6b6a57a2b606fb833/src/FSCM.Application/Features/Refunds/RefundService.cs Automation: Manual / candidate Version: 1.3; Actual result: —; Evidence: —
A16: FT-041-N | B16: Handle manual refund and evidence Negative — Refund without evidence | C16: 1. Seed isolated FSCM fixture with required SKU, retailer, warehouse, roles and state; record starting stock/payment/ledger snapshots. 2. Sign in as Operator; Administrator; perform scenario: Refund without evidence. 3. Submit both the valid operation and the specified invalid/boundary input. 4. Compare response, persisted state, actor audit, once-only effects and unchanged records against the expected result. | D16: Reject absent evidence/self-approval | E16: Test environment seeded; authorized Operator; Administrator; transaction isolated and resettable. | F16: Not Run | O16: Type: Negative; Role: Operator; Administrator; Level: System / Integration SRS v1.8 / BR: 3.10.4; BR-66–70 Test data: Refund without evidence Source: https://github.com/GFA26SE63/FSCM-Backend/blob/0f56f7099f07aa60d76673e6b6a57a2b606fb833/src/FSCM.Application/Features/Refunds/RefundService.cs Automation: Manual / candidate Version: 1.3; Actual result: —; Evidence: —
A17: FT-041-B | B17: Handle manual refund and evidence Boundary — Repeated refund key or amount beyond cap | C17: 1. Seed isolated FSCM fixture with required SKU, retailer, warehouse, roles and state; record starting stock/payment/ledger snapshots. 2. Sign in as Operator; Administrator; perform scenario: Repeated refund key or amount beyond cap. 3. Submit both the valid operation and the specified invalid/boundary input. 4. Compare response, persisted state, actor audit, once-only effects and unchanged records against the expected result. | D17: Prevent duplicate and over-refund | E17: Test environment seeded; authorized Operator; Administrator; transaction isolated and resettable. | F17: Not Run | O17: Type: Boundary; Role: Operator; Administrator; Level: System / Integration SRS v1.8 / BR: 3.10.4; BR-66–70 Test data: Repeated refund key or amount beyond cap Source: https://github.com/GFA26SE63/FSCM-Backend/blob/0f56f7099f07aa60d76673e6b6a57a2b606fb833/src/FSCM.Application/Features/Refunds/RefundService.cs Automation: Manual / candidate Version: 1.3; Actual result: —; Evidence: —
A18: FT-042-P | B18: Complaint adjustment uses allocated net price of affected batch | C18: 1. Create discrepancy against one priced allocation fragment. 2. Have Operator propose and Admin approve adjustment. 3. Read net price snapshot. | D18: Adjustment cap = affected quantity × actual approved net unit price of that batch/warehouse; one adjustment ledger entry, no premature inventory return. | E18: Test environment seeded; authorized Operator; Administrator; transaction isolated and resettable. | F18: Not Run | O18: Type: Positive; Role: Operator; Administrator; Level: System / Integration SRS v1.8 / BR: 3.10.4; BR-67–70 Test data: Approved claim with affected net allocated price Source: https://github.com/GFA26SE63/FSCM-Backend/blob/0f56f7099f07aa60d76673e6b6a57a2b606fb833/src/FSCM.API/Controllers/PaymentsController.cs Automation: Manual / candidate Version: 1.3; Actual result: —; Evidence: —
A19: FT-042-N | B19: Financial adjustment for complaint Negative — Adjust beyond claimed quantity/value | C19: 1. Seed isolated FSCM fixture with required SKU, retailer, warehouse, roles and state; record starting stock/payment/ledger snapshots. 2. Sign in as Operator; Administrator; perform scenario: Adjust beyond claimed quantity/value. 3. Submit both the valid operation and the specified invalid/boundary input. 4. Compare response, persisted state, actor audit, once-only effects and unchanged records against the expected result. | D19: Reject exceeding caps / duplicate adjustment | E19: Test environment seeded; authorized Operator; Administrator; transaction isolated and resettable. | F19: Not Run | O19: Type: Negative; Role: Operator; Administrator; Level: System / Integration SRS v1.8 / BR: 3.10.4; BR-67–70 Test data: Adjust beyond claimed quantity/value Source: https://github.com/GFA26SE63/FSCM-Backend/blob/0f56f7099f07aa60d76673e6b6a57a2b606fb833/src/FSCM.API/Controllers/PaymentsController.cs Automation: Manual / candidate Version: 1.3; Actual result: —; Evidence: —
A20: FT-042-B | B20: Financial adjustment for complaint Boundary — Claim rejected after pending disputed amount | C20: 1. Seed isolated FSCM fixture with required SKU, retailer, warehouse, roles and state; record starting stock/payment/ledger snapshots. 2. Sign in as Operator; Administrator; perform scenario: Claim rejected after pending disputed amount. 3. Submit both the valid operation and the specified invalid/boundary input. 4. Compare response, persisted state, actor audit, once-only effects and unchanged records against the expected result. | D20: Restore undisputed collection on rejection; no automatic bank refund | E20: Test environment seeded; authorized Operator; Administrator; transaction isolated and resettable. | F20: Not Run | O20: Type: Boundary; Role: Operator; Administrator; Level: System / Integration SRS v1.8 / BR: 3.10.4; BR-67–70 Test data: Claim rejected after pending disputed amount Source: https://github.com/GFA26SE63/FSCM-Backend/blob/0f56f7099f07aa60d76673e6b6a57a2b606fb833/src/FSCM.API/Controllers/PaymentsController.cs Automation: Manual / candidate Version: 1.3; Actual result: —; Evidence: —
A21: R5-TC-COMP-01 | B21: Batch-specific discrepancy cap | C21: 1. Operator recommends; 2. Admin approves; 3. Inspect ledger. | D21: Adjustment cap=2×72,000 not gross or batch B price; no automatic return-to-stock. | E21: Accepted complaint on allocated batch A (net 72k) and batch B (net 90k). Test data: Affected A qty=2; adjusted unit price A=72,000. | F21: Not Run | O21: Requirement/Traceability: SRS v1.8 §3.10.4; BR-67–69; M09/WF03/TS01 Priority: P1; Level: Integration / System / Acceptance Version: 1.3; Actual result: —; Evidence: —
A22: R5-TC-COMP-02 | B22: Unauthorized adjustment denied | C22: 1. Submit approval as Sales; 2. Check audit and balances. | D22: Denied; only authorized Operator recommendation and Admin final acceptance; no financial mutation. | E22: Sales user and Operator/Admin roles seeded. Test data: Sales attempts approve complaint. | F22: Not Run | O22: Requirement/Traceability: R5-07; SRS v1.8 §3.10.4; M09/WF03/TS02 Priority: P1; Level: Integration / System / Acceptance Version: 1.3; Actual result: —; Evidence: —
A23: R5-TC-REF-01 | B23: Manual refund evidence rejection then supplement | C23: Submit authorized manual transfer with evidence; request independent verification. | D23: Refund remains unverified until separate authorized approval; amount capped at outstanding obligation. | E23: Paid order with approved refund obligation and operator transfer proof. | F23: Not Run | O23: Requirement/Traceability: SRS v1.8 §3.10.4; BR-74; AC-3.10.4-01; M10/WF03/TS01 Priority: P1; Level: Integration / System / Acceptance Version: 1.3; Actual result: —; Evidence: —
... A26: R5-TC-REF-04 | B26: Refund verification not second loyalty deduction | C26: 1. Complete adjustment; 2. Verify refund; 3. Replay. | D26: One linked loyalty correction total; refund verification does not deduct points again. | E26: Loyalty correction posted when financial adjustment Completed. Test data: Refund verify event replay. | F26: Not Run | O26: Requirement/Traceability: R5-08; SRS v1.8 §3.10.4/NFR-D04; M10/WF03/TS04 Priority: P1; Level: Integration / System / Acceptance Version: 1.3; Actual result: —; Evidence: —

Sheet Payments & Receivables
A2: Feature | B2: Payments & Receivables | R2: Passed
A3: Test requirement | B3: Reject COD and prepaid cash. Verify full prepaid bank transfer at actual transaction time before quotation deadline, allowing authorized staff verification afterward only if fulfillment feasibility remains valid; require approved Deferred term, actual full receipt due-date basis, and correct cash/transfer actors. | R3: Failed
A4: Number of TCs | B4: =COUNTA(A12:A25) -> 14 | R4: Pending
A5: Testing Round | B5: Passed | C5: Failed | D5: Pending | E5: N/A | R5: N/A
A6: Round 1 | B6: =COUNTIF(F12:F25,"Passed")+COUNTIF(F12:F25,"Pass") -> 0 | C6: =COUNTIF(F12:F25,"Failed")+COUNTIF(F12:F25,"Fail") -> 0 | D6: =COUNTIF(F12:F25,"Not Run")+COUNTIF(F12:F25,"Blocked")+COUNTIF(F12:F25,"Pending")+COUNTBLANK(F12:F25) -> 14 | E6: =COUNTIF(F12:F25,"N/A") -> 0
A7: Round 2 | B7: =COUNTIF(I12:I25,"Passed")+COUNTIF(I12:I25,"Pass") -> 0 | C7: =COUNTIF(I12:I25,"Failed")+COUNTIF(I12:I25,"Fail") -> 0 | D7: =COUNTIF(I12:I25,"Not Run")+COUNTIF(I12:I25,"Blocked")+COUNTIF(I12:I25,"Pending") -> 0 | E7: =COUNTIF(I12:I25,"N/A") -> 0
A8: Round 3 | B8: =COUNTIF(L12:L25,"Passed")+COUNTIF(L12:L25,"Pass") -> 0 | C8: =COUNTIF(L12:L25,"Failed")+COUNTIF(L12:L25,"Fail") -> 0 | D8: =COUNTIF(L12:L25,"Not Run")+COUNTIF(L12:L25,"Blocked")+COUNTIF(L12:L25,"Pending") -> 0 | E8: =COUNTIF(L12:L25,"N/A") -> 0
A10: Test Case ID | B10: Test Case Description | C10: Test Case Procedure | D10: Expected Results | E10: Pre-conditions | F10: Round 1 | G10: Test date | H10: Tester | I10: Round 2 | J10: Test date | K10: Tester | L10: Round 3 | M10: Test date | N10: Tester | O10: Note
A11: Payments & Receivables — FSCM scenarios
A12: FT-039-P | B12: Full prepaid transfer accepted by transaction time and feasibility | C12: 1. Approve 612,000 VND P1 batch quote. 2. Bank transfer full amount before quote deadline. 3. Authorized Operator confirms after deadline but while ETA/MLOR remains feasible. 4. Inspect one PO, picking and ledger. | D12: Allowed if actual transfer is timely and fulfillment still valid; transfer verification time alone does not cause false rejection. One PO after verified payment; no early dispatch. | E12: Test environment seeded; authorized Retailer; Sales; Operator; transaction isolated and resettable. | F12: Not Run | O12: Type: Positive; Role: Retailer; Sales; Operator; Level: System / Integration SRS v1.8 / BR: 3.10.1; BR-51–53 Test data: Record permitted final-price collection Source: https://github.com/GFA26SE63/FSCM-Backend/blob/0f56f7099f07aa60d76673e6b6a57a2b606fb833/src/FSCM.Application/Features/Payments/PaymentService.cs Automation: Manual / candidate Version: 1.3; Actual result: —; Evidence: —
A13: FT-039-N | B13: Reject COD and prepaid cash for purchase order | C13: 1. Select COD; 2. Attempt prepaid cash; 3. Inspect PO and payment ledger after both. | D13: Reject both COD and cash prepaid; no PO, dispatch or ledger effect. Sales cash only for delivered approved credit. | E13: Test environment seeded; authorized Retailer; Sales; Operator; transaction isolated and resettable. | F13: Not Run | O13: Type: Negative; Role: Retailer; Sales; Operator; Level: System / Integration SRS v1.8 / BR: 3.10.1; BR-51–53 Test data: Prepaid collection before allocation approval Source: https://github.com/GFA26SE63/FSCM-Backend/blob/0f56f7099f07aa60d76673e6b6a57a2b606fb833/src/FSCM.Application/Features/Payments/PaymentService.cs Automation: Manual / candidate Version: 1.3; Actual result: —; Evidence: —
A14: FT-039-B | B14: Deferred payment requires current approved retailer credit term | C14: 1. Try missing/expired/current retailer terms; 2. Accept quotation as Deferred; 3. Inspect ledger and PO. | D14: Only current approved term permits Deferred; resulting deferred due date is based on actual completed receipt. | E14: Test environment seeded; authorized Retailer; Sales; Operator; transaction isolated and resettable. | F14: Not Run | O14: Type: Boundary; Role: Retailer; Sales; Operator; Level: System / Integration SRS v1.8 / BR: 3.10.1; BR-51–53 Test data: Collection of partial amount Source: https://github.com/GFA26SE63/FSCM-Backend/blob/0f56f7099f07aa60d76673e6b6a57a2b606fb833/src/FSCM.Application/Features/Payments/PaymentService.cs Automation: Manual / candidate Version: 1.3; Actual result: —; Evidence: —
A15: FT-040-P | B15: Deferred due date starts at completed actual receipt | C15: 1. Select valid deferred. 2. Dispatch multiwarehouse order. 3. Confirm last required quantity. 4. Compute term-based due date. | D15: Due date is established from completed actual receipt and approved retailer term; prepaid quote deadline is independent. | E15: Test environment seeded; authorized Operator; System; transaction isolated and resettable. | F15: Not Run | O15: Type: Positive; Role: Operator; System; Level: System / Integration SRS v1.8 / BR: 3.10.1; BR-52–53 Test data: Delivered credit order 7/14/30 days Source: https://github.com/GFA26SE63/FSCM-Backend/blob/0f56f7099f07aa60d76673e6b6a57a2b606fb833/src/FSCM.Application/Features/Payments/PaymentService.cs Automation: Manual / candidate Version: 1.3; Actual result: —; Evidence: —
A16: FT-040-N | B16: Calculate deferred due date and overdue Negative — Credit without eligible term | C16: 1. Seed isolated FSCM fixture with required SKU, retailer, warehouse, roles and state; record starting stock/payment/ledger snapshots. 2. Sign in as Operator; System; perform scenario: Credit without eligible term. 3. Submit both the valid operation and the specified invalid/boundary input. 4. Compare response, persisted state, actor audit, once-only effects and unchanged records against the expected result. | D16: Reject ineligible deferred payment | E16: Test environment seeded; authorized Operator; System; transaction isolated and resettable. | F16: Not Run | O16: Type: Negative; Role: Operator; System; Level: System / Integration SRS v1.8 / BR: 3.10.1; BR-52–53 Test data: Credit without eligible term Source: https://github.com/GFA26SE63/FSCM-Backend/blob/0f56f7099f07aa60d76673e6b6a57a2b606fb833/src/FSCM.Application/Features/Payments/PaymentService.cs Automation: Manual / candidate Version: 1.3; Actual result: —; Evidence: —
A17: FT-040-B | B17: Calculate deferred due date and overdue Boundary — Due date exactly today | C17: 1. Seed isolated FSCM fixture with required SKU, retailer, warehouse, roles and state; record starting stock/payment/ledger snapshots. 2. Sign in as Operator; System; perform scenario: Due date exactly today. 3. Submit both the valid operation and the specified invalid/boundary input. 4. Compare response, persisted state, actor audit, once-only effects and unchanged records against the expected result. | D17: Mark overdue only after due date | E17: Test environment seeded; authorized Operator; System; transaction isolated and resettable. | F17: Not Run | O17: Type: Boundary; Role: Operator; System; Level: System / Integration SRS v1.8 / BR: 3.10.1; BR-52–53 Test data: Due date exactly today Source: https://github.com/GFA26SE63/FSCM-Backend/blob/0f56f7099f07aa60d76673e6b6a57a2b606fb833/src/FSCM.Application/Features/Payments/PaymentService.cs Automation: Manual / candidate Version: 1.3; Actual result: —; Evidence: —
A18: R5-TC-PAY-01 | B18: COD is rejected at method selection | C18: Attempt COD selection through UI and direct API after approved quotation; examine ledger and PO. | D18: COD is unavailable/rejected, regardless of route; no PO, payment or dispatch side effect. | E18: Retailer has an accepted versioned quotation; method=COD. | F18: Not Run | O18: Requirement/Traceability: R5-01; SRS v1.8 §3.10.1/BR-51; M10/WF01/TS01 Priority: P1; Level: Integration / System / Acceptance Version: 1.3; Actual result: —; Evidence: —
A19: R5-TC-PAY-02 | B19: Prepaid cash is rejected | C19: Attempt cash for prepaid quotation; attempt authorized Sales credit collection as control. | D19: Prepaid cash rejected; cash allowed only for full collection of assigned delivered deferred receivable by Sales. | E19: Approved prepaid quote and separate fully delivered deferred invoice. | F19: Not Run | O19: Requirement/Traceability: R5-01; SRS v1.8 §3.10.1/BR-51; M10/WF01/TS02 Priority: P1; Level: Integration / System / Acceptance Version: 1.3; Actual result: —; Evidence: —
A20: R5-TC-PAY-03 | B20: Prepaid bank transfer after approved price | C20: Approve allocation/batch price; accept prepaid quote; submit bank transfer proof; Operator verifies before deadline; attempt dispatch. | D20: Only verified full bank transfer creates PO and picking; no COD; dispatch impossible before successful verification. | E20: Approved price/version; quotation accepted; exact transfer amount/reference; valid deadline. | F20: Not Run | O20: Requirement/Traceability: SRS v1.8 §3.6.6/§3.10.1; BR-51/72; R5-05; M10/WF01/TS03 Priority: P1; Level: Integration / System / Acceptance Version: 1.3; Actual result: —; Evidence: —
A21: R5-TC-PAY-04 | B21: Prepaid transfer time on deadline; verification arrives later | C21: 1. Admin approves P1 final quote and sets response/payment deadline 10:00. 2. Retailer bank transfers full 612,000 VND at 09:59; Operator verifies at 10:05. 3. Revalidate current shipment ETA, expiry, MLOR and state. 4. Repeat using transfer time 10:01. | D21: The on-time 09:59 transfer can be accepted despite 10:05 verification IF fulfillment remains feasible and quote not irreversibly expired; late 10:01 transfer rejected. No duplicate PO/payment or dispatch before validation. | E21: Final quote approved; verified immutable bank transaction timestamp and matching proof; no COD. | F21: Not Run | O21: Requirement/Traceability: SRS v1.8 §3.6.6; BR-51/72; M10/WF01/TS04 Priority: P1; Level: Integration / System / Acceptance Version: 1.3; Actual result: —; Evidence: —
A22: R5-TC-PAY-05 | B22: Deferred requires valid approved term | C22: Select Deferred with missing, expired and valid approved retailer terms; inspect PO and ledger. | D22: Only C may choose Deferred and convert quote to PO; others rejected with no stock/payment side effect. | E22: Retailers A: no term, B: expired term, C: current approved term. | F22: Not Run | O22: Requirement/Traceability: SRS v1.8 §3.6.6/§3.10.1; BR-51/73; M10/WF02/TS01 Priority: P1; Level: Integration / System / Acceptance Version: 1.3; Actual result: —; Evidence: —
A23: R5-TC-PAY-06 | B23: Deferred due date from full receipt | C23: Confirm all required quantities of two shipments on different dates; inspect credit due date. | D23: Due date = 02/10/2026 based on last actual full receipt; prepaid quotation deadline remains separate. | E23: Deferred PO with approved term=14 days; last complete receipt=18/09/2026. | F23: Not Run | O23: Requirement/Traceability: SRS v1.8 §3.10.1; AC-3.10.1-01; M10/WF02/TS02 Priority: P1; Level: Integration / System / Acceptance Version: 1.3; Actual result: —; Evidence: —
... A25: R5-TC-PAY-08 | B25: Bank transfer credited by authorized staff | C25: Operator records approved bank transfer; replay; attempt same action as Sales. | D25: One correct ledger payment; repeated request no duplicate; unauthorized bank-transfer verification forbidden. | E25: Verified transfer reference, canonical receivable, authorized Operator and unauthorized Sales. | F25: Not Run | O25: Requirement/Traceability: SRS v1.8 §3.10.1; UC-36; R5-01; M10/WF02/TS04 Priority: P1; Level: Integration / System / Acceptance Version: 1.3; Actual result: —; Evidence: —

Sheet Loyalty Management
A2: Feature | B2: Loyalty Management | R2: Passed
A3: Test requirement | B3: After full physical shipment quantities, settlement and no open complaint, award floor(net eligible VND/10,000) once: P1 612,000 ->61, after 72,000 adjustment ->54 (delta -7). A missing-quantity order cannot become Completed by settlement alone. Staff finalize redeemed gifts with delivery evidence; Retailer confirmation not mandatory. | R3: Failed
A4: Number of TCs | B4: =COUNTA(A12:A26) -> 15 | R4: Pending
A5: Testing Round | B5: Passed | C5: Failed | D5: Pending | E5: N/A | R5: N/A
A6: Round 1 | B6: =COUNTIF(F12:F26,"Passed")+COUNTIF(F12:F26,"Pass") -> 0 | C6: =COUNTIF(F12:F26,"Failed")+COUNTIF(F12:F26,"Fail") -> 0 | D6: =COUNTIF(F12:F26,"Not Run")+COUNTIF(F12:F26,"Blocked")+COUNTIF(F12:F26,"Pending")+COUNTBLANK(F12:F26) -> 15 | E6: =COUNTIF(F12:F26,"N/A") -> 0
A7: Round 2 | B7: =COUNTIF(I12:I26,"Passed")+COUNTIF(I12:I26,"Pass") -> 0 | C7: =COUNTIF(I12:I26,"Failed")+COUNTIF(I12:I26,"Fail") -> 0 | D7: =COUNTIF(I12:I26,"Not Run")+COUNTIF(I12:I26,"Blocked")+COUNTIF(I12:I26,"Pending") -> 0 | E7: =COUNTIF(I12:I26,"N/A") -> 0
A8: Round 3 | B8: =COUNTIF(L12:L26,"Passed")+COUNTIF(L12:L26,"Pass") -> 0 | C8: =COUNTIF(L12:L26,"Failed")+COUNTIF(L12:L26,"Fail") -> 0 | D8: =COUNTIF(L12:L26,"Not Run")+COUNTIF(L12:L26,"Blocked")+COUNTIF(L12:L26,"Pending") -> 0 | E8: =COUNTIF(L12:L26,"N/A") -> 0
A10: Test Case ID | B10: Test Case Description | C10: Test Case Procedure | D10: Expected Results | E10: Pre-conditions | F10: Round 1 | G10: Test date | H10: Tester | I10: Round 2 | J10: Test date | K10: Tester | L10: Round 3 | M10: Test date | N10: Tester | O10: Note
A11: Loyalty Management — FSCM scenarios
A12: FT-043-P | B12: Earn points once after full actual receipt, settlement and no open complaint | C12: 1. Complete all shipment quantities; 2. Settle payment; 3. Resolve complaints; 4. Run earning twice. | D12: Exactly one initial points award only after all conditions satisfied. | E12: Test environment seeded; authorized System; transaction isolated and resettable. | F12: Not Run | O12: Type: Positive; Role: System; Level: System / Integration SRS v1.8 / BR: 3.10.2; BR-54 Test data: Fully received settled no open complaint Source: https://github.com/GFA26SE63/FSCM-Backend/blob/0f56f7099f07aa60d76673e6b6a57a2b606fb833/src/FSCM.Application/Features/Loyalty/LoyaltyService.cs Automation: Manual / candidate Version: 1.3; Actual result: —; Evidence: —
A13: FT-043-N | B13: Do not earn with unresolved complaint or incomplete shipment | C13: 1. Mark all shipment records confirmed with missing quantity or keep a complaint unresolved. 2. Settle amount. 3. Trigger earning. | D13: No loyalty points before actual full receipt and complaint resolution, even when status flags or payment appear complete. | E13: Test environment seeded; authorized System; transaction isolated and resettable. | F13: Not Run | O13: Type: Negative; Role: System; Level: System / Integration SRS v1.8 / BR: 3.10.2; BR-54 Test data: Order not fully delivered or settled Source: https://github.com/GFA26SE63/FSCM-Backend/blob/0f56f7099f07aa60d76673e6b6a57a2b606fb833/src/FSCM.Application/Features/Loyalty/LoyaltyService.cs Automation: Manual / candidate Version: 1.3; Actual result: —; Evidence: —
A14: FT-043-B | B14: Earn points boundary at 100,000 VND | C14: 1. Fully receive and settle 100,000 VND eligible order with no unresolved complaint. 2. Trigger earning twice. 3. Check ledger rounding and count. | D14: floor(100,000/10,000) = 10 points posted once (not 1). 99,999 VND earns 9 points; no duplicate ledger. | E14: Point rate 1 per 10,000 VND; full actual quantity received; no complaint; payment settled. | F14: Not Run | O14: Type: Boundary; Role: System; Level: System / Integration SRS v1.8 / BR: 3.10.2; BR-54 Test data: Eligible amount exactly 100000 VND Source: https://github.com/GFA26SE63/FSCM-Backend/blob/0f56f7099f07aa60d76673e6b6a57a2b606fb833/src/FSCM.Application/Features/Loyalty/LoyaltyService.cs Automation: Manual / candidate Version: 1.3; Actual result: —; Evidence: —
A15: FT-044-P | B15: Staff completes gift after documented physical delivery | C15: 1. Retailer requests gift costing 60 points. 2. Administrator approves and points are deducted/hold settled once. 3. Operator records gift delivered with evidence. 4. Authorized Administrator/Operator finalizes Completed; repeat and try unauthorized Sales. | D15: Completed after authorized staff delivery confirmation with evidence; no Retailer confirmation step required. No duplicate point debit and unauthorized action denied. | E15: Test environment seeded; authorized Retailer; Administrator; transaction isolated and resettable. | F15: Not Run | O15: Type: Positive; Role: Retailer; Administrator; Level: System / Integration SRS v1.8 / BR: 3.10.3; BR-55,70 Test data: Enough points and active reward Source: https://github.com/GFA26SE63/FSCM-Backend/blob/0f56f7099f07aa60d76673e6b6a57a2b606fb833/src/FSCM.API/Controllers/LoyaltyRedemptionsController.cs Automation: Manual / candidate Version: 1.3; Actual result: —; Evidence: —
A16: FT-044-N | B16: Redeem reward and settle points Negative — Insufficient / negative corrected balance | C16: 1. Seed isolated FSCM fixture with required SKU, retailer, warehouse, roles and state; record starting stock/payment/ledger snapshots. 2. Sign in as Retailer; Administrator; perform scenario: Insufficient / negative corrected balance. 3. Submit both the valid operation and the specified invalid/boundary input. 4. Compare response, persisted state, actor audit, once-only effects and unchanged records against the expected result. | D16: Block invalid redemption | E16: Test environment seeded; authorized Retailer; Administrator; transaction isolated and resettable. | F16: Not Run | O16: Type: Negative; Role: Retailer; Administrator; Level: System / Integration SRS v1.8 / BR: 3.10.3; BR-55,70 Test data: Insufficient / negative corrected balance Source: https://github.com/GFA26SE63/FSCM-Backend/blob/0f56f7099f07aa60d76673e6b6a57a2b606fb833/src/FSCM.API/Controllers/LoyaltyRedemptionsController.cs Automation: Manual / candidate Version: 1.3; Actual result: —; Evidence: —
A17: FT-044-B | B17: Gift rejection releases holds once and negative balance blocks redemption | C17: 1. Reject a pending redemption and repeat. 2. Record P1 adjustment causing balance -6 per F5. 3. Retailer attempts a second gift. 4. Inspect ledger and stocks. | D17: Rejected holds released exactly once; negative corrected balance -6 blocks new request; staff delivery confirmation governs completion, not Retailer UI confirmation. | E17: Test environment seeded; authorized Retailer; Administrator; transaction isolated and resettable. | F17: Not Run | O17: Type: Boundary; Role: Retailer; Administrator; Level: System / Integration SRS v1.8 / BR: 3.10.3; BR-55,70 Test data: Request rejected after points held Source: https://github.com/GFA26SE63/FSCM-Backend/blob/0f56f7099f07aa60d76673e6b6a57a2b606fb833/src/FSCM.API/Controllers/LoyaltyRedemptionsController.cs Automation: Manual / candidate Version: 1.3; Actual result: —; Evidence: —
A18: FT-045-P | B18: Manage loyalty program and gift catalog Positive — Create eligible program/reward | C18: 1. Seed isolated FSCM fixture with required SKU, retailer, warehouse, roles and state; record starting stock/payment/ledger snapshots. 2. Sign in as Administrator; perform scenario: Create eligible program/reward. 3. Submit both the valid operation and the specified invalid/boundary input. 4. Compare response, persisted state, actor audit, once-only effects and unchanged records against the expected result. | D18: Store program and reward configuration | E18: Test environment seeded; authorized Administrator; transaction isolated and resettable. | F18: Not Run | O18: Type: Positive; Role: Administrator; Level: System / Integration SRS v1.8 / BR: 3.10.3; BR-54–55 Test data: Create eligible program/reward Source: https://github.com/GFA26SE63/FSCM-Backend/blob/0f56f7099f07aa60d76673e6b6a57a2b606fb833/src/FSCM.Application/Features/Loyalty/RewardService.cs Automation: Manual / candidate Version: 1.3; Actual result: —; Evidence: —
A19: FT-045-N | B19: Manage loyalty program and gift catalog Negative — Activate out-of-stock reward | C19: 1. Seed isolated FSCM fixture with required SKU, retailer, warehouse, roles and state; record starting stock/payment/ledger snapshots. 2. Sign in as Administrator; perform scenario: Activate out-of-stock reward. 3. Submit both the valid operation and the specified invalid/boundary input. 4. Compare response, persisted state, actor audit, once-only effects and unchanged records against the expected result. | D19: Reject invalid activation | E19: Test environment seeded; authorized Administrator; transaction isolated and resettable. | F19: Not Run | O19: Type: Negative; Role: Administrator; Level: System / Integration SRS v1.8 / BR: 3.10.3; BR-54–55 Test data: Activate out-of-stock reward Source: https://github.com/GFA26SE63/FSCM-Backend/blob/0f56f7099f07aa60d76673e6b6a57a2b606fb833/src/FSCM.Application/Features/Loyalty/RewardService.cs Automation: Manual / candidate Version: 1.3; Actual result: —; Evidence: —
A20: FT-045-B | B20: Manage loyalty program and gift catalog Boundary — Expiration exactly current day | C20: 1. Seed isolated FSCM fixture with required SKU, retailer, warehouse, roles and state; record starting stock/payment/ledger snapshots. 2. Sign in as Administrator; perform scenario: Expiration exactly current day. 3. Submit both the valid operation and the specified invalid/boundary input. 4. Compare response, persisted state, actor audit, once-only effects and unchanged records against the expected result. | D20: Apply documented expiry boundary consistently | E20: Test environment seeded; authorized Administrator; transaction isolated and resettable. | F20: Not Run | O20: Type: Boundary; Role: Administrator; Level: System / Integration SRS v1.8 / BR: 3.10.3; BR-54–55 Test data: Expiration exactly current day Source: https://github.com/GFA26SE63/FSCM-Backend/blob/0f56f7099f07aa60d76673e6b6a57a2b606fb833/src/FSCM.Application/Features/Loyalty/RewardService.cs Automation: Manual / candidate Version: 1.3; Actual result: —; Evidence: —
A21: R5-TC-LOY-01 | B21: Full receipt is mandatory even after complaint settlement | C21: 1. Dispatch 10 cartons; Retailer receives 8 and records missing 2. 2. Resolve complaint and adjust financial balance fully. 3. Trigger Completed and earn. 4. Separately confirm missing 2 cartons physically received and settle outstanding amounts; retry. | D21: After only 8/10 received, order remains non-Delivered/non-Completed and earns 0 points even if adjustment settled. Completion and earning require full physical quantity, full payment and no open complaint. | E21: Multiwarehouse delivery with one initially missing portion; open discrepancy; eventual full settlement. | F21: Not Run | O21: Requirement/Traceability: Registration §3.2; SRS v1.8 §3.10.3; NFR-D04; R5-08; M11/WF01/TS01 Priority: P1; Level: Integration / System / Acceptance Version: 1.3; Actual result: —; Evidence: —
A22: R5-TC-LOY-02 | B22: Exactly once initial earning | C22: Publish initial earning event; deliver same event repeatedly; compare ledger and balance. | D22: Exactly one initial earning ledger entry and one balance increase per order. | E22: Eligible completed order, settled net amount, no open complaint; duplicated event/ID. | F22: Not Run | O22: Requirement/Traceability: SRS v1.8 §3.10.3; BR-54; NFR-D04; M11/WF01/TS02 Priority: P1; Level: Integration / System / Acceptance Version: 1.3; Actual result: —; Evidence: —
A23: R5-TC-LOY-03 | B23: F5 P1 adjustment 61 -> 54 points and possible -6 balance | C23: 1. Fully receive and settle P1=612,000 VND; post 61 points. 2. Redeem gift costing 60 (remaining=1). 3. Approve affected A1 complaint adjustment 72,000 VND, reducing eligible value to 540,000. 4. Run correction twice and verify refund separately. | D23: Target points=floor(540,000/10,000)=54; correction -7, final balance=1-7=-6. Exactly one correction; manual refund verification does NOT deduct points again. | E23: Five Main Flows F5 sheet 04; P1 fully received (no missing quantity), disputed A1 batch priced net 72,000; claim authorized, full settlement. | F23: Not Run | O23: Requirement/Traceability: R5-08; SRS v1.8 §3.10.4/NFR-D04; M11/WF02/TS01 Priority: P1; Level: Integration / System / Acceptance Version: 1.3; Actual result: —; Evidence: —
... A26: R5-TC-LOY-06 | B26: Gift completed by authorized staff on verified delivery | C26: 1. Retailer requests gift. 2. Admin approves and holds/settles points once. 3. Operator/Admin records physical delivery evidence and marks Completed. 4. Retry same transition; let Sales attempt unauthorized completion. | D26: Authorized staff may complete without extra Retailer confirmation; status/points/stock once only; unauthorized actor denied. | E26: Approved gift with delivery evidence, intended Retailer account, still unconfirmed. | F26: Not Run | O26: Requirement/Traceability: R5-08; SRS v1.8 §3.10.3/BR-75 lifecycle; M11/WF03/TS03 Priority: P1; Level: Integration / System / Acceptance Version: 1.3; Actual result: —; Evidence: —

Sheet Territory & Sales Groups
A2: Feature | B2: Territory & Sales Groups | R2: Passed
A3: Test requirement | B3: Verify Sales and retailer assignments stay within valid regions and permissions. Reject cross-region retailer coverage and preserve assignment history when transferring a Sales representative between groups. | R3: Failed
A4: Number of TCs | B4: =COUNTA(A12:A14) -> 3 | R4: Pending
A5: Testing Round | B5: Passed | C5: Failed | D5: Pending | E5: N/A | R5: N/A
A6: Round 1 | B6: =COUNTIF(F12:F14,"Passed")+COUNTIF(F12:F14,"Pass") -> 0 | C6: =COUNTIF(F12:F14,"Failed")+COUNTIF(F12:F14,"Fail") -> 0 | D6: =COUNTIF(F12:F14,"Not Run")+COUNTIF(F12:F14,"Blocked")+COUNTIF(F12:F14,"Pending")+COUNTBLANK(F12:F14) -> 3 | E6: =COUNTIF(F12:F14,"N/A") -> 0
A7: Round 2 | B7: =COUNTIF(I12:I14,"Passed")+COUNTIF(I12:I14,"Pass") -> 0 | C7: =COUNTIF(I12:I14,"Failed")+COUNTIF(I12:I14,"Fail") -> 0 | D7: =COUNTIF(I12:I14,"Not Run")+COUNTIF(I12:I14,"Blocked")+COUNTIF(I12:I14,"Pending") -> 0 | E7: =COUNTIF(I12:I14,"N/A") -> 0
A8: Round 3 | B8: =COUNTIF(L12:L14,"Passed")+COUNTIF(L12:L14,"Pass") -> 0 | C8: =COUNTIF(L12:L14,"Failed")+COUNTIF(L12:L14,"Fail") -> 0 | D8: =COUNTIF(L12:L14,"Not Run")+COUNTIF(L12:L14,"Blocked")+COUNTIF(L12:L14,"Pending") -> 0 | E8: =COUNTIF(L12:L14,"N/A") -> 0
A10: Test Case ID | B10: Test Case Description | C10: Test Case Procedure | D10: Expected Results | E10: Pre-conditions | F10: Round 1 | G10: Test date | H10: Tester | I10: Round 2 | J10: Test date | K10: Tester | L10: Round 3 | M10: Test date | N10: Tester | O10: Note
A11: Territory & Sales Groups — FSCM scenarios
A12: FT-046-P | B12: Manage sales groups and coverage Positive — Assign Sales and retailer in same region | C12: 1. Seed isolated FSCM fixture with required SKU, retailer, warehouse, roles and state; record starting stock/payment/ledger snapshots. 2. Sign in as Sales Manager; perform scenario: Assign Sales and retailer in same region. 3. Submit both the valid operation and the specified invalid/boundary input. 4. Compare response, persisted state, actor audit, once-only effects and unchanged records against the expected result. | D12: Persist valid scope and membership | E12: Test environment seeded; authorized Sales Manager; transaction isolated and resettable. | F12: Not Run | O12: Type: Positive; Role: Sales Manager; Level: System / Integration SRS v1.8 / BR: 3.11.1; BR-03 Test data: Assign Sales and retailer in same region Source: https://github.com/GFA26SE63/FSCM-Backend/blob/0f56f7099f07aa60d76673e6b6a57a2b606fb833/src/FSCM.Application/Features/Territory/TerritoryService.cs Automation: Manual / candidate Version: 1.3; Actual result: —; Evidence: —
