Workbook
Name Z_BE54E0AD_3725_4423_92D7_4F1C045BE1BC_.wvu.Cols: 'Apply Job'!$E:$E
Name Z_2C0D9096_8D85_462A_A9B5_0B488ADB4269_.wvu.Cols: 'Apply Job'!$E:$E
Name Z_6F1DCD5D_5DAC_4817_BF40_2B66F6F593E6_.wvu.Cols: 'Apply Job'!$E:$E
Name Z_2C0D9096_8D85_462A_A9B5_0B488ADB4269_.wvu.PrintArea: Statistics!$A:$I
Name Z_6F1DCD5D_5DAC_4817_BF40_2B66F6F593E6_.wvu.PrintArea: Statistics!$A:$I
Name Z_BE54E0AD_3725_4423_92D7_4F1C045BE1BC_.wvu.PrintArea: Statistics!$A:$I
Name ACTION: #REF!

Sheet Guideline
A1: git
A3: 1. Overview
A4: - In the template, Unit test cases are based on functions. Each sheet presents test cases for one function.
A5: - Cover: General information of the project and Unit Test cases
A6: - FunctionList: The list of Classes and Functions in the document. + To control that the number of Unit TC meets customer's requirement or the norm, user should fill value for 'Normal number of Test cases/KLOC'.
A7: + Click on Function link to open the related Test cases of the function. Note: You should create new Function sheet before creating the link
A8: - Test Report: provive the overview results of Functions Unit test: Test coverage, Test successful coverage (Summary, for normal/abnormal/boundary cases)
A9: Note: Should check the formula of "Sub Total" if you add more functions
A11: 2. Content in Test function sheet
A12: 2.1 Combination of test cases.
A13: - To verify that number of Unit TC meets customer's requirement or not. User has to fill number LOC of tested function and fill value of 'Normal number test cases/KLOC' item in FunctionList sheet, which is required by customer or normal value. The number of lacked TC is shown in 'Lack of test cases' item.
A14: - If the number of Unit TC does not meet the requirement, creator should explain the reasons.
... A48: - Report 5 uses ONLY Test Documentation, Unit Test and Test Report. Execution status/evidence must come from verified CI/manual test records.

Sheet Cover
B2: UNIT TEST DOCUMENT
A4: Project Name | B4: FSCM – Short Shelf-Life FMCG Supply Chain Management | E4: Creator | F4: Tran Ngoc Khiet, Doan Duc Hai
A5: Project Code | B5: FA26SE083 | E5: Issue Date | F5: 46323
A6: Document Code | B6: FA26SE083_Unit Test_v1.3 | E6: Version | F6: 1.3
A9: Record of change
A10: Effective Date | B10: Version | C10: Change Item | D10: *A,D,M | E10: Change description | F10: Reference
A11: 46308 | B11: 1 | C11: Initial FSCM unit test plan (v1.0) | D11: A | E11: Version 1.0: Initial unit test plan and scope. | F11: SRS v1.5; SDD v1.4; FSCM source code
A12: 27/10/2026 | B12: 1.1 | C12: Adapt example format for FSCM (v1.1) | D12: M | E12: Version 1.1: 192 source-mapped cases, 38 function sheets. | F12: FSCM-Backend / FSCM-Mobile
A13: 27/10/2026 | B13: 1.1 | C13: Reset pending execution states and rebuild statistics | D13: M | E13: Do not mark test cases Pass/Fail before execution. | F13: Example Report5_Unit Test.xlsx
A14: 28/10/2026 | B14: 1.2 | C14: Unit Test v1.2 alignment to SRS/SDD v1.8; 3-file Report 5 package | D14: M | E14: Retain 42 original sheets and 192 planned scenarios; align prepaid/credit, cutoff, MLOR, fixed/% price, manual Send, fulfillment/loyalty, and requirement trace. | F14: Test_Documentation v1.2; Unit_Test v1.2; Test_Report v1.2; SRS/SDD v1.8; R5-01..R5-12
A15: 28/10/2026 | B15: 1.3 | C15: Main Flows F1–F5 decisions and executable Unit Test design | D15: M | E15: Apply seven approved decisions (00:00, percentage-only discounts, 1 point/10,000 VND, full receipt, positive pricing, Admin/Operator catalog rights, staff gift completion); refine group promotion, allocation tie-break and financial examples. Preserve 192 planned scenarios, Not Run. | F15: Five Main Flows F1–F5; SRS/SDD v1.8; Test Documentation/Test Report v1.3

Sheet Functions
E2: Function List
A4: Project Name | E4: =Cover!B4 -> FSCM – Short Shelf-Life FMCG Supply Chain Management
A5: Project Code | E5: =Cover!B5 -> FA26SE083
A6: Normal number of Test cases/KLOC | E6: N/A
A7: Test Environment Setup Description | E7: FSCM .NET 10/xUnit and Flutter. Main Flows F1–F5 test baseline v1.3; cutoff 00:00 ICT; percentage-only shelf-life discounts; 1 point / 10,000 VND; full actual receipt before Completed. Execution results require evidence.
A10: No | B10: Requirement Name | C10: Class Name | D10: Function Name | E10: Function Code(Optional) | F10: Sheet Name | G10: Description | H10: Pre-Condition
A11: 1 | B11: Review versioned FEFO–MLOR allocation proposals and approved batch prices; allow only an authorized Administrator to approve the current version or request a reasoned recalculation. Reject stale or repeated conflicting d | C11: AllocationPlanApprovalTests | D11: Allocation proposal review, approval and revision | E11: F-01 | F11: Allocation Plan Approval | G11: Review versioned FEFO–MLOR allocation proposals and approved batch prices; allow only an authorized Administrator to approve the current version or request a reasoned recalculation. Reject stale or repeated conflicting decisions and do not reserve stock before approval. | H11: Isolated test database/fixtures; authorized actor and required stock/payment state. Execute only with verified evidence. Mapping managed in Test Documentation, Unit Test and Test Report v1.3.
A12: 2 | B12: Record and verify manual refunds against approved cancellation or complaint adjustments, limiting each refund to the affected batch’s actual net price. Preserve evidence and require independent Administrator verification | C12: RefundServiceTests | D12: Manual refund state, evidence and separation of duties | E12: F-02 | F12: Refund Service | G12: Record and verify manual refunds against approved cancellation or complaint adjustments, limiting each refund to the affected batch’s actual net price. Preserve evidence and require independent Administrator verification without applying a second loyalty reversal. | H12: Isolated test database/fixtures; authorized actor and required stock/payment state. Execute only with verified evidence. Mapping managed in Test Documentation, Unit Test and Test Report v1.3.
A13: 3 | B13: Allocate eligible warehouse batches to orders in server-acceptance priority without replacing batches already given to earlier orders. Support multi-batch fulfillment; if any required line is short, release all tentative | C13: AllocationPlannerTests | D13: Order priority, multi-batch allocation and whole-order shortfall | E13: F-03 | F13: Allocation Planner | G13: Allocate eligible warehouse batches to orders in server-acceptance priority without replacing batches already given to earlier orders. Support multi-batch fulfillment; if any required line is short, release all tentative draws for that order to the shared pool. At equal weighted score use earliest expiry, shortest rout | H13: Isolated test database/fixtures; authorized actor and required stock/payment state. Execute only with verified evidence. Mapping managed in Test Documentation, Unit Test and Test Report v1.3.
A14: 4 | B14: Reject COD as an unsupported payment method. Verify a full prepaid bank transfer only after final-price approval and before dispatch; allow full cash collection for an assigned, delivered deferred order and restrict bank | C14: ManualPaymentServiceTests | D14: Prepaid transfer, deferred cash collection, actor scope; reject COD | E14: F-04 | F14: Manual Payment | G14: Reject COD as an unsupported payment method. Verify a full prepaid bank transfer only after final-price approval and before dispatch; allow full cash collection for an assigned, delivered deferred order and restrict bank-transfer verification to authorized staff. Credit cash collection remains assigned Sales only after | H14: Isolated test database/fixtures; authorized actor and required stock/payment state. Execute only with verified evidence. Mapping managed in Test Documentation, Unit Test and Test Report v1.3.
A15: 5 | B15: Keep warehouse stock unchanged until a goods receipt is approved; then create or merge the appropriate SKU–expiry batch and record one auditable stock movement. Prevent duplicate receipts and reject reuse of an idempoten | C15: InventoryServiceTests | D15: Goods receipt posting and warehouse balances | E15: F-05 | F15: Inventory Service | G15: Keep warehouse stock unchanged until a goods receipt is approved; then create or merge the appropriate SKU–expiry batch and record one auditable stock movement. Prevent duplicate receipts and reject reuse of an idempotency key with different contents. | H15: Isolated test database/fixtures; authorized actor and required stock/payment state. Execute only with verified evidence. Mapping managed in Test Documentation, Unit Test and Test Report v1.3.
A16: 6 | B16: Generate and split QR labels only for valid available batch quantities, preserving unique codes, parent–child lineage and warehouse/batch identity. Repeated operations must not create duplicate labels or change stock qua | C16: QrLabelServiceTests | D16: QR quantity labels, lineage, split and replay | E16: F-06 | F16: QR Label Service | G16: Generate and split QR labels only for valid available batch quantities, preserving unique codes, parent–child lineage and warehouse/batch identity. Repeated operations must not create duplicate labels or change stock quantities twice. | H16: Isolated test database/fixtures; authorized actor and required stock/payment state. Execute only with verified evidence. Mapping managed in Test Documentation, Unit Test and Test Report v1.3.
A17: 7 | B17: Plan each valid daily allocation-run snapshot once using its frozen settings and eligible orders. Handle missing runs and unreachable warehouse routes predictably; record shortage explanations without reserving physical | C17: AllocationRunPlanningTests | D17: Daily run orchestration, shared pool, trace records | E17: F-07 | F17: Allocation Run Planning | G17: Plan each valid daily allocation-run snapshot once using its frozen settings and eligible orders. Handle missing runs and unreachable warehouse routes predictably; record shortage explanations without reserving physical inventory during planning. | H17: Isolated test database/fixtures; authorized actor and required stock/payment state. Execute only with verified evidence. Mapping managed in Test Documentation, Unit Test and Test Report v1.3.
A18: 8 | B18: Return each order’s approved allocation result by line, warehouse and batch, including final batch prices, shortage or release reasons and allocation state. Short orders remain unfulfilled and must not retain priority wh | C18: AllocationRunResultTests | D18: Allocation outcome and shortage reporting | E18: F-08 | F18: Allocation Run Result | G18: Return each order’s approved allocation result by line, warehouse and batch, including final batch prices, shortage or release reasons and allocation state. Short orders remain unfulfilled and must not retain priority when recreated as new orders. | H18: Isolated test database/fixtures; authorized actor and required stock/payment state. Execute only with verified evidence. Mapping managed in Test Documentation, Unit Test and Test Report v1.3.
A19: 9 | B19: Resolve each retailer line’s minimum life on receipt (MLOR) by SKU rule first, then category rule, then product default. Apply expiry and arrival-time eligibility before any shelf-life discount; discounts must never rela | C19: WarehouseConfigurationServiceTests | D19: Warehouse master data, service scope and MLOR | E19: F-09 | F19: Warehouse Config | G19: Resolve each retailer line’s minimum life on receipt (MLOR) by SKU rule first, then category rule, then product default. Apply expiry and arrival-time eligibility before any shelf-life discount; discounts must never relax the effective MLOR. | H19: Isolated test database/fixtures; authorized actor and required stock/payment state. Execute only with verified evidence. Mapping managed in Test Documentation, Unit Test and Test Report v1.3.
A20: 10 | B20: Record the eligibility filters, rejection reasons, weighted scores and selected quantities for every candidate batch and warehouse in an allocation proposal. Preserve the effective MLOR, source versions and scoring setti | C20: AllocationTraceServiceTests | D20: Line/warehouse candidate filtering and trace evidence | E20: F-10 | F20: Allocation Trace | G20: Record the eligibility filters, rejection reasons, weighted scores and selected quantities for every candidate batch and warehouse in an allocation proposal. Preserve the effective MLOR, source versions and scoring settings used by the run. | H20: Isolated test database/fixtures; authorized actor and required stock/payment state. Execute only with verified evidence. Mapping managed in Test Documentation, Unit Test and Test Report v1.3.
A21: 11 | B21: Filter stock by batch availability, expiry, service reach and MLOR, then allocate deterministically under server order priority (score tie: earlier expiry, nearer warehouse, ascending batch code) and whole-order fulfillm | C21: AllocationEngineTests | D21: FEFO–MLOR scoring and FEFO benchmark | E21: F-11 | F21: Allocation Engine + Benchmark | G21: Filter stock by batch availability, expiry, service reach and MLOR, then allocate deterministically under server order priority (score tie: earlier expiry, nearer warehouse, ascending batch code) and whole-order fulfillment rules. Compare Weighted FEFO and Strict FEFO on identical eligible data using complete/short cou | H21: Isolated test database/fixtures; authorized actor and required stock/payment state. Execute only with verified evidence. Mapping managed in Test Documentation, Unit Test and Test Report v1.3.
A22: 12 | B22: Configure shelf-life tiers as percentage discounts only (0% to less than 100%); reject fixed-amount rules and any final rounded unit price <=0. Apply eligible SKU over category tier after MLOR eligibility and ordinary pr | C22: ShelfLifeDiscountServiceTests | D22: Tier precedence and expiration-window boundaries | E22: F-12 | F22: Shelf Life Discount | G22: Configure shelf-life tiers as percentage discounts only (0% to less than 100%); reject fixed-amount rules and any final rounded unit price <=0. Apply eligible SKU over category tier after MLOR eligibility and ordinary promotion, retain immutable per-batch and warehouse pricing with whole-VND rounding. | H22: Isolated test database/fixtures; authorized actor and required stock/payment state. Execute only with verified evidence. Mapping managed in Test Documentation, Unit Test and Test Report v1.3.
... A48: 38 | B48: Authorize both Administrator and Operator to create, price, edit Draft, publish and inactivate SKU records within their scopes; preserve unique SKU, versioned prices and Published immutability. Unauthorized users cannot | C48: CatalogServiceTests | D48: Category hierarchy and product publish/clone lifecycle | E48: F-38 | F48: Catalog Service | G48: Authorize both Administrator and Operator to create, price, edit Draft, publish and inactivate SKU records within their scopes; preserve unique SKU, versioned prices and Published immutability. Unauthorized users cannot edit; replacements create independent Draft versions without stock/history transfer. | H48: Isolated test database/fixtures; authorized actor and required stock/payment state. Execute only with verified evidence. Mapping managed in Test Documentation, Unit Test and Test Report v1.3.

Sheet Statistics
A2: UNIT TEST REPORT
A4: Project Name | B4: =Cover!B4 -> FSCM – Short Shelf-Life FMCG Supply Chain Management | D4: Creator | F4: Doan Duc Hai
A5: Project Code | B5: =Cover!B5 -> FA26SE083 | D5: Reviewer/Approver
A6: Document Code | B6: FA26SE083_Unit Test Report_v1.3 | D6: Issue Date | F6: 46323
A7: Notes | B7: Report 5 v1.3 includes exactly Test Documentation, Unit Test and Test Report. 192 planned Unit Test scenarios; Pass/Fail/Executed Date/Evidence remain blank until tested. Business baseline: allocation 00:00 ICT; percentage-only expiry tiers; 1 point/10,000 VND; no gift confirmation step by Retailer.
A11: No | B11: Function code | C11: Passed | D11: Failed | E11: Untested | F11: N | G11: A | H11: B | I11: Total Test Cases
A12: 1 | B12: Allocation Plan Approval | C12: ='Allocation Plan Approval'!A7 -> 0 | D12: ='Allocation Plan Approval'!C7 -> 0 | E12: ='Allocation Plan Approval'!F7 -> 6 | F12: ='Allocation Plan Approval'!L7 -> 3 | G12: ='Allocation Plan Approval'!M7 -> 3 | H12: ='Allocation Plan Approval'!N7 -> 0 | I12: ='Allocation Plan Approval'!O7 -> 6
A13: 2 | B13: Refund Service | C13: ='Refund Service'!A7 -> 0 | D13: ='Refund Service'!C7 -> 0 | E13: ='Refund Service'!F7 -> 4 | F13: ='Refund Service'!L7 -> 1 | G13: ='Refund Service'!M7 -> 2 | H13: ='Refund Service'!N7 -> 1 | I13: ='Refund Service'!O7 -> 4
A14: 3 | B14: Allocation Planner | C14: ='Allocation Planner'!A7 -> 0 | D14: ='Allocation Planner'!C7 -> 0 | E14: ='Allocation Planner'!F7 -> 5 | F14: ='Allocation Planner'!L7 -> 2 | G14: ='Allocation Planner'!M7 -> 2 | H14: ='Allocation Planner'!N7 -> 1 | I14: ='Allocation Planner'!O7 -> 5
A15: 4 | B15: Manual Payment | C15: ='Manual Payment'!A7 -> 0 | D15: ='Manual Payment'!C7 -> 0 | E15: ='Manual Payment'!F7 -> 4 | F15: ='Manual Payment'!L7 -> 2 | G15: ='Manual Payment'!M7 -> 2 | H15: ='Manual Payment'!N7 -> 0 | I15: ='Manual Payment'!O7 -> 4
A16: 5 | B16: Inventory Service | C16: ='Inventory Service'!A7 -> 0 | D16: ='Inventory Service'!C7 -> 0 | E16: ='Inventory Service'!F7 -> 5 | F16: ='Inventory Service'!L7 -> 3 | G16: ='Inventory Service'!M7 -> 2 | H16: ='Inventory Service'!N7 -> 0 | I16: ='Inventory Service'!O7 -> 5
A17: 6 | B17: QR Label Service | C17: ='QR Label Service'!A7 -> 0 | D17: ='QR Label Service'!C7 -> 0 | E17: ='QR Label Service'!F7 -> 4 | F17: ='QR Label Service'!L7 -> 3 | G17: ='QR Label Service'!M7 -> 1 | H17: ='QR Label Service'!N7 -> 0 | I17: ='QR Label Service'!O7 -> 4
A18: 7 | B18: Allocation Run Planning | C18: ='Allocation Run Planning'!A7 -> 0 | D18: ='Allocation Run Planning'!C7 -> 0 | E18: ='Allocation Run Planning'!F7 -> 4 | F18: ='Allocation Run Planning'!L7 -> 1 | G18: ='Allocation Run Planning'!M7 -> 3 | H18: ='Allocation Run Planning'!N7 -> 0 | I18: ='Allocation Run Planning'!O7 -> 4
A19: 8 | B19: Allocation Run Result | C19: ='Allocation Run Result'!A7 -> 0 | D19: ='Allocation Run Result'!C7 -> 0 | E19: ='Allocation Run Result'!F7 -> 4 | F19: ='Allocation Run Result'!L7 -> 2 | G19: ='Allocation Run Result'!M7 -> 2 | H19: ='Allocation Run Result'!N7 -> 0 | I19: ='Allocation Run Result'!O7 -> 4
A20: 9 | B20: Warehouse Config | C20: ='Warehouse Config'!A7 -> 0 | D20: ='Warehouse Config'!C7 -> 0 | E20: ='Warehouse Config'!F7 -> 4 | F20: ='Warehouse Config'!L7 -> 2 | G20: ='Warehouse Config'!M7 -> 1 | H20: ='Warehouse Config'!N7 -> 1 | I20: ='Warehouse Config'!O7 -> 4
A21: 10 | B21: Allocation Trace | C21: ='Allocation Trace'!A7 -> 0 | D21: ='Allocation Trace'!C7 -> 0 | E21: ='Allocation Trace'!F7 -> 4 | F21: ='Allocation Trace'!L7 -> 2 | G21: ='Allocation Trace'!M7 -> 2 | H21: ='Allocation Trace'!N7 -> 0 | I21: ='Allocation Trace'!O7 -> 4
A22: 11 | B22: Allocation Engine + Benchmark | C22: ='Allocation Engine + Benchmark'!A7 -> 0 | D22: ='Allocation Engine + Benchmark'!C7 -> 0 | E22: ='Allocation Engine + Benchmark'!F7 -> 7 | F22: ='Allocation Engine + Benchmark'!L7 -> 4 | G22: ='Allocation Engine + Benchmark'!M7 -> 1 | H22: ='Allocation Engine + Benchmark'!N7 -> 2 | I22: ='Allocation Engine + Benchmark'!O7 -> 7
A23: 12 | B23: Shelf Life Discount | C23: ='Shelf Life Discount'!A7 -> 0 | D23: ='Shelf Life Discount'!C7 -> 0 | E23: ='Shelf Life Discount'!F7 -> 4 | F23: ='Shelf Life Discount'!L7 -> 2 | G23: ='Shelf Life Discount'!M7 -> 0 | H23: ='Shelf Life Discount'!N7 -> 2 | I23: ='Shelf Life Discount'!O7 -> 4
A24: 13 | B24: Order Service | C24: ='Order Service'!A7 -> 0 | D24: ='Order Service'!C7 -> 0 | E24: ='Order Service'!F7 -> 5 | F24: ='Order Service'!L7 -> 2 | G24: ='Order Service'!M7 -> 2 | H24: ='Order Service'!N7 -> 1 | I24: ='Order Service'!O7 -> 5
A25: 14 | B25: Promotion Service | C25: ='Promotion Service'!A7 -> 0 | D25: ='Promotion Service'!C7 -> 0 | E25: ='Promotion Service'!F7 -> 5 | F25: ='Promotion Service'!L7 -> 3 | G25: ='Promotion Service'!M7 -> 1 | H25: ='Promotion Service'!N7 -> 1 | I25: ='Promotion Service'!O7 -> 5
A26: 15 | B26: Report Service | C26: ='Report Service'!A7 -> 0 | D26: ='Report Service'!C7 -> 0 | E26: ='Report Service'!F7 -> 4 | F26: ='Report Service'!L7 -> 2 | G26: ='Report Service'!M7 -> 2 | H26: ='Report Service'!N7 -> 0 | I26: ='Report Service'!O7 -> 4
A27: 16 | B27: Retailer Service | C27: ='Retailer Service'!A7 -> 0 | D27: ='Retailer Service'!C7 -> 0 | E27: ='Retailer Service'!F7 -> 5 | F27: ='Retailer Service'!L7 -> 3 | G27: ='Retailer Service'!M7 -> 2 | H27: ='Retailer Service'!N7 -> 0 | I27: ='Retailer Service'!O7 -> 5
A28: 17 | B28: Loyalty & Rewards | C28: ='Loyalty & Rewards'!A7 -> 0 | D28: ='Loyalty & Rewards'!C7 -> 0 | E28: ='Loyalty & Rewards'!F7 -> 5 | F28: ='Loyalty & Rewards'!L7 -> 2 | G28: ='Loyalty & Rewards'!M7 -> 2 | H28: ='Loyalty & Rewards'!N7 -> 1 | I28: ='Loyalty & Rewards'!O7 -> 5
A29: 18 | B29: Delivery ETA + Maps | C29: ='Delivery ETA + Maps'!A7 -> 0 | D29: ='Delivery ETA + Maps'!C7 -> 0 | E29: ='Delivery ETA + Maps'!F7 -> 5 | F29: ='Delivery ETA + Maps'!L7 -> 2 | G29: ='Delivery ETA + Maps'!M7 -> 1 | H29: ='Delivery ETA + Maps'!N7 -> 2 | I29: ='Delivery ETA + Maps'!O7 -> 5
A30: 19 | B30: Delivery Service | C30: ='Delivery Service'!A7 -> 0 | D30: ='Delivery Service'!C7 -> 0 | E30: ='Delivery Service'!F7 -> 5 | F30: ='Delivery Service'!L7 -> 0 | G30: ='Delivery Service'!M7 -> 3 | H30: ='Delivery Service'!N7 -> 2 | I30: ='Delivery Service'!O7 -> 5
A31: 20 | B31: Allocation Pricing | C31: ='Allocation Pricing'!A7 -> 0 | D31: ='Allocation Pricing'!C7 -> 0 | E31: ='Allocation Pricing'!F7 -> 5 | F31: ='Allocation Pricing'!L7 -> 3 | G31: ='Allocation Pricing'!M7 -> 1 | H31: ='Allocation Pricing'!N7 -> 1 | I31: ='Allocation Pricing'!O7 -> 5
A32: 21 | B32: Picking Service | C32: ='Picking Service'!A7 -> 0 | D32: ='Picking Service'!C7 -> 0 | E32: ='Picking Service'!F7 -> 5 | F32: ='Picking Service'!L7 -> 2 | G32: ='Picking Service'!M7 -> 3 | H32: ='Picking Service'!N7 -> 0 | I32: ='Picking Service'!O7 -> 5
A33: 22 | B33: Shipment Service | C33: ='Shipment Service'!A7 -> 0 | D33: ='Shipment Service'!C7 -> 0 | E33: ='Shipment Service'!F7 -> 5 | F33: ='Shipment Service'!L7 -> 2 | G33: ='Shipment Service'!M7 -> 3 | H33: ='Shipment Service'!N7 -> 0 | I33: ='Shipment Service'!O7 -> 5
A34: 23 | B34: Allocation Reservation | C34: ='Allocation Reservation'!A7 -> 0 | D34: ='Allocation Reservation'!C7 -> 0 | E34: ='Allocation Reservation'!F7 -> 5 | F34: ='Allocation Reservation'!L7 -> 3 | G34: ='Allocation Reservation'!M7 -> 2 | H34: ='Allocation Reservation'!N7 -> 0 | I34: ='Allocation Reservation'!O7 -> 5
A35: 24 | B35: Allocation Run Service | C35: ='Allocation Run Service'!A7 -> 0 | D35: ='Allocation Run Service'!C7 -> 0 | E35: ='Allocation Run Service'!F7 -> 5 | F35: ='Allocation Run Service'!L7 -> 0 | G35: ='Allocation Run Service'!M7 -> 2 | H35: ='Allocation Run Service'!N7 -> 3 | I35: ='Allocation Run Service'!O7 -> 5
A36: 25 | B36: Expiry Sweep & Outbox | C36: ='Expiry Sweep & Outbox'!A7 -> 0 | D36: ='Expiry Sweep & Outbox'!C7 -> 0 | E36: ='Expiry Sweep & Outbox'!F7 -> 7 | F36: ='Expiry Sweep & Outbox'!L7 -> 3 | G36: ='Expiry Sweep & Outbox'!M7 -> 3 | H36: ='Expiry Sweep & Outbox'!N7 -> 1 | I36: ='Expiry Sweep & Outbox'!O7 -> 7
A37: 26 | B37: Allocation Price Lookup | C37: ='Allocation Price Lookup'!A7 -> 0 | D37: ='Allocation Price Lookup'!C7 -> 0 | E37: ='Allocation Price Lookup'!F7 -> 4 | F37: ='Allocation Price Lookup'!L7 -> 2 | G37: ='Allocation Price Lookup'!M7 -> 1 | H37: ='Allocation Price Lookup'!N7 -> 1 | I37: ='Allocation Price Lookup'!O7 -> 4
A38: 27 | B38: MB Money and Limits | C38: ='MB Money and Limits'!A7 -> 0 | D38: ='MB Money and Limits'!C7 -> 0 | E38: ='MB Money and Limits'!F7 -> 7 | F38: ='MB Money and Limits'!L7 -> 4 | G38: ='MB Money and Limits'!M7 -> 1 | H38: ='MB Money and Limits'!N7 -> 2 | I38: ='MB Money and Limits'!O7 -> 7
A39: 28 | B39: Allocation Scenarios | C39: ='Allocation Scenarios'!A7 -> 0 | D39: ='Allocation Scenarios'!C7 -> 0 | E39: ='Allocation Scenarios'!F7 -> 5 | F39: ='Allocation Scenarios'!L7 -> 0 | G39: ='Allocation Scenarios'!M7 -> 3 | H39: ='Allocation Scenarios'!N7 -> 2 | I39: ='Allocation Scenarios'!O7 -> 5
A40: 29 | B40: Transit Table | C40: ='Transit Table'!A7 -> 0 | D40: ='Transit Table'!C7 -> 0 | E40: ='Transit Table'!F7 -> 4 | F40: ='Transit Table'!L7 -> 2 | G40: ='Transit Table'!M7 -> 0 | H40: ='Transit Table'!N7 -> 2 | I40: ='Transit Table'!O7 -> 4
A41: 30 | B41: MB Business IDs | C41: ='MB Business IDs'!A7 -> 0 | D41: ='MB Business IDs'!C7 -> 0 | E41: ='MB Business IDs'!F7 -> 9 | F41: ='MB Business IDs'!L7 -> 6 | G41: ='MB Business IDs'!M7 -> 2 | H41: ='MB Business IDs'!N7 -> 1 | I41: ='MB Business IDs'!O7 -> 9
A42: 31 | B42: Payment Service | C42: ='Payment Service'!A7 -> 0 | D42: ='Payment Service'!C7 -> 0 | E42: ='Payment Service'!F7 -> 5 | F42: ='Payment Service'!L7 -> 2 | G42: ='Payment Service'!M7 -> 2 | H42: ='Payment Service'!N7 -> 1 | I42: ='Payment Service'!O7 -> 5
A43: 32 | B43: Run Picking Issue | C43: ='Run Picking Issue'!A7 -> 0 | D43: ='Run Picking Issue'!C7 -> 0 | E43: ='Run Picking Issue'!E7 -> 5 | F43: ='Run Picking Issue'!K7 -> 3 | G43: ='Run Picking Issue'!L7 -> 2 | H43: ='Run Picking Issue'!M7 -> 0 | I43: ='Run Picking Issue'!N7 -> 5
A44: 33 | B44: Identity Service | C44: ='Identity Service'!A7 -> 0 | D44: ='Identity Service'!C7 -> 0 | E44: ='Identity Service'!E7 -> 5 | F44: ='Identity Service'!K7 -> 4 | G44: ='Identity Service'!L7 -> 1 | H44: ='Identity Service'!M7 -> 0 | I44: ='Identity Service'!N7 -> 5
A45: 34 | B45: Offline Snapshot & Queue | C45: ='Offline Snapshot & Queue'!A7 -> 0 | D45: ='Offline Snapshot & Queue'!C7 -> 0 | E45: ='Offline Snapshot & Queue'!E7 -> 10 | F45: ='Offline Snapshot & Queue'!K7 -> 3 | G45: ='Offline Snapshot & Queue'!L7 -> 6 | H45: ='Offline Snapshot & Queue'!M7 -> 1 | I45: ='Offline Snapshot & Queue'!N7 -> 10
A46: 35 | B46: Territory Service | C46: ='Territory Service'!A7 -> 0 | D46: ='Territory Service'!C7 -> 0 | E46: ='Territory Service'!E7 -> 4 | F46: ='Territory Service'!K7 -> 1 | G46: ='Territory Service'!L7 -> 2 | H46: ='Territory Service'!M7 -> 1 | I46: ='Territory Service'!N7 -> 4
A47: 36 | B47: Inventory Lifecycle | C47: ='Inventory Lifecycle'!A7 -> 0 | D47: ='Inventory Lifecycle'!C7 -> 0 | E47: ='Inventory Lifecycle'!E7 -> 4 | F47: ='Inventory Lifecycle'!K7 -> 2 | G47: ='Inventory Lifecycle'!L7 -> 2 | H47: ='Inventory Lifecycle'!M7 -> 0 | I47: ='Inventory Lifecycle'!N7 -> 4
A48: 37 | B48: Inventory Lock | C48: ='Inventory Lock'!A7 -> 0 | D48: ='Inventory Lock'!C7 -> 0 | E48: ='Inventory Lock'!E7 -> 4 | F48: ='Inventory Lock'!K7 -> 1 | G48: ='Inventory Lock'!L7 -> 2 | H48: ='Inventory Lock'!M7 -> 1 | I48: ='Inventory Lock'!N7 -> 4
A49: 38 | B49: Catalog Service | C49: ='Catalog Service'!A7 -> 0 | D49: ='Catalog Service'!C7 -> 0 | E49: ='Catalog Service'!E7 -> 5 | F49: ='Catalog Service'!K7 -> 3 | G49: ='Catalog Service'!L7 -> 2 | H49: ='Catalog Service'!M7 -> 0 | I49: ='Catalog Service'!N7 -> 5
B50: Sub total | C50: =SUM(C12:C49) -> 0 | D50: =SUM(D12:D49) -> 0 | E50: =SUM(E12:E49) -> 192 | F50: =SUM(F12:F49) -> 87 | G50: =SUM(G12:G49) -> 74 | H50: =SUM(H12:H49) -> 31 | I50: =SUM(I12:I49) -> 192
B52: Test coverage | D52: =IFERROR((C50+D50)*100/I50,0) -> 0 | E52: %
B53: Test successful coverage | D53: =IFERROR(C50*100/I50,0) -> 0 | E53: %
B54: Normal case | D54: =IFERROR(F50*100/I50,0) -> 45.3125 | E54: %
B55: Abnormal case | D55: =IFERROR(G50*100/I50,0) -> 38.541667 | E55: %
B56: Boundary case | D56: =IFERROR(H50*100/I50,0) -> 16.145833 | E56: %

Sheet Allocation Plan Approval
A2: Function Code | C2: =Functions!E11 -> F-01 | F2: Function Name | L2: =Functions!D11 -> Allocation proposal review, approval and revision
A3: Created By | C3: Doan Duc Hai | F3: Executed By
A4: Lines of code | F4: Lack of test cases | L4: =IF(OR(C4="",Functions!E6="N/A"),"N/A",C4*Functions!E6/1000-O7) -> N/A
A5: Test requirement | C5: Review versioned FEFO–MLOR allocation proposals and approved batch prices; allow only an authorized Administrator to approve the current version or request a reasoned recalculation. Reject stale or repeated conflicting decisions and do not reserve stock before approval.
A6: Passed | C6: Failed | F6: Untested | L6: N/A/B | O6: Total Test Cases
A7: =COUNTIF(F39:O39,"P") -> 0 | C7: =COUNTIF(F39:O39,"F") -> 0 | F7: =SUM(O7,-A7,-C7) -> 6 | L7: =COUNTIF(F38:O38,"N") -> 3 | M7: =COUNTIF(F38:O38,"A") -> 3 | N7: =COUNTIF(F38:O38,"B") -> 0 | O7: =COUNTA(F9:O9) -> 6
F9: UTCID01 | G9: UTCID02 | H9: UTCID03 | I9: UTCID04 | J9: UTCID05 | K9: UTCID06
A10: Condition | B10: Input / scenario
D11: Draft plan has no approved final price or stock reservation | F11: O
D12: Admin approves priced proposal version v2 with current version token | G12: O
D13: Second decision is made on an already approved proposal | H13: O
D14: Admin approves using stale expected proposal version | I14: O
D16: Admin requests recalculation with reason and version v2 | J16: O
D17: Recalculation is requested without a reason | K17: O
A29: Confirm | B29: Expected result
D30: Run is AwaitingApproval; no quotation, PO, reservation or picking list exists | F30: O
D31: One approved price version is recorded; reservation and quotation are consistent | G31: O
D33: Reject incompatible re-decision; no extra reservation or pricing snapshot | H33: O
D35: 409 conflict; no stock hold, PO, picking or payment side effects | I35: O
D36: New proposal version is pending; old approved trace retained; no silent price overwrite | J36: O
D37: Validation error; current proposal status and price snapshot unchanged | K37: O
A38: Result | B38: Type(N : Normal, A : Abnormal, B : Boundary) | F38: N | G38: N | H38: A | I38: A | J38: N | K38: A
B39: Passed/Failed
B40: Executed Date
B41: Defect ID

Sheet Refund Service
A2: Function Code | C2: =Functions!E12 -> F-02 | F2: Function Name | L2: =Functions!D12 -> Manual refund state, evidence and separation of duties
A3: Created By | C3: Doan Duc Hai | F3: Executed By
A4: Lines of code | F4: Lack of test cases | L4: =IF(OR(C4="",Functions!E6="N/A"),"N/A",C4*Functions!E6/1000-O7) -> N/A
A5: Test requirement | C5: Record and verify manual refunds against approved cancellation or complaint adjustments, limiting each refund to the affected batch’s actual net price. Preserve evidence and require independent Administrator verification without applying a second loyalty reversal.
A6: Passed | C6: Failed | F6: Untested | L6: N/A/B | O6: Total Test Cases
A7: =COUNTIF(F51:O51,"P") -> 0 | C7: =COUNTIF(F51:O51,"F") -> 0 | F7: =SUM(O7,-A7,-C7) -> 4 | L7: =COUNTIF(F50:O50,"N") -> 1 | M7: =COUNTIF(F50:O50,"A") -> 2 | N7: =COUNTIF(F50:O50,"B") -> 1 | O7: =COUNTA(F9:O9) -> 4
F9: UTCID01 | G9: UTCID02 | H9: UTCID03 | I9: UTCID04
A10: Condition | B10: Input / scenario
D11: Operator submits bank transfer evidence; independent Administrator verifies | F11: O
D12: Refund concerns 3 damaged units of batch X whose approved net unit price is 85 | G12: O
D14: Administrator rejects inadequate refund proof; Operator re-submits supplements | H14: O
D15: User who submitted refund evidence attempts to verify it | I15: O
A33: Confirm | B33: Expected result
D34: Two-person authorization; verification cannot debit loyalty again | F34: O
D35: Max approved refund = 255 based on affected batch X net price, not list/average | G35: O
D37: Preserve rejected evidence history; only new verified evidence can complete refund | H37: O
D38: Separation-of-duties 403; no duplicate payment, refund or points reversal | I38: O
A50: Result | B50: Type(N : Normal, A : Abnormal, B : Boundary) | F50: N | G50: B | H50: A | I50: A
B51: Passed/Failed
B52: Executed Date
B53: Defect ID

Sheet Allocation Planner
A2: Function Code | C2: =Functions!E13 -> F-03 | F2: Function Name | L2: =Functions!D13 -> Order priority, multi-batch allocation and whole-order shortfall
A3: Created By | C3: Doan Duc Hai | F3: Executed By
A4: Lines of code | F4: Lack of test cases | L4: =IF(OR(C4="",Functions!E6="N/A"),"N/A",C4*Functions!E6/1000-O7) -> N/A
A5: Test requirement | C5: Allocate eligible warehouse batches to orders in server-acceptance priority without replacing batches already given to earlier orders. Support multi-batch fulfillment; if any required line is short, release all tentative draws for that order to the shared pool. At equal weighted score use earliest expiry, shortest route distance, then ascending batch code; do not swap an earlier order batch for a later order.
A6: Passed | C6: Failed | F6: Untested | L6: N/A/B | O6: Total Test Cases
A7: =COUNTIF(F27:O27,"P") -> 0 | C7: =COUNTIF(F27:O27,"F") -> 0 | F7: =SUM(O7,-A7,-C7) -> 5 | L7: =COUNTIF(F26:O26,"N") -> 2 | M7: =COUNTIF(F26:O26,"A") -> 2 | N7: =COUNTIF(F26:O26,"B") -> 1 | O7: =COUNTA(F9:O9) -> 5
F9: UTCID01 | G9: UTCID02 | H9: UTCID03 | I9: UTCID04 | J9: UTCID05
A10: Condition | B10: Input / scenario
D11: Earlier eligible order A needs 10; later order B needs same 10 | F11: O
D12: Later order has shorter route or better FEFO score than already fulfilled A | G12: O
D14: First order has two lines; second line cannot be filled | H14: O
D15: Short order releases 10 from SKU-A; later complete order requests 10 | I15: O
D17: Order needs 10 split between batches/warehouses 6 + 4 | J17: O
A19: Confirm | B19: Expected result
D20: A owns its allocated batch; later B cannot take or swap that allocation | F20: O
D21: Never displace A batch; later order is short if pool is insufficient | G21: O
D23: Return all tentative draws for first order; no partial fulfillment | H23: O
D24: Later eligible order can use released pool without inheriting old priority | I24: O
D25: Exactly 10 allocated with trace per batch/warehouse, no duplicate count | J25: O
A26: Result | B26: Type(N : Normal, A : Abnormal, B : Boundary) | F26: N | G26: A | H26: A | I26: N | J26: B
B27: Passed/Failed
B28: Executed Date
B29: Defect ID

Sheet Manual Payment
A2: Function Code | C2: =Functions!E14 -> F-04 | F2: Function Name | L2: =Functions!D14 -> Prepaid transfer, deferred cash collection, actor scope; reject COD
A3: Created By | C3: Doan Duc Hai | F3: Executed By
A4: Lines of code | F4: Lack of test cases | L4: =IF(OR(C4="",Functions!E6="N/A"),"N/A",C4*Functions!E6/1000-O7) -> N/A
A5: Test requirement | C5: Reject COD as an unsupported payment method. Verify a full prepaid bank transfer only after final-price approval and before dispatch; allow full cash collection for an assigned, delivered deferred order and restrict bank-transfer verification to authorized staff. Credit cash collection remains assigned Sales only after delivery; transfer verification requires authorized Operator/Administrator.
A6: Passed | C6: Failed | F6: Untested | L6: N/A/B | O6: Total Test Cases
A7: =COUNTIF(F54:O54,"P") -> 0 | C7: =COUNTIF(F54:O54,"F") -> 0 | F7: =SUM(O7,-A7,-C7) -> 4 | L7: =COUNTIF(F53:O53,"N") -> 2 | M7: =COUNTIF(F53:O53,"A") -> 2 | N7: =COUNTIF(F53:O53,"B") -> 0 | O7: =COUNTA(F9:O9) -> 4
F9: UTCID01 | G9: UTCID02 | H9: UTCID03 | I9: UTCID04
A10: Condition | B10: Input / scenario
D11: Any actor requests COD for an order at any status | F11: O
D12: Operator verifies full prepaid BANK TRANSFER proof after approved final quote and before dispatch | G12: O
D14: Sales collects CASH for own fully delivered deferred order under valid credit term | H14: O
D15: Sales tries bank-transfer verification or submits partial deferred collection | I15: O
A32: Confirm | B32: Expected result
D33: Unsupported COD rejected; payment/PO/dispatch/ledger unchanged | F33: O
D35: Create one verified prepaid payment against approved net price before deadline; replay idempotent | G35: O
D36: Full cash collection is allowed only for assigned Sales; record once with evidence | H36: O
D37: Reject wrong actor or partial amount; Operator/Admin checks bank transfer; no premature settlement | I37: O
A53: Result | B53: Type(N : Normal, A : Abnormal, B : Boundary) | F53: A | G53: N | H53: N | I53: A
B54: Passed/Failed
B55: Executed Date
B56: Defect ID

Sheet Inventory Service
A2: Function Code | C2: =Functions!E15 -> F-05 | F2: Function Name | L2: =Functions!D15 -> Goods receipt posting and warehouse balances
A3: Created By | C3: Doan Duc Hai | F3: Executed By
A4: Lines of code | F4: Lack of test cases | L4: =IF(OR(C4="",Functions!E6="N/A"),"N/A",C4*Functions!E6/1000-O7) -> N/A
A5: Test requirement | C5: Keep warehouse stock unchanged until a goods receipt is approved; then create or merge the appropriate SKU–expiry batch and record one auditable stock movement. Prevent duplicate receipts and reject reuse of an idempotency key with different contents.
A6: Passed | C6: Failed | F6: Untested | L6: N/A/B | O6: Total Test Cases
A7: =COUNTIF(F44:O44,"P") -> 0 | C7: =COUNTIF(F44:O44,"F") -> 0 | F7: =SUM(O7,-A7,-C7) -> 5 | L7: =COUNTIF(F43:O43,"N") -> 3 | M7: =COUNTIF(F43:O43,"A") -> 2 | N7: =COUNTIF(F43:O43,"B") -> 0 | O7: =COUNTA(F9:O9) -> 5
F9: UTCID01 | G9: UTCID02 | H9: UTCID03 | I9: UTCID04 | J9: UTCID05
A10: Condition | B10: Input / scenario
D11: Creating receipt keeps inventory unchanged until approval | F11: O
D12: Approval creates business batch and inventory ledger | G12: O
D14: Same warehouse sku and expiry merges into existing batch on approv… | H14: O
D15: Repeated create and approval are idempotent without adding stock t… | I15: O
D16: Reusing idempotency key for changed payload is rejected | J16: O
A31: Confirm | B31: Expected result
D32: Creating receipt keeps inventory unchanged until approval. | F32: O
D34: Approval creates business batch and inventory ledger. | G34: O
D35: Same warehouse sku and expiry merges into existing batch on approval. | H35: O
D36: Repeated create and approval are idempotent without adding stock twic… | I36: O
D37: Reusing idempotency key for changed payload is rejected. | J37: O
A43: Result | B43: Type(N : Normal, A : Abnormal, B : Boundary) | F43: N | G43: N | H43: N | I43: A | J43: A
B44: Passed/Failed
B45: Executed Date
B46: Defect ID

Sheet QR Label Service
A2: Function Code | C2: =Functions!E16 -> F-06 | F2: Function Name | L2: =Functions!D16 -> QR quantity labels, lineage, split and replay
A3: Created By | C3: Doan Duc Hai | F3: Executed By
A4: Lines of code | F4: Lack of test cases | L4: =IF(OR(C4="",Functions!E6="N/A"),"N/A",C4*Functions!E6/1000-O7) -> N/A
A5: Test requirement | C5: Generate and split QR labels only for valid available batch quantities, preserving unique codes, parent–child lineage and warehouse/batch identity. Repeated operations must not create duplicate labels or change stock quantities twice.
A6: Passed | C6: Failed | F6: Untested | L6: N/A/B | O6: Total Test Cases
A7: =COUNTIF(F47:O47,"P") -> 0 | C7: =COUNTIF(F47:O47,"F") -> 0 | F7: =SUM(O7,-A7,-C7) -> 4 | L7: =COUNTIF(F46:O46,"N") -> 3 | M7: =COUNTIF(F46:O46,"A") -> 1 | N7: =COUNTIF(F46:O46,"B") -> 0 | O7: =COUNTA(F9:O9) -> 4
F9: UTCID01 | G9: UTCID02 | H9: UTCID03 | I9: UTCID04
A10: Condition | B10: Input / scenario
D11: Generate creates code and is idempotent | F11: O
D12: Generate rejects quantity above unlabelled physical stock | G12: O
D14: Generate counts picked stock but excludes already issued labels | H14: O
D15: Split reduces parent and links child to root | I15: O
A31: Confirm | B31: Expected result
D32: Generate creates code and is idempotent. | F32: O
D34: Generate rejects quantity above unlabelled physical stock. | G34: O
D35: Generate counts picked stock but excludes already issued labels. | H35: O
D36: Split reduces parent and links child to root. | I36: O
A46: Result | B46: Type(N : Normal, A : Abnormal, B : Boundary) | F46: N | G46: A | H46: N | I46: N
B47: Passed/Failed
B48: Executed Date
B49: Defect ID

Sheet Allocation Run Planning
A2: Function Code | C2: =Functions!E17 -> F-07 | F2: Function Name | L2: =Functions!D17 -> Daily run orchestration, shared pool, trace records
A3: Created By | C3: Doan Duc Hai | F3: Executed By
A4: Lines of code | F4: Lack of test cases | L4: =IF(OR(C4="",Functions!E6="N/A"),"N/A",C4*Functions!E6/1000-O7) -> N/A
A5: Test requirement | C5: Plan each valid daily allocation-run snapshot once using its frozen settings and eligible orders. Handle missing runs and unreachable warehouse routes predictably; record shortage explanations without reserving physical inventory during planning.
A6: Passed | C6: Failed | F6: Untested | L6: N/A/B | O6: Total Test Cases
A7: =COUNTIF(F46:O46,"P") -> 0 | C7: =COUNTIF(F46:O46,"F") -> 0 | F7: =SUM(O7,-A7,-C7) -> 4 | L7: =COUNTIF(F45:O45,"N") -> 1 | M7: =COUNTIF(F45:O45,"A") -> 3 | N7: =COUNTIF(F45:O45,"B") -> 0 | O7: =COUNTA(F9:O9) -> 4
F9: UTCID01 | G9: UTCID02 | H9: UTCID03 | I9: UTCID04
A10: Condition | B10: Input / scenario
D11: Scheduler plans same dated run a second time | F11: O
D12: Unknown run ID is requested for planning | G12: O
D14: Route unavailable for all batches at cutoff snapshot | H14: O
D15: All eligible orders share one accepted server-timestamp order | I15: O
A31: Confirm | B31: Expected result
D32: Second planning attempt cannot overwrite committed run snapshot or priority | F32: O
D33: NotFound, no new run and no writes to stock/trace | G33: O
D35: Orders are Short with shortage cause; no stock reserved | H35: O
D37: One AwaitingApproval proposal; shared tentative pool leaves physical stock unchanged | I37: O
A45: Result | B45: Type(N : Normal, A : Abnormal, B : Boundary) | F45: A | G45: A | H45: A | I45: N
B46: Passed/Failed
B47: Executed Date
B48: Defect ID

Sheet Allocation Run Result
A2: Function Code | C2: =Functions!E18 -> F-08 | F2: Function Name | L2: =Functions!D18 -> Allocation outcome and shortage reporting
A3: Created By | C3: Doan Duc Hai | F3: Executed By
A4: Lines of code | F4: Lack of test cases | L4: =IF(OR(C4="",Functions!E6="N/A"),"N/A",C4*Functions!E6/1000-O7) -> N/A
A5: Test requirement | C5: Return each order’s approved allocation result by line, warehouse and batch, including final batch prices, shortage or release reasons and allocation state. Short orders remain unfulfilled and must not retain priority when recreated as new orders.
A6: Passed | C6: Failed | F6: Untested | L6: N/A/B | O6: Total Test Cases
A7: =COUNTIF(F42:O42,"P") -> 0 | C7: =COUNTIF(F42:O42,"F") -> 0 | F7: =SUM(O7,-A7,-C7) -> 4 | L7: =COUNTIF(F41:O41,"N") -> 2 | M7: =COUNTIF(F41:O41,"A") -> 2 | N7: =COUNTIF(F41:O41,"B") -> 0 | O7: =COUNTA(F9:O9) -> 4
F9: UTCID01 | G9: UTCID02 | H9: UTCID03 | I9: UTCID04
A10: Condition | B10: Input / scenario
D11: Order is complete across warehouse A and B with approved batch prices | F11: O
D12: Complete A and short B appear in one daily run | G12: O
D14: Order is short and user chooses Create New Order | H14: O
D15: One order line is Released because another line is short | I15: O
A26: Confirm | B26: Expected result
D27: Result aggregates exact chosen quantities and price versions per portion | F27: O
D29: Only A may reserve after approval; B is short and has no held stock | G29: O
D30: New order has new key and server acceptance timestamp; old priority never retained | H30: O
D32: Display Released/Short reason correctly; no partial allocation made permanent | I32: O
A41: Result | B41: Type(N : Normal, A : Abnormal, B : Boundary) | F41: N | G41: N | H41: A | I41: A
B42: Passed/Failed
B43: Executed Date
B44: Defect ID

Sheet Warehouse Config
A2: Function Code | C2: =Functions!E19 -> F-09 | F2: Function Name | L2: =Functions!D19 -> Warehouse master data, service scope and MLOR
A3: Created By | C3: Doan Duc Hai | F3: Executed By
A4: Lines of code | F4: Lack of test cases | L4: =IF(OR(C4="",Functions!E6="N/A"),"N/A",C4*Functions!E6/1000-O7) -> N/A
A5: Test requirement | C5: Resolve each retailer line’s minimum life on receipt (MLOR) by SKU rule first, then category rule, then product default. Apply expiry and arrival-time eligibility before any shelf-life discount; discounts must never relax the effective MLOR.
A6: Passed | C6: Failed | F6: Untested | L6: N/A/B | O6: Total Test Cases
A7: =COUNTIF(F46:O46,"P") -> 0 | C7: =COUNTIF(F46:O46,"F") -> 0 | F7: =SUM(O7,-A7,-C7) -> 4 | L7: =COUNTIF(F45:O45,"N") -> 2 | M7: =COUNTIF(F45:O45,"A") -> 1 | N7: =COUNTIF(F45:O45,"B") -> 1 | O7: =COUNTA(F9:O9) -> 4
F9: UTCID01 | G9: UTCID02 | H9: UTCID03 | I9: UTCID04
A10: Condition | B10: Input / scenario
D11: Retailer SKU MLOR=70% and parent category MLOR=50% | F11: O
D12: Retailer has no SKU MLOR, category MLOR=60% | G12: O
D14: Discount eligible tier exists for batch whose life at ETA fails effective MLOR | H14: O
D15: No retailer SKU/category rule, product default MLOR=40% | I15: O
A30: Confirm | B30: Expected result
D31: Resolve SKU 70%; record effective policy and version | F31: O
D33: Resolve category 60%; product default only when neither exists | G33: O
D34: Reject batch first; near-expiry override is future scope, discount cannot relax MLOR | H34: O
D36: Use product default; evaluate at ETA with policy snapshot | I36: O
A45: Result | B45: Type(N : Normal, A : Abnormal, B : Boundary) | F45: N | G45: N | H45: A | I45: B
B46: Passed/Failed
B47: Executed Date
B48: Defect ID

Sheet Allocation Trace
A2: Function Code | C2: =Functions!E20 -> F-10 | F2: Function Name | L2: =Functions!D20 -> Line/warehouse candidate filtering and trace evidence
A3: Created By | C3: Doan Duc Hai | F3: Executed By
A4: Lines of code | F4: Lack of test cases | L4: =IF(OR(C4="",Functions!E6="N/A"),"N/A",C4*Functions!E6/1000-O7) -> N/A
A5: Test requirement | C5: Record the eligibility filters, rejection reasons, weighted scores and selected quantities for every candidate batch and warehouse in an allocation proposal. Preserve the effective MLOR, source versions and scoring settings used by the run.
A6: Passed | C6: Failed | F6: Untested | L6: N/A/B | O6: Total Test Cases
A7: =COUNTIF(F43:O43,"P") -> 0 | C7: =COUNTIF(F43:O43,"F") -> 0 | F7: =SUM(O7,-A7,-C7) -> 4 | L7: =COUNTIF(F42:O42,"N") -> 2 | M7: =COUNTIF(F42:O42,"A") -> 2 | N7: =COUNTIF(F42:O42,"B") -> 0 | O7: =COUNTA(F9:O9) -> 4
F9: UTCID01 | G9: UTCID02 | H9: UTCID03 | I9: UTCID04
A10: Condition | B10: Input / scenario
D11: Batch does not meet configured SKU MLOR at projected ETA | F11: O
D12: Candidate pool mixes expired, out-of-range and eligible batches | G12: O
D14: Two eligible batches differ in weighted distance/FEFO score | H14: O
D15: Earlier line loses tentative stock because another line is short | I15: O
A25: Confirm | B25: Expected result
D26: Trace rejects at eligibility filter with MLOR reason, before discount | F26: O
D27: Trace records consistent stage and deterministic rejection reasons | G27: O
D29: Trace retains winning and losing score components and tie-break reason | H29: O
D30: Trace shows released quantity/reason; no approved reservation exists | I30: O
A42: Result | B42: Type(N : Normal, A : Abnormal, B : Boundary) | F42: A | G42: N | H42: N | I42: A
B43: Passed/Failed
B44: Executed Date
B45: Defect ID

Sheet Allocation Engine + Benchmark
A2: Function Code | C2: =Functions!E21 -> F-11 | F2: Function Name | L2: =Functions!D21 -> FEFO–MLOR scoring and FEFO benchmark
A3: Created By | C3: Doan Duc Hai | F3: Executed By
A4: Lines of code | F4: Lack of test cases | L4: =IF(OR(C4="",Functions!E6="N/A"),"N/A",C4*Functions!E6/1000-O7) -> N/A
A5: Test requirement | C5: Filter stock by batch availability, expiry, service reach and MLOR, then allocate deterministically under server order priority (score tie: earlier expiry, nearer warehouse, ascending batch code) and whole-order fulfillment rules. Compare Weighted FEFO and Strict FEFO on identical eligible data using complete/short counts, near-expiry quantity, distance, warehouses used and runtime.
A6: Passed | C6: Failed | F6: Untested | L6: N/A/B | O6: Total Test Cases
A7: =COUNTIF(F41:O41,"P") -> 0 | C7: =COUNTIF(F41:O41,"F") -> 0 | F7: =SUM(O7,-A7,-C7) -> 7 | L7: =COUNTIF(F40:O40,"N") -> 4 | M7: =COUNTIF(F40:O40,"A") -> 1 | N7: =COUNTIF(F40:O40,"B") -> 2 | O7: =COUNTA(F9:O9) -> 7
F9: UTCID01 | G9: UTCID02 | H9: UTCID03 | I9: UTCID04 | J9: UTCID05 | K9: UTCID06 | L9: UTCID07
A10: Condition | B10: Input / scenario
D11: Eligible and ineligible batches mixed; MLOR, expiry, locks and ETA apply | F11: O
D12: At ETA batch life is one hour below minimum despite discounted price | G12: O
D14: Same eligible pool has near and far warehouses with weighted priorities | H14: O
D15: One batch partly consumed; another order follows in run priority | I15: O
D17: Order cannot fill every required line after greedy selection | J17: O
D18: Three candidates have identical weighted scores: first compare expiry; at same expiry compare warehouse distance; at same distance compare batch code. | K18: O
D20: Weighted FEFO and strict FEFO use identical eligible pool, priority and all-or-nothing rule | L20: O
A29: Confirm | B29: Expected result
D30: Apply every hard eligibility filter before scoring or discounting | F30: O
D32: Reject batch; no same-day rounding or MLOR override | G32: O
D33: Use documented deterministic weighted score; record total distance | H33: O
D34: Recompute coverage from remaining pool, not original on-hand | I34: O
D36: All-or-nothing; count Short order and release all tentative draws | J36: O
D38: On equal weighted scores, choose earliest expiry; if tied choose nearer warehouse; if still tied choose lexicographically lower batch code; same trace on rerun. | K38: O
D39: Record complete/short orders, near-expiry qty, distance, warehouses/order, runtime for both; do not assert global optimum | L39: O
A40: Result | B40: Type(N : Normal, A : Abnormal, B : Boundary) | F40: N | G40: B | H40: N | I40: N | J40: A | K40: B | L40: N
B41: Passed/Failed
B42: Executed Date
B43: Defect ID

Sheet Shelf Life Discount
A2: Function Code | C2: =Functions!E22 -> F-12 | F2: Function Name | L2: =Functions!D22 -> Tier precedence and expiration-window boundaries
A3: Created By | C3: Doan Duc Hai | F3: Executed By
A4: Lines of code | F4: Lack of test cases | L4: =IF(OR(C4="",Functions!E6="N/A"),"N/A",C4*Functions!E6/1000-O7) -> N/A
A5: Test requirement | C5: Configure shelf-life tiers as percentage discounts only (0% to less than 100%); reject fixed-amount rules and any final rounded unit price <=0. Apply eligible SKU over category tier after MLOR eligibility and ordinary promotion, retain immutable per-batch and warehouse pricing with whole-VND rounding.
A6: Passed | C6: Failed | F6: Untested | L6: N/A/B | O6: Total Test Cases
A7: =COUNTIF(F45:O45,"P") -> 0 | C7: =COUNTIF(F45:O45,"F") -> 0 | F7: =SUM(O7,-A7,-C7) -> 4 | L7: =COUNTIF(F44:O44,"N") -> 2 | M7: =COUNTIF(F44:O44,"A") -> 0 | N7: =COUNTIF(F44:O44,"B") -> 2 | O7: =COUNTA(F9:O9) -> 4
F9: UTCID01 | G9: UTCID02 | H9: UTCID03 | I9: UTCID04
A10: Condition | B10: Input / scenario
D11: SKU percentage tier and category percentage tier both match the same eligible batch | F11: O
D12: SKU tier absent; category tier 15% matches batch remaining life at pricing moment | G12: O
D14: Fixed-amount discount submitted (12 VND per unit, 7 units); compare unchanged percentage-only tier and state. | H14: O
D15: Percentage tier boundary produces fractional VND; reject fixed tier and rounded zero net unit price. | I15: O
A29: Confirm | B29: Expected result
D30: Apply SKU tier once; no stacking and no MLOR relaxation | F30: O
D32: Apply category 15% after batch eligibility, preserve source/version snapshot | G32: O
D33: Reject fixed amount discount configuration; no accepted rule/price record. Valid percentage 12% of 100 VND × 7 units yields total reduction 84 VND, net 616 VND. | H33: O
D34: Use approved currency rounding and upper-exclusive band; net per unit > 0; never waive MLOR | I34: O
A44: Result | B44: Type(N : Normal, A : Abnormal, B : Boundary) | F44: N | G44: N | H44: B | I44: B
B45: Passed/Failed
B46: Executed Date
B47: Defect ID

Sheet Order Service
A2: Function Code | C2: =Functions!E23 -> F-13 | F2: Function Name | L2: =Functions!D23 -> Capture, scope, offline idempotency and order review
A3: Created By | C3: Doan Duc Hai | F3: Executed By
A4: Lines of code | F4: Lack of test cases | L4: =IF(OR(C4="",Functions!E6="N/A"),"N/A",C4*Functions!E6/1000-O7) -> N/A
A5: Test requirement | C5: Accept assisted Sales orders only for active retailers within the Sales assignment, validate quantity steps and store the server-accepted order without immediately selecting stock. Enforce unique request keys, server timestamps and authorized review before the daily cutoff.
A6: Passed | C6: Failed | F6: Untested | L6: N/A/B | O6: Total Test Cases
A7: =COUNTIF(F51:O51,"P") -> 0 | C7: =COUNTIF(F51:O51,"F") -> 0 | F7: =SUM(O7,-A7,-C7) -> 5 | L7: =COUNTIF(F50:O50,"N") -> 2 | M7: =COUNTIF(F50:O50,"A") -> 2 | N7: =COUNTIF(F50:O50,"B") -> 1 | O7: =COUNTA(F9:O9) -> 5
F9: UTCID01 | G9: UTCID02 | H9: UTCID03 | I9: UTCID04 | J9: UTCID05
A10: Condition | B10: Input / scenario
D11: Sales sends assigned-retailer order with valid line, no batch chosen | F11: O
D12: Server receives same request key and unchanged payload twice | G12: O
D14: Sales attempts order for retailer outside current territory | H14: O
D15: Operator reviews order BEFORE 00:00, but server accepted it AFTER cutoff | I15: O
D16: Payload edited after conflict, but same completed idempotency key reused | J16: O
A35: Confirm | B35: Expected result
D36: Create Sales Order PendingReview; not a PO and no inventory reservation | F36: O
D37: One Sales Order and one server timestamp; no duplicated promotion/stock effect | G37: O
D39: Forbidden; no order or accepted timestamp | H39: O
D40: Exclude from current run; next eligible run only | I40: O
D44: Reject key reuse; new intentional submission requires a NEW key | J44: O
A50: Result | B50: Type(N : Normal, A : Abnormal, B : Boundary) | F50: N | G50: N | H50: A | I50: B | J50: A
B51: Passed/Failed
B52: Executed Date
B53: Defect ID

Sheet Promotion Service
A2: Function Code | C2: =Functions!E24 -> F-14 | F2: Function Name | L2: =Functions!D24 -> Campaign, batch discount scope and non-stacking
A3: Created By | C3: Doan Duc Hai | F3: Executed By
A4: Lines of code | F4: Lack of test cases | L4: =IF(OR(C4="",Functions!E6="N/A"),"N/A",C4*Functions!E6/1000-O7) -> N/A
A5: Test requirement | C5: Create scoped promotions, including group SKU threshold measured from the SUM of eligible SKU quantities in the SAME Sales Order (SKU_A 6 + SKU_B 4 meets 10). Apply best ordinary promotion per line with deterministic code tie-break. Shelf-life tiers accept percentages <100% only; fixed discount and zero final price are rejected.
A6: Passed | C6: Failed | F6: Untested | L6: N/A/B | O6: Total Test Cases
A7: =COUNTIF(F38:O38,"P") -> 0 | C7: =COUNTIF(F38:O38,"F") -> 0 | F7: =SUM(O7,-A7,-C7) -> 5 | L7: =COUNTIF(F37:O37,"N") -> 3 | M7: =COUNTIF(F37:O37,"A") -> 1 | N7: =COUNTIF(F37:O37,"B") -> 1 | O7: =COUNTA(F9:O9) -> 5
F9: UTCID01 | G9: UTCID02 | H9: UTCID03 | I9: UTCID04 | J9: UTCID05
A10: Condition | B10: Input / scenario
D11: Admin/Operator creates promotion for group SKU_A+SKU_B requiring 10 cartons across eligible lines of one Sales Order. | F11: O
D12: Campaign dates span UTC/Vietnam-day boundary | G12: O
D14: Admin attempts to configure fixed-amount shelf-life tier; valid 20% tier is also submitted. | H14: O
D15: Discount tier validity overlaps another tier in same scope | I15: O
D16: Group promotion has SKU_A=6 and SKU_B=4 in same order (threshold 10), then 20% eligible shelf-life tier on selected batch. | J16: O
A27: Confirm | B27: Expected result
D28: Valid group threshold: A6+B4 or A10; reject A6+B3 and A6+foreign SKU4; preserve eligible scope and audit. | F28: O
D30: Compare to authoritative business clock without shifting rule unexpectedly | G30: O
D31: Fixed-amount tier rejected; only percentage tiers <100% accepted; 100% or rounded-to-zero final price rejected. | H31: O
D32: Reject conflicting tier versions; no duplicate application | I32: O
D33: Apply 10% group promotion to 6×100,000 + 4×50,000 = 800,000 VND (net 720,000), then independent % shelf-life discount by eligible batch; one ordinary promotion per line. | J33: O
A37: Result | B37: Type(N : Normal, A : Abnormal, B : Boundary) | F37: N | G37: B | H37: N | I37: A | J37: N
B38: Passed/Failed
B39: Executed Date
B40: Defect ID

Sheet Report Service
A2: Function Code | C2: =Functions!E25 -> F-15 | F2: Function Name | L2: =Functions!D25 -> Role-scoped recognized revenue and leaderboard
A3: Created By | C3: Doan Duc Hai | F3: Executed By
A4: Lines of code | F4: Lack of test cases | L4: =IF(OR(C4="",Functions!E6="N/A"),"N/A",C4*Functions!E6/1000-O7) -> N/A
A5: Test requirement | C5: Calculate and display recognized sales revenue, rankings and group performance using approved business amounts and the requesting user’s authorized territory. Administrators may view all groups; Sales Managers and Sales must remain restricted to their permitted scope.
A6: Passed | C6: Failed | F6: Untested | L6: N/A/B | O6: Total Test Cases
A7: =COUNTIF(F47:U47,"P") -> 0 | C7: =COUNTIF(F47:U47,"F") -> 0 | F7: =SUM(O7,-A7,-C7) -> 4 | L7: =COUNTIF(F46:U46,"N") -> 2 | M7: =COUNTIF(F46:U46,"A") -> 2 | N7: =COUNTIF(F46:U46,"B") -> 0 | O7: =COUNTA(F9:U9) -> 4
F9: UTCID01 | G9: UTCID02 | H9: UTCID03 | I9: UTCID04
A10: Condition | B10: Input / scenario
D11: Admin sees all reps ranked by recognized revenue desc | F11: O
D13: Sales manager only sees own group members | G13: O
D14: Sales manager cannot query a group they do not belong to | H14: O
D16: Sales with no active group is forbidden | I16: O
A32: Confirm | B32: Expected result
D33: Admin sees all reps ranked by recognized revenue desc. | F33: O
D34: Sales manager only sees own group members. | G34: O
D35: Sales manager cannot query a group they do not belong to. | H35: O
D36: Sales with no active group is forbidden. | I36: O
A46: Result | B46: Type(N : Normal, A : Abnormal, B : Boundary) | F46: N | G46: N | H46: A | I46: A
B47: Passed/Failed
B48: Executed Date
B49: Defect ID

Sheet Retailer Service
A2: Function Code | C2: =Functions!E26 -> F-16 | F2: Function Name | L2: =Functions!D26 -> Retailer prospect assessment, activation and uniqueness
A3: Created By | C3: Doan Duc Hai | F3: Executed By
A4: Lines of code | F4: Lack of test cases | L4: =IF(OR(C4="",Functions!E6="N/A"),"N/A",C4*Functions!E6/1000-O7) -> N/A
A5: Test requirement | C5: Declare, assess and approve retailer profiles with required information, duplicate checks and documented decisions. On authorized approval, activate the retailer and assign the permanent business code; rejection or incomplete review must preserve the proper state and reason.
A6: Passed | C6: Failed | F6: Untested | L6: N/A/B | O6: Total Test Cases
A7: =COUNTIF(F50:P50,"P") -> 0 | C7: =COUNTIF(F50:P50,"F") -> 0 | F7: =SUM(O7,-A7,-C7) -> 5 | L7: =COUNTIF(F49:P49,"N") -> 3 | M7: =COUNTIF(F49:P49,"A") -> 2 | N7: =COUNTIF(F49:P49,"B") -> 0 | O7: =COUNTA(F9:P9) -> 5
F9: UTCID01 | G9: UTCID02 | H9: UTCID03 | I9: UTCID04 | J9: UTCID05
A10: Condition | B10: Input / scenario
D11: Declaration calculates size and class a and assigns temporary code | F11: O
D13: Approval activates retailer and replaces declaration code | G13: O
D14: Rejection requires reason | H14: O
D16: Approval requires reason | I16: O
D17: Duplicate retailer declaration is rejected | J17: O
A34: Confirm | B34: Expected result
D35: Declaration calculates size and class a and assigns temporary code. | F35: O
D36: Approval activates retailer and replaces declaration code. | G36: O
D39: Rejection requires reason. | H39: O
D40: Approval requires reason. | I40: O
D42: Duplicate retailer declaration is rejected. | J42: O
A49: Result | B49: Type(N : Normal, A : Abnormal, B : Boundary) | F49: N | G49: N | H49: A | I49: N | J49: A
B50: Passed/Failed
B51: Executed Date
B52: Defect ID

Sheet Loyalty & Rewards
A2: Function Code | C2: =Functions!E27 -> F-17 | F2: Function Name | L2: =Functions!D27 -> Loyalty programs and reward eligibility
A3: Created By | C3: Doan Duc Hai | F3: Executed By
A4: Lines of code | F4: Lack of test cases | L4: =IF(OR(C4="",Functions!E6="N/A"),"N/A",C4*Functions!E6/1000-O7) -> N/A
A5: Test requirement | C5: Award points exactly once at floor(eligible settled net VND / 10,000) only after full physical receipt of all shipment quantities, financial settlement and no unresolved complaint. Do not complete a partially received order by adjustment alone. Allow audited correction and negative balances; staff finalize gift fulfillment after documented delivery without mandatory Retailer confirmation.
A6: Passed | C6: Failed | F6: Untested | L6: N/A/B | O6: Total Test Cases
A7: =COUNTIF(F47:N47,"P") -> 0 | C7: =COUNTIF(F47:N47,"F") -> 0 | F7: =SUM(O7,-A7,-C7) -> 5 | L7: =COUNTIF(F46:N46,"N") -> 2 | M7: =COUNTIF(F46:N46,"A") -> 2 | N7: =COUNTIF(F46:N46,"B") -> 1 | O7: =COUNTA(F9:N9) -> 5
F9: UTCID01 | G9: UTCID02 | H9: UTCID03 | I9: UTCID04 | J9: UTCID05
A10: Condition | B10: Input / scenario
D11: All shipped quantities physically received; payment fully settled; no unresolved complaint; eligible amount 612,000 VND. | F11: O
D13: Order has unresolved complaint OR missing units OR outstanding settlement | G13: O
D14: Authorized adjustment posted after Completed exceeds available loyalty points | H14: O
D16: Retailer requests gift with sufficient available points and stock | I16: O
D17: Gift physically delivered with staff delivery evidence; authorized Operator/Admin finalizes fulfillment (Retailer confirmation is not required). | J17: O
A33: Confirm | B33: Expected result
D34: After full physical receipt and payment, award floor(eligible net VND/10,000) points exactly once; e.g., 612,000 VND -> 61 points. | F34: O
D35: No Completed and no points for any missing quantity, even after complaint adjustment or staff settlement. | G35: O
D37: Post linked correction once, allow audited negative balance and prevent duplicate reverse | H37: O
D38: Hold once; on Admin approval consume hold once; reject/cancel releases | I38: O
D40: Authorized Admin/Operator completes after gift delivery evidence; no Retailer confirmation is required; no double point debit. | J40: O
A46: Result | B46: Type(N : Normal, A : Abnormal, B : Boundary) | F46: N | G46: A | H46: B | I46: N | J46: A
B47: Passed/Failed
B48: Executed Date
B49: Defect ID

Sheet Delivery ETA + Maps
A2: Function Code | C2: =Functions!E28 -> F-18 | F2: Function Name | L2: =Functions!D28 -> Receipt ETA and map distance validation
A3: Created By | C3: Doan Duc Hai | F3: Executed By
A4: Lines of code | F4: Lack of test cases | L4: =IF(OR(C4="",Functions!E6="N/A"),"N/A",C4*Functions!E6/1000-O7) -> N/A
A5: Test requirement | C5: Calculate projected delivery and receipt times from approved allocation, warehouse schedules and versioned route/transit data. Respect Vietnam business-date cutoff and changed locations; unavailable or stale routes must not produce an invented zero-distance ETA.
A6: Passed | C6: Failed | F6: Untested | L6: N/A/B | O6: Total Test Cases
A7: =COUNTIF(F46:M46,"P") -> 0 | C7: =COUNTIF(F46:M46,"F") -> 0 | F7: =SUM(O7,-A7,-C7) -> 5 | L7: =COUNTIF(F45:M45,"N") -> 2 | M7: =COUNTIF(F45:M45,"A") -> 1 | N7: =COUNTIF(F45:M45,"B") -> 2 | O7: =COUNTA(F9:M9) -> 5
F9: UTCID01 | G9: UTCID02 | H9: UTCID03 | I9: UTCID04 | J9: UTCID05
A10: Condition | B10: Input / scenario
D11: Run approved and picking pending; dispatch slot not yet available | F11: O
D13: Order accepted at/after 00:00 Vietnam local business-date cutoff | G13: O
D14: Order accepted on 31/12 at 23:59:59 ICT; next is Jan 1 | H14: O
D16: Distance/transit configuration revised after earlier ETA snapshot | I16: O
D17: Map provider is unavailable and no trusted route is cached | J17: O
A33: Confirm | B33: Expected result
D34: ETA includes post-picking slot and transit, not only driving duration | F34: O
D35: ETA uses following eligible run date; never device-local time | G35: O
D37: Business-date conversion retains Asia/Ho_Chi_Minh month/year rollover | H37: O
D38: Use versioned location, distance and transit tables for that snapshot | I38: O
D39: Fail controlled; do not substitute distance=0 or bypass radius | J39: O
A45: Result | B45: Type(N : Normal, A : Abnormal, B : Boundary) | F45: N | G45: B | H45: B | I45: N | J45: A
B46: Passed/Failed
B47: Executed Date
B48: Defect ID

Sheet Delivery Service
A2: Function Code | C2: =Functions!E29 -> F-19 | F2: Function Name | L2: =Functions!D29 -> Dispatch and QR receipt rules across warehouses
A3: Created By | C3: Doan Duc Hai | F3: Executed By
A4: Lines of code | F4: Lack of test cases | L4: =IF(OR(C4="",Functions!E6="N/A"),"N/A",C4*Functions!E6/1000-O7) -> N/A
A5: Test requirement | C5: Permit dispatch only when every warehouse portion is ready, required prepaid funds are verified and no inventory lock or picking exception remains. Validate actual retailer receipt and discrepancy quantities; incomplete receipts must not mark an order Delivered or earn loyalty points.
A6: Passed | C6: Failed | F6: Untested | L6: N/A/B | O6: Total Test Cases
A7: =COUNTIF(F46:M46,"P") -> 0 | C7: =COUNTIF(F46:M46,"F") -> 0 | F7: =SUM(O7,-A7,-C7) -> 5 | L7: =COUNTIF(F45:M45,"N") -> 0 | M7: =COUNTIF(F45:M45,"A") -> 3 | N7: =COUNTIF(F45:M45,"B") -> 2 | O7: =COUNTA(F9:M9) -> 5
F9: UTCID01 | G9: UTCID02 | H9: UTCID03 | I9: UTCID04 | J9: UTCID05
A10: Condition | B10: Input / scenario
D11: All warehouse portions marked Ready but prepaid bank transfer remains unverified | F11: O
D13: All warehouses Ready but a batch is Locked or an unresolved pick exception exists | G13: O
D15: Retailer confirms receipt with received=0 and missing=expected for a shipment | H15: O
D16: Retailer reports received=7 but damaged=8 for expected 10 | I16: O
D18: All shipments have receipt confirmations but total actually received is short | J18: O
A33: Confirm | B33: Expected result
D34: Reject dispatch: prepaid requires fully verified final amount before dispatch | F34: O
D36: Block entire order dispatch until authorized exception decision and stock check | G36: O
D37: Persist discrepancy; no Delivered, no loyalty points and no automatic stock return | H37: O
D39: Reject: 0 ≤ damaged ≤ received; no partially committed receipt | I39: O
D40: Order remains non-Delivered until authorized settlement; no premature points | J40: O
A45: Result | B45: Type(N : Normal, A : Abnormal, B : Boundary) | F45: A | G45: A | H45: B | I45: B | J45: A
B46: Passed/Failed
B47: Executed Date
B48: Defect ID

Sheet Allocation Pricing
A2: Function Code | C2: =Functions!E30 -> F-20 | F2: Function Name | L2: =Functions!D30 -> Batch-specific shelf-life discounts and price snapshots
A3: Created By | C3: Doan Duc Hai | F3: Executed By
A4: Lines of code | F4: Lack of test cases | L4: =IF(OR(C4="",Functions!E6="N/A"),"N/A",C4*Functions!E6/1000-O7) -> N/A
A5: Test requirement | C5: Calculate only percentage-based shelf-life discount on each eligible allocated batch after quantity promotion, never a fixed-amount tier. Reject final net unit prices <=0; preserve batch/warehouse percentage and net-price snapshots for approved quotation, adjustments and refunds.
A6: Passed | C6: Failed | F6: Untested | L6: N/A/B | O6: Total Test Cases
A7: =COUNTIF(F47:J47,"P") -> 0 | C7: =COUNTIF(F47:J47,"F") -> 0 | F7: =SUM(O7,-A7,-C7) -> 5 | L7: =COUNTIF(F46:J46,"N") -> 3 | M7: =COUNTIF(F46:J46,"A") -> 1 | N7: =COUNTIF(F46:J46,"B") -> 1 | O7: =COUNTA(F9:J9) -> 5
F9: UTCID01 | G9: UTCID02 | H9: UTCID03 | I9: UTCID04 | J9: UTCID05
A10: Condition | B10: Input / scenario
D11: Eligible near-expiry allocated batch matches approved percentage shelf-life tier | F11: O
D13: Eligible allocated quantity splits 6 units from warehouse A and 4 from warehouse B | G13: O
D14: Fixed-amount discount submitted (12 VND per unit, 7 units); compare unchanged percentage-only tier and state. | H14: O
D16: Plan contains two batches with distinct final net unit prices and shared SKU | I16: O
D17: One batch fails MLOR or expiry check even though discount would be large | J17: O
A34: Confirm | B34: Expected result
D35: Compute per-batch percent discount after eligibility, preserve effective tier/version | F35: O
D36: Percentage-only discount snapshots independently preserved across split warehouse/batch lines. | G36: O
D37: Deduct 84 total on correct net basis; no stacking, round as approved | H37: O
D38: Do not average batch prices; refund uses exact affected batch net unit price | I38: O
D40: Reject batch before pricing; discount does not change hard eligibility | J40: O
A46: Result | B46: Type(N : Normal, A : Abnormal, B : Boundary) | F46: N | G46: N | H46: B | I46: N | J46: A
B47: Passed/Failed
B48: Executed Date
B49: Defect ID

Sheet Picking Service
A2: Function Code | C2: =Functions!E31 -> F-21 | F2: Function Name | L2: =Functions!D31 -> QR-based batch picking and readiness
A3: Created By | C3: Doan Duc Hai | F3: Executed By
A4: Lines of code | F4: Lack of test cases | L4: =IF(OR(C4="",Functions!E6="N/A"),"N/A",C4*Functions!E6/1000-O7) -> N/A
A5: Test requirement | C5: Allow assigned warehouse staff to scan and complete the correct batch and QR picking quantities while preserving allocation-price links. Reject wrong, duplicated or locked scans, and block readiness or dispatch until authorized picking exceptions are resolved.
A6: Passed | C6: Failed | F6: Untested | L6: N/A/B | O6: Total Test Cases
A7: =COUNTIF(F50:O50,"P") -> 0 | C7: =COUNTIF(F50:O50,"F") -> 0 | F7: =SUM(O7,-A7,-C7) -> 5 | L7: =COUNTIF(F49:O49,"N") -> 2 | M7: =COUNTIF(F49:O49,"A") -> 3 | N7: =COUNTIF(F49:O49,"B") -> 0 | O7: =COUNTA(F9:O9) -> 5
F9: UTCID01 | G9: UTCID02 | H9: UTCID03 | I9: UTCID04 | J9: UTCID05
A10: Condition | B10: Input / scenario
D11: Keeper scans correct batch QR against assigned warehouse picking gather | F11: O
D13: Keeper scans duplicate or wrong-warehouse/locked QR label | G13: O
D14: Keeper raises shortage/pick exception before line completion | H14: O
D16: Admin resolves picking exception and permits documented recovery | I16: O
D17: All picking quantities complete but separate lock/exception still open | J17: O
A34: Confirm | B34: Expected result
D35: Record picked quantity and split mapping without issuing physical stock | F35: O
D36: Reject scan atomically; preserve gather, reservation and price mapping | G36: O
D38: Block readiness until authorized resolution; preserve audit/evidence | H38: O
D39: Resume/rework only authorized lines; do not silently substitute batch | I39: O
D41: Do not permit dispatch solely from Ready flags | J41: O
A49: Result | B49: Type(N : Normal, A : Abnormal, B : Boundary) | F49: N | G49: A | H49: A | I49: N | J49: A
B50: Passed/Failed
B51: Executed Date
B52: Defect ID

Sheet Shipment Service
A2: Function Code | C2: =Functions!E32 -> F-22 | F2: Function Name | L2: =Functions!D32 -> Shipment progression, reconciliation and exceptions
A3: Created By | C3: Doan Duc Hai | F3: Executed By
A4: Lines of code | F4: Lack of test cases | L4: =IF(OR(C4="",Functions!E6="N/A"),"N/A",C4*Functions!E6/1000-O7) -> N/A
A5: Test requirement | C5: Create and reconcile one shipment per valid warehouse portion without duplicate effects. Track authorized delivery attempts, retries, failed-delivery resolution and actual receipt totals; never automatically restore issued stock or settle exceptions without an authorized decision.
A6: Passed | C6: Failed | F6: Untested | L6: N/A/B | O6: Total Test Cases
A7: =COUNTIF(F50:P50,"P") -> 0 | C7: =COUNTIF(F50:P50,"F") -> 0 | F7: =SUM(O7,-A7,-C7) -> 5 | L7: =COUNTIF(F49:P49,"N") -> 2 | M7: =COUNTIF(F49:P49,"A") -> 3 | N7: =COUNTIF(F49:P49,"B") -> 0 | O7: =COUNTA(F9:P9) -> 5
F9: UTCID01 | G9: UTCID02 | H9: UTCID03 | I9: UTCID04 | J9: UTCID05
A10: Condition | B10: Input / scenario
D11: Shipment records are queried repeatedly after each warehouse has completed its picking | F11: O
D13: Operator retries delivery or reconciliation after a failed attempt | G13: O
D14: One shipment fails and no signed return or stock resolution exists | H14: O
D16: All shipment receipts confirmed yet one portion is missing units | I16: O
D17: Unauthorised user attempts to settle/close disputed shipment | J17: O
A34: Confirm | B34: Expected result
D35: Create/reconcile one shipment per valid warehouse portion with stable IDs | F35: O
D36: No duplicate shipment/attempt; authorized state decision, audit, and idempotency | G36: O
D37: No automatic stock credit; retain issued stock and exception for Admin decision | H37: O
D39: Do not mark order Delivered on confirmation count alone; reconcile actual quantities | I39: O
D41: Reject unauthorized action; preserve disputed balance and evidence | J41: O
A49: Result | B49: Type(N : Normal, A : Abnormal, B : Boundary) | F49: N | G49: N | H49: A | I49: A | J49: A
B50: Passed/Failed
B51: Executed Date
B52: Defect ID

Sheet Allocation Reservation
A2: Function Code | C2: =Functions!E33 -> F-23 | F2: Function Name | L2: =Functions!D33 -> Post-approval reservation and concurrency consistency
A3: Created By | C3: Doan Duc Hai | F3: Executed By
A4: Lines of code | F4: Lack of test cases | L4: =IF(OR(C4="",Functions!E6="N/A"),"N/A",C4*Functions!E6/1000-O7) -> N/A
A5: Test requirement | C5: Reserve a batch quantity only when the Administrator approves a current allocation and final-price version. Recheck stock, locks, expiry and optimistic versions atomically; record the reservation once and reject conflicts without partial stock changes.
A6: Passed | C6: Failed | F6: Untested | L6: N/A/B | O6: Total Test Cases
A7: =COUNTIF(F47:K47,"P") -> 0 | C7: =COUNTIF(F47:K47,"F") -> 0 | F7: =SUM(O7,-A7,-C7) -> 5 | L7: =COUNTIF(F46:K46,"N") -> 3 | M7: =COUNTIF(F46:K46,"A") -> 2 | N7: =COUNTIF(F46:K46,"B") -> 0 | O7: =COUNTA(F9:K9) -> 5
F9: UTCID01 | G9: UTCID02 | H9: UTCID03 | I9: UTCID04 | J9: UTCID05
A10: Condition | B10: Input / scenario
D11: Administrator approves valid price version and stock remains eligible | F11: O
D13: Successful reservation writes batch and ledger links | G13: O
D14: Approval/reservation call retries same plan version | H14: O
D16: Another transaction consumes stock between planning and approval | I16: O
D17: Batch expires/is locked between planning and reservation | J17: O
A34: Confirm | B34: Expected result
D35: Reserve once after approval; physical on-hand unchanged | F35: O
D36: Each reserved fragment points to approved allocation price snapshot | G36: O
D38: No duplicate reservation or outbox side effect | H38: O
D39: All-or-nothing conflict; no partial reservation or picking release | I39: O
D41: Reject hold and require authorized recalculation; no stock overdraft | J41: O
A46: Result | B46: Type(N : Normal, A : Abnormal, B : Boundary) | F46: N | G46: N | H46: N | I46: A | J46: A
B47: Passed/Failed
B48: Executed Date
B49: Defect ID

Sheet Allocation Run Service
A2: Function Code | C2: =Functions!E34 -> F-24 | F2: Function Name | L2: =Functions!D34 -> Cutoff, daily run uniqueness and immutable snapshots
A3: Created By | C3: Doan Duc Hai | F3: Executed By
A4: Lines of code | F4: Lack of test cases | L4: =IF(OR(C4="",Functions!E6="N/A"),"N/A",C4*Functions!E6/1000-O7) -> N/A
A5: Test requirement | C5: Build one daily allocation run at the 00:00 Asia/Ho_Chi_Minh cutoff from orders both accepted and approved strictly before midnight. Use server acceptance time then order code for priority, handle exact-boundary and year-change cases, and ignore the mobile device clock.
A6: Passed | C6: Failed | F6: Untested | L6: N/A/B | O6: Total Test Cases
A7: =COUNTIF(F48:K48,"P") -> 0 | C7: =COUNTIF(F48:K48,"F") -> 0 | F7: =SUM(O7,-A7,-C7) -> 5 | L7: =COUNTIF(F47:K47,"N") -> 0 | M7: =COUNTIF(F47:K47,"A") -> 2 | N7: =COUNTIF(F47:K47,"B") -> 3 | O7: =COUNTA(F9:K9) -> 5
F9: UTCID01 | G9: UTCID02 | H9: UTCID03 | I9: UTCID04 | J9: UTCID05
A10: Condition | B10: Input / scenario
D11: Server accepted 23:59:59 and Operator approved 23:59:59 Asia/Ho_Chi_Minh | F11: O
D13: Either acceptance or approval is exactly 00:00 Vietnam local time | G13: O
D14: Either server acceptance or Operator approval falls after 00:00 cutoff | H14: O
D16: 31 December 23:59:59 transitions to 1 January 00:00 Vietnam local time | I16: O
D17: Mobile device clock is manipulated before Sales manually sends a draft | J17: O
A34: Confirm | B34: Expected result
D35: Include in cutoff snapshot; sort by server acceptance time then order code | F35: O
D36: Exclude from prior-day cutoff; include in next eligible run, never keep prior priority | G36: O
D38: Not eligible for the closed run; device time does not override server timestamps | H38: O
D39: Correct date/year split; unique daily run keyed by Vietnam business date | I39: O
D40: Server records real acceptance timestamp; no priority from local device time | J40: O
A47: Result | B47: Type(N : Normal, A : Abnormal, B : Boundary) | F47: B | G47: B | H47: A | I47: B | J47: A
B48: Passed/Failed
B49: Executed Date
B50: Defect ID

Sheet Expiry Sweep & Outbox
A2: Function Code | C2: =Functions!E35 -> F-25 | F2: Function Name | L2: =Functions!D35 -> Expiry sweep and notification outbox
A3: Created By | C3: Doan Duc Hai | F3: Executed By
A4: Lines of code | F4: Lack of test cases | L4: =IF(OR(C4="",Functions!E6="N/A"),"N/A",C4*Functions!E6/1000-O7) -> N/A
A5: Test requirement | C5: Detect near-expiry and expired batches through a repeatable scheduled sweep, locking unusable quantities while preserving reserved-stock resolution requirements. Publish expiry events and notifications through an idempotent outbox without duplicate business effects.
A6: Passed | C6: Failed | F6: Untested | L6: N/A/B | O6: Total Test Cases
A7: =COUNTIF(F46:M46,"P") -> 0 | C7: =COUNTIF(F46:M46,"F") -> 0 | F7: =SUM(O7,-A7,-C7) -> 7 | L7: =COUNTIF(F45:M45,"N") -> 3 | M7: =COUNTIF(F45:M45,"A") -> 3 | N7: =COUNTIF(F45:M45,"B") -> 1 | O7: =COUNTA(F9:M9) -> 7
F9: UTCID01 | G9: UTCID02 | H9: UTCID03 | I9: UTCID04 | J9: UTCID05 | K9: UTCID06 | L9: UTCID07
A10: Condition | B10: Input / scenario
D11: Daily sweep visits batch after real expiry timestamp | F11: O
D13: Expired batch unreserved/available | G13: O
D14: Expired batch overlaps live reservation | H14: O
D16: Near-expiry but still valid batch | I16: O
D17: Outbox delivers same business event twice | J17: O
D19: Notification send fails transiently | K19: O
D20: Retry limit exceeded by permanent payload error | L20: O
A33: Confirm | B33: Expected result
D34: Mark expired once, persist outbox and track business date | F34: O
D35: Lock unusable quantity without changing physical balance | G35: O
D37: Flag for authorized resolution; never silently release order stock | H37: O
D39: Only mark near expiry; no false expired lock or sale bypass | I39: O
D40: Consumer deduplicates by event and recipient; no repeated loyalty effect | J40: O
D41: Retry as documented; transaction and business state remain committed | K41: O
D42: Persist Failed, evidence and alert; no duplicate business writes | L42: O
A45: Result | B45: Type(N : Normal, A : Abnormal, B : Boundary) | F45: N | G45: N | H45: A | I45: B | J45: N | K45: A | L45: A
B46: Passed/Failed
B47: Executed Date
B48: Defect ID
G53: 46103

Sheet Allocation Price Lookup
A2: Function Code | C2: =Functions!E36 -> F-26 | F2: Function Name | L2: =Functions!D36 -> Read model for approved allocated line prices
A3: Created By | C3: Doan Duc Hai | F3: Executed By
A4: Lines of code | F4: Lack of test cases | L4: =IF(OR(C4="",Functions!E6="N/A"),"N/A",C4*Functions!E6/1000-O7) -> N/A
A5: Test requirement | C5: Return a version-consistent approved price breakdown for every order line and allocated batch, including discounts, quantities, warehouse portions and rounded totals. Do not treat unapproved versions as final; use the exact affected batch net price for any refund calculation.
A6: Passed | C6: Failed | F6: Untested | L6: N/A/B | O6: Total Test Cases
A7: =COUNTIF(F47:I47,"P") -> 0 | C7: =COUNTIF(F47:I47,"F") -> 0 | F7: =SUM(O7,-A7,-C7) -> 4 | L7: =COUNTIF(F46:I46,"N") -> 2 | M7: =COUNTIF(F46:I46,"A") -> 1 | N7: =COUNTIF(F46:I46,"B") -> 1 | O7: =COUNTA(F9:I9) -> 4
F9: UTCID01 | G9: UTCID02 | H9: UTCID03 | I9: UTCID04
A10: Condition | B10: Input / scenario
D11: Order line split into batches X and Y with distinct net prices | F11: O
D13: Approved order has two lines with independently rounded split totals | G13: O
D14: Refund request identifies damaged qty from batch Y | H14: O
D15: Plan version awaits Administrator price approval | I15: O
A34: Confirm | B34: Expected result
D35: Read model returns independent quantity/price snapshot for each batch | F35: O
D37: Order total equals sum of approved net split amounts, no re-price | G37: O
D38: Refund cap uses Y allocated net price only, not average/list price | H38: O
D39: Do not expose pending version as final or refundable price | I39: O
A46: Result | B46: Type(N : Normal, A : Abnormal, B : Boundary) | F46: N | G46: N | H46: B | I46: A
B47: Passed/Failed
B48: Executed Date
B49: Defect ID

Sheet MB Money and Limits
A2: Function Code | C2: =Functions!E37 -> F-27 | F2: Function Name | L2: =Functions!D37 -> Flutter VND formatting and quantity step/buffer
A3: Created By | C3: Doan Duc Hai | F3: Executed By
A4: Lines of code | F4: Lack of test cases | L4: =IF(OR(C4="",Functions!E6="N/A"),"N/A",C4*Functions!E6/1000-O7) -> N/A
A5: Test requirement | C5: Format Vietnamese currency amounts and discounts correctly, parse entered money values safely, and calculate the maximum order quantity as available stock minus buffer rounded down to the configured carton step without becoming negative.
A6: Passed | C6: Failed | F6: Untested | L6: N/A/B | O6: Total Test Cases
A7: =COUNTIF(F49:L49,"P") -> 0 | C7: =COUNTIF(F49:L49,"F") -> 0 | F7: =SUM(O7,-A7,-C7) -> 7 | L7: =COUNTIF(F48:L48,"N") -> 4 | M7: =COUNTIF(F48:L48,"A") -> 1 | N7: =COUNTIF(F48:L48,"B") -> 2 | O7: =COUNTA(F9:L9) -> 7
F9: UTCID01 | G9: UTCID02 | H9: UTCID03 | I9: UTCID04 | J9: UTCID05 | K9: UTCID06 | L9: UTCID07
A10: Condition | B10: Input / scenario
D11: uses dots as thousands separators and the đ suffix | F11: O
D13: negative amounts and rounding | G13: O
D14: minus shows discounts, zero stays plain | H14: O
D16: millions and billions use a decimal comma | I16: O
D17: ignores separators and symbols | J17: O
D18: available minus buffer, rounded down to a multiple of 10 | K18: O
D20: never negative | L20: O
A34: Confirm | B34: Expected result
D35: uses dots as thousands separators and the đ suffix. | F35: O
D36: negative amounts and rounding. | G36: O
D38: minus shows discounts, zero stays plain. | H38: O
D39: millions and billions use a decimal comma. | I39: O
D40: ignores separators and symbols. | J40: O
D41: available minus buffer, rounded down to a multiple of 10. | K41: O
D43: never negative. | L43: O
A48: Result | B48: Type(N : Normal, A : Abnormal, B : Boundary) | F48: N | G48: B | H48: B | I48: N | J48: N | K48: N | L48: A
B49: Passed/Failed
B50: Executed Date
B51: Defect ID

Sheet Allocation Scenarios
A2: Function Code | C2: =Functions!E38 -> F-28 | F2: Function Name | L2: =Functions!D38 -> FEFO/MLOR scenarios, equality, deadline and priority
A3: Created By | C3: Doan Duc Hai | F3: Executed By
A4: Lines of code | F4: Lack of test cases | L4: =IF(OR(C4="",Functions!E6="N/A"),"N/A",C4*Functions!E6/1000-O7) -> N/A
A5: Test requirement | C5: Validate end-to-end daily allocation business rules for the 00:00 Vietnam cutoff, immutable server priority, all-or-nothing fulfillment and no batch swapping. New orders created after a shortage receive new priority; discounted batches must still meet the original effective MLOR.
A6: Passed | C6: Failed | F6: Untested | L6: N/A/B | O6: Total Test Cases
A7: =COUNTIF(F47:K47,"P") -> 0 | C7: =COUNTIF(F47:K47,"F") -> 0 | F7: =SUM(O7,-A7,-C7) -> 5 | L7: =COUNTIF(F46:K46,"N") -> 0 | M7: =COUNTIF(F46:K46,"A") -> 3 | N7: =COUNTIF(F46:K46,"B") -> 2 | O7: =COUNTA(F9:K9) -> 5
F9: UTCID01 | G9: UTCID02 | H9: UTCID03 | I9: UTCID04 | J9: UTCID05
A10: Condition | B10: Input / scenario
D11: Both acceptance and approval timestamps are strictly before 00:00 | F11: O
D13: Approval before cutoff but acceptance at 00:00; reverse case too | G13: O
D14: Later order would be complete only by swapping earlier batch | H14: O
D15: Short order resubmitted as new order after run closes | I15: O
D16: Discount offered on otherwise ineligible MLOR batch | J16: O
A33: Confirm | B33: Expected result
D34: Order enters current eligible run in server acceptance priority | F34: O
D35: Either late timestamp defers entire order to next run | G35: O
D37: No swapping; earlier order keeps batch, later order is short | H37: O
D38: New key/timestamp; no retained priority or automatic requeue | I38: O
D39: Reject batch in hard filters; no near-expiry MLOR override | J39: O
A46: Result | B46: Type(N : Normal, A : Abnormal, B : Boundary) | F46: B | G46: B | H46: A | I46: A | J46: A
B47: Passed/Failed
B48: Executed Date
B49: Defect ID

Sheet Transit Table
A2: Function Code | C2: =Functions!E39 -> F-29 | F2: Function Name | L2: =Functions!D39 -> Distance-band intervals and versioned transit rules
A3: Created By | C3: Doan Duc Hai | F3: Executed By
A4: Lines of code | F4: Lack of test cases | L4: =IF(OR(C4="",Functions!E6="N/A"),"N/A",C4*Functions!E6/1000-O7) -> N/A
A5: Test requirement | C5: Publish versioned warehouse transit-distance rules with valid non-overlapping bands, costs and effective periods. Resolve the correct historical version and handle exact upper bounds and routes beyond the supported distance consistently.
A6: Passed | C6: Failed | F6: Untested | L6: N/A/B | O6: Total Test Cases
A7: =COUNTIF(F56:O56,"P") -> 0 | C7: =COUNTIF(F56:O56,"F") -> 0 | F7: =SUM(O7,-A7,-C7) -> 4 | L7: =COUNTIF(F55:O55,"N") -> 2 | M7: =COUNTIF(F55:O55,"A") -> 0 | N7: =COUNTIF(F55:O55,"B") -> 2 | O7: =COUNTA(F9:O9) -> 4
F9: UTCID01 | G9: UTCID02 | H9: UTCID03 | I9: UTCID04
A10: Condition | B10: Input / scenario
D11: Publish stores bands cost and first version | F11: O
D12: Publish closes the previous version instead of overwriting it | G12: O
D14: Lookup at a past moment returns the version that was in force | H14: O
D15: Lookup treats the band upper bound as exclusive | I15: O
A38: Confirm | B38: Expected result
D39: Publish stores bands cost and first version. | F39: O
D40: Publish closes the previous version instead of overwriting it. | G40: O
D41: Lookup at a past moment returns the version that was in force. | H41: O
D42: Lookup treats the band upper bound as exclusive. | I42: O
A55: Result | B55: Type(N : Normal, A : Abnormal, B : Boundary) | F55: B | G55: N | H55: N | I55: B | Q55: N | R55: N | S55: N
B56: Passed/Failed
B57: Executed Date
B58: Defect ID

Sheet MB Business IDs
A2: Function Code | C2: =Functions!E40 -> F-30 | F2: Function Name | L2: =Functions!D40 -> Flutter business code formatting and validation
A3: Created By | C3: Doan Duc Hai | F3: Executed By
A4: Lines of code | F4: Lack of test cases | L4: =IF(OR(C4="",Functions!E6="N/A"),"N/A",C4*Functions!E6/1000-O7) -> N/A
A5: Test requirement | C5: Generate and validate stable FSCM business identifiers for orders, batches, picking documents, offline drafts and QR payloads. Enforce document prefixes, zero padding, field-length constraints, device-code association and invalid-code rejection.
A6: Passed | C6: Failed | F6: Untested | L6: N/A/B | O6: Total Test Cases
A7: =COUNTIF(F38:O38,"P") -> 0 | C7: =COUNTIF(F38:O38,"F") -> 0 | F7: =SUM(O7,-A7,-C7) -> 9 | L7: =COUNTIF(F37:O37,"N") -> 6 | M7: =COUNTIF(F37:O37,"A") -> 2 | N7: =COUNTIF(F37:O37,"B") -> 1 | O7: =COUNTA(F9:O9) -> 9
F9: UTCID01 | G9: UTCID02 | H9: UTCID03 | I9: UTCID04 | J9: UTCID05 | K9: UTCID06 | L9: UTCID07 | M9: UTCID08 | N9: UTCID09
A10: Condition | B10: Input / scenario
D11: zero-padded business ids | F11: O
D12: batch, picking list and documents | G12: O
D14: offline order code is paired with the device code | H14: O
D15: rejects values wider than the field | I15: O
D16: accepts well-formed codes | J16: O
D17: rejects malformed codes | K17: O
D19: batchExpiry reads the date out of the batch code | L19: O
D20: orderOfPickingList strips the warehouse letter | M20: O
D21: recognises what a QR can carry | N21: O
A22: Confirm | B22: Expected result
D23: zero-padded business ids. | F23: O
D24: batch, picking list and documents. | G24: O
D26: offline order code is paired with the device code. | H26: O
D27: rejects values wider than the field. | I27: O
D29: accepts well-formed codes. | J29: O
D30: rejects malformed codes. | K30: O
D31: batchExpiry reads the date out of the batch code. | L31: O
D33: orderOfPickingList strips the warehouse letter. | M33: O
D34: recognises what a QR can carry. | N34: O
A37: Result | B37: Type(N : Normal, A : Abnormal, B : Boundary) | F37: B | G37: N | H37: N | I37: A | J37: N | K37: A | L37: N | M37: N | N37: N
B38: Passed/Failed
B39: Executed Date
B40: Defect ID

Sheet Payment Service
A2: Function Code | C2: =Functions!E41 -> F-31 | F2: Function Name | L2: =Functions!D41 -> Final price, prepaid/deferred payment and receivable terms; reject COD
A3: Created By | C3: Doan Duc Hai | F3: Executed By
A4: Lines of code | F4: Lack of test cases | L4: =IF(OR(C4="",Functions!E6="N/A"),"N/A",C4*Functions!E6/1000-O7) -> N/A
A5: Test requirement | C5: Allow a Retailer to select prepaid bank transfer after the approved quotation or deferred payment only with an active approved retailer credit term. Reject COD, verify full prepaid payment before dispatch, start deferred due dates from full receipt and enforce cash/transfer actor permissions.
A6: Passed | C6: Failed | F6: Untested | L6: N/A/B | O6: Total Test Cases
A7: =COUNTIF(F46:O46,"P") -> 0 | C7: =COUNTIF(F46:O46,"F") -> 0 | F7: =SUM(O7,-A7,-C7) -> 5 | L7: =COUNTIF(F45:O45,"N") -> 2 | M7: =COUNTIF(F45:O45,"A") -> 2 | N7: =COUNTIF(F45:O45,"B") -> 1 | O7: =COUNTA(F9:O9) -> 5
F9: UTCID01 | G9: UTCID02 | H9: UTCID03 | I9: UTCID04 | J9: UTCID05
A10: Condition | B10: Input / scenario
D11: Retailer accepts final-price quotation and chooses prepaid bank transfer | F11: O
D12: Retailer without active approved payment term selects deferred payment | G12: O
D14: Deferred order is actually fully received on date D with approved term 15 days | H14: O
D15: Assigned Sales collects full outstanding CASH on delivered deferred receivable | I15: O
D16: Wrong role attempts transfer verification or COD request is submitted | J16: O
A26: Confirm | B26: Expected result
D27: Verify full transfer by prepaid deadline, after approved quote and before dispatch | F27: O
D28: Reject deferred, no PO or due-date creation; COD never offered | G28: O
D30: Deferred due = D + 15 calendar days, based on full receipt, not quote/prepaid deadline | H30: O
D31: Allow once, audit receipt; Sales cannot verify transfer or choose COD | I31: O
D33: Reject forbidden actor/method, no payment side effects | J33: O
A45: Result | B45: Type(N : Normal, A : Abnormal, B : Boundary) | F45: N | G45: A | H45: B | I45: N | J45: A
B46: Passed/Failed
B47: Executed Date
B48: Defect ID

Sheet Run Picking Issue
A2: Function Code | C2: =Functions!E42 -> F-32 | E2: Function Name | K2: =Functions!D42 -> Create grouped warehouse picking documents after approval
A3: Created By | C3: Doan Duc Hai | E3: Executed By
A4: Lines of code | E4: Lack of test cases | K4: =IF(OR(C4="",Functions!E6="N/A"),"N/A",C4*Functions!E6/1000-N7) -> N/A
A5: Test requirement | C5: Issue warehouse picking lists only after a valid approved quotation becomes a Purchase Order through eligible deferred acceptance or fully verified prepaid transfer. Generate one idempotent list per warehouse, preserve allocation prices and do not move stock merely by issuing a list.
A6: Passed | C6: Failed | E6: Untested | K6: N/A/B | N6: Total Test Cases
A7: =COUNTIF(E40:N40,"P") -> 0 | C7: =COUNTIF(E40:N40,"F") -> 0 | E7: =SUM(N7,-A7,-C7) -> 5 | K7: =COUNTIF(E39:N39,"N") -> 3 | L7: =COUNTIF(E39:N39,"A") -> 2 | M7: =COUNTIF(E39:N39,"B") -> 0 | N7: =COUNTA(E9:N9) -> 5
E9: UTCID01 | F9: UTCID02 | G9: UTCID03 | H9: UTCID04 | I9: UTCID05
A10: Condition | B10: Input / scenario
D11: Quote approved but Retailer has NOT accepted / chosen payment | E11: O
D12: Retailer accepts approved quote and authorized credit term is active | F12: O
D13: Prepaid Retailer accepted but transfer not fully verified | G13: O
D14: Same approved PO picking issue request is retried | H14: O
D16: Two warehouses split same product with approved price references | I16: O
A31: Confirm | B31: Expected result
D32: No PO yet; no picking lists released | E32: O
D33: Issue PO and one picking document per warehouse | F33: O
D34: Do not create/issue picking lists until authorized verification | G34: O
D35: Return same picking documents; never duplicate issues | H35: O
D37: Every split references immutable per-batch approved net pricing | I37: O
A39: Result | B39: Type(N : Normal, A : Abnormal, B : Boundary) | E39: A | F39: N | G39: A | H39: N | I39: N
B40: Passed/Failed
B41: Executed Date
B42: Defect ID

Sheet Identity Service
A2: Function Code | C2: =Functions!E43 -> F-33 | E2: Function Name | K2: =Functions!D43 -> JWT sign-in, scoped access, lockout and token rotation
A3: Created By | C3: Doan Duc Hai | E3: Executed By
A4: Lines of code | E4: Lack of test cases | K4: =IF(OR(C4="",Functions!E6="N/A"),"N/A",C4*Functions!E6/1000-N7) -> N/A
A5: Test requirement | C5: Authenticate active FSCM accounts, issue scoped access and refresh tokens, enforce failed-login lockout and safe token rotation, and allow Microsoft Entra exchange only for preprovisioned authorized users. Prevent unauthorized Administrator creation or role promotion.
A6: Passed | C6: Failed | E6: Untested | K6: N/A/B | N6: Total Test Cases
A7: =COUNTIF(E52:L52,"P") -> 0 | C7: =COUNTIF(E52:L52,"F") -> 0 | E7: =SUM(N7,-A7,-C7) -> 5 | K7: =COUNTIF(E51:L51,"N") -> 4 | L7: =COUNTIF(E51:L51,"A") -> 1 | M7: =COUNTIF(E51:L51,"B") -> 0 | N7: =COUNTA(E9:L9) -> 5
E9: UTCID01 | F9: UTCID02 | G9: UTCID03 | H9: UTCID04 | I9: UTCID05
A10: Condition | B10: Input / scenario
D11: Login issues tokens and includes current scope | E11: O
D12: Login locks account after five failed attempts | F12: O
D14: Refresh rotates the refresh token | G14: O
D15: User management never creates or promotes admin | H15: O
D16: Entra exchange links only preprovisioned entra account and issues… | I16: O
A31: Confirm | B31: Expected result
D32: Login issues tokens and includes current scope. | E32: O
D33: Login locks account after five failed attempts. | F33: O
D34: Refresh rotates the refresh token. | G34: O
D35: User management never creates or promotes admin. | H35: O
D36: Entra exchange links only preprovisioned entra account and issues int… | I36: O
A51: Result | B51: Type (N/B/A) | E51: N | F51: A | G51: N | H51: N | I51: N
B52: Pass/Fail (P/F)
B53: Executed Date
B54: Defect ID

Sheet Offline Snapshot & Queue
A2: Function Code | C2: =Functions!E44 -> F-34 | E2: Function Name | K2: =Functions!D44 -> Manual offline Send, server revalidation, idempotency and technical retry
A3: Created By | C3: Doan Duc Hai | E3: Executed By
A4: Lines of code | E4: Lack of test cases | K4: =IF(OR(C4="",Functions!E6="N/A"),"N/A",C4*Functions!E6/1000-N7) -> N/A
A5: Test requirement | C5: Keep cached offline orders as local drafts until Sales explicitly selects Send; reconnection alone must not submit them. Revalidate current price, MLOR and retailer assignment; require confirmation of changes and use immutable idempotency keys for safe technical retries.
A6: Passed | C6: Failed | E6: Untested | K6: N/A/B | N6: Total Test Cases
A7: =COUNTIF(E57:N57,"P") -> 0 | C7: =COUNTIF(E57:N57,"F") -> 0 | E7: =SUM(N7,-A7,-C7) -> 10 | K7: =COUNTIF(E56:N56,"N") -> 3 | L7: =COUNTIF(E56:N56,"A") -> 6 | M7: =COUNTIF(E56:N56,"B") -> 1 | N7: =COUNTA(E9:N9) -> 10
E9: UTCID01 | F9: UTCID02 | G9: UTCID03 | H9: UTCID04 | I9: UTCID05 | J9: UTCID06 | K9: UTCID07 | L9: UTCID08 | M9: UTCID09 | N9: UTCID10
A10: Condition | B10: Input / scenario
D11: Phone reconnects while Sales has one unsent offline draft | E11: O
D12: Sales taps Send with current retailer assignment and unchanged price/MLOR snapshot | F12: O
D13: Base price changes while offline draft is stored | G13: O
D14: Retailer SKU/category MLOR changes while draft is stored | H14: O
D15: Retailer is removed from Sales territory while draft is offline | I15: O
D17: Sales changes a draft payload after a completed submission/rejection | J17: O
D18: Transport times out after manual Send but server has accepted exact payload | K18: O
D20: Two technical retries follow manual Send: attempts 1 and 2 | L20: O
D21: Reconnect happens while an unsent draft is pending | M21: O
D22: Server accepted order but response was lost; Sales retries | N22: O
A40: Confirm | B40: Expected result
D41: Draft stays queued; no automatic POST until Sales explicitly taps Send | E41: O
D42: Submit one request; server validates before recording acceptance time | F42: O
D44: Prompt Sales to confirm new authoritative price before sending a new submission | G44: O
D45: Require explicit acceptance of changed terms; do not silently reuse cached condition | H45: O
D47: Reject out-of-scope order; no new server order; draft remains visible | I47: O
D48: Use a NEW idempotency key on intentional payload edit; old key replay never changes content | J48: O
D50: Retry same immutable payload with SAME key; exactly one server order | K50: O
D52: Backoff 20 s then 40 s; bounded; never bypass new-condition confirmation | L52: O
D53: Automatic retry cannot bypass explicit Sales Send/confirm | M53: O
D55: Exactly one server order/code; local queue becomes Synced on reconciliation | N55: O
A56: Result | B56: Type (N/B/A) | E56: A | F56: N | G56: A | H56: A | I56: A | J56: A | K56: N | L56: B | M56: A | N56: N
B57: Pass/Fail (P/F)
B58: Executed Date
B59: Defect ID

Sheet Territory Service
A2: Function Code | C2: =Functions!E45 -> F-35 | E2: Function Name | K2: =Functions!D45 -> Sales-group assignment and data-scope authorization
A3: Created By | C3: Doan Duc Hai | E3: Executed By
A4: Lines of code | E4: Lack of test cases | K4: =IF(OR(C4="",Functions!E6="N/A"),"N/A",C4*Functions!E6/1000-N7) -> N/A
A5: Test requirement | C5: Maintain regions, Sales groups, member history and retailer coverage with correct active assignments. Restrict orders and queries to the actor’s current territory, including server revalidation when an offline draft is submitted after an assignment change.
A6: Passed | C6: Failed | E6: Untested | K6: N/A/B | N6: Total Test Cases
A7: =COUNTIF(E57:N57,"P") -> 0 | C7: =COUNTIF(E57:N57,"F") -> 0 | E7: =SUM(N7,-A7,-C7) -> 4 | K7: =COUNTIF(E56:N56,"N") -> 1 | L7: =COUNTIF(E56:N56,"A") -> 2 | M7: =COUNTIF(E56:N56,"B") -> 1 | N7: =COUNTA(E9:N9) -> 4
E9: UTCID01 | F9: UTCID02 | G9: UTCID03 | H9: UTCID04
A10: Condition | B10: Input / scenario
D11: Create region code and attach Sales group | E11: O
D12: Sales was transferred to a different region after draft saved | F12: O
D14: Sales Manager requests group or retailer from other region | G14: O
D15: Retailer assignment changes while offline order waits | H15: O
A38: Confirm | B38: Expected result
D39: Normalize code and restrict conflicting active assignments | E39: O
D40: Historical membership retained; current scope used at manual submission | F40: O
D42: Forbidden; no unrelated order/ledger data returned | G42: O
D44: Reject stale scoped order; require refreshed server authorization | H44: O
A56: Result | B56: Type (N/B/A) | E56: N | F56: B | G56: A | H56: A
B57: Pass/Fail (P/F)
B58: Executed Date
B59: Defect ID

Sheet Inventory Lifecycle
A2: Function Code | C2: =Functions!E46 -> F-36 | E2: Function Name | K2: =Functions!D46 -> Reservation, dispatch issue and release ledger
A3: Created By | C3: Doan Duc Hai | E3: Executed By
A4: Lines of code | E4: Lack of test cases | K4: =IF(OR(C4="",Functions!E6="N/A"),"N/A",C4*Functions!E6/1000-N7) -> N/A
A5: Test requirement | C5: Maintain consistent batch balances across reservation, picking, dispatch, lock and release transitions. Physical stock decreases only on authorized dispatch, repeated commands remain idempotent and delivery failure does not automatically return stock without approved resolution.
A6: Passed | C6: Failed | E6: Untested | K6: N/A/B | N6: Total Test Cases
A7: =COUNTIF(E46:N46,"P") -> 0 | C7: =COUNTIF(E46:N46,"F") -> 0 | E7: =SUM(N7,-A7,-C7) -> 4 | K7: =COUNTIF(E45:N45,"N") -> 2 | L7: =COUNTIF(E45:N45,"A") -> 2 | M7: =COUNTIF(E45:N45,"B") -> 0 | N7: =COUNTA(E9:N9) -> 4
E9: UTCID01 | F9: UTCID02 | G9: UTCID03 | H9: UTCID04
A10: Condition | B10: Input / scenario
D11: Admin approved price; reservation is committed | E11: O
D12: Dispatcher tries to issue more than reserved, or there is active lock | F12: O
D14: Same dispatch movement is repeated after success | G14: O
D15: Delivery failure occurs without Admin-approved return transaction | H15: O
A26: Confirm | B26: Expected result
D27: Reserved rises, Available falls, OnHand unchanged until dispatch | E27: O
D28: Reject atomically; no negative/phantom quantity | F28: O
D30: One issue ledger transaction; no duplicated on-hand deduction | G30: O
D31: Do not auto-credit inventory or release reservation | H31: O
A45: Result | B45: Type (N/B/A) | E45: N | F45: A | G45: N | H45: A
B46: Pass/Fail (P/F)
B47: Executed Date
B48: Defect ID

Sheet Inventory Lock
A2: Function Code | C2: =Functions!E47 -> F-37 | E2: Function Name | K2: =Functions!D47 -> Quality/expiry stock lock and role restrictions
A3: Created By | C3: Doan Duc Hai | E3: Executed By
A4: Lines of code | E4: Lack of test cases | K4: =IF(OR(C4="",Functions!E6="N/A"),"N/A",C4*Functions!E6/1000-N7) -> N/A
A5: Test requirement | C5: Lock damaged, expired or otherwise unusable inventory in the authorized warehouse without exceeding physical quantity or silently altering reserved stock. Record required reasons, evidence and resolution flags, and reject unauthorized unlocking or exception settlement.
A6: Passed | C6: Failed | E6: Untested | K6: N/A/B | N6: Total Test Cases
A7: =COUNTIF(E53:N53,"P") -> 0 | C7: =COUNTIF(E53:N53,"F") -> 0 | E7: =SUM(N7,-A7,-C7) -> 4 | K7: =COUNTIF(E52:N52,"N") -> 1 | L7: =COUNTIF(E52:N52,"A") -> 2 | M7: =COUNTIF(E52:N52,"B") -> 1 | N7: =COUNTA(E9:N9) -> 4
E9: UTCID01 | F9: UTCID02 | G9: UTCID03 | H9: UTCID04
A10: Condition | B10: Input / scenario
D11: Warehouse Keeper locks unreserved damaged quantity within own warehouse | E11: O
D12: Lock overlaps stock already reserved for approved PO | F12: O
D14: Lock quantity exceeds physical or violates invariant | G14: O
D15: Sales actor tries to remove lock or settle picking exception | H15: O
A37: Confirm | B37: Expected result
D38: Available falls, physical stays; reason/evidence are retained | E38: O
D39: Mark for exception resolution; block dispatch until authorized | F39: O
D41: Reject and keep balance/ledger untouched | G41: O
D42: Forbidden; only designated actor may resolve and audit | H42: O
A52: Result | B52: Type (N/B/A) | E52: N | F52: A | G52: B | H52: A
B53: Pass/Fail (P/F)
B54: Executed Date
B55: Defect ID

Sheet Catalog Service
A2: Function Code | C2: =Functions!E48 -> F-38 | E2: Function Name | K2: =Functions!D48 -> Category hierarchy and product publish/clone lifecycle
A3: Created By | C3: Doan Duc Hai | E3: Executed By
A4: Lines of code | E4: Lack of test cases | K4: =IF(OR(C4="",Functions!E6="N/A"),"N/A",C4*Functions!E6/1000-N7) -> N/A
A5: Test requirement | C5: Authorize both Administrator and Operator to create, price, edit Draft, publish and inactivate SKU records within their scopes; preserve unique SKU, versioned prices and Published immutability. Unauthorized users cannot edit; replacements create independent Draft versions without stock/history transfer.
A6: Passed | C6: Failed | E6: Untested | K6: N/A/B | N6: Total Test Cases
A7: =COUNTIF(E40:N40,"P") -> 0 | C7: =COUNTIF(E40:N40,"F") -> 0 | E7: =SUM(N7,-A7,-C7) -> 5 | K7: =COUNTIF(E39:N39,"N") -> 3 | L7: =COUNTIF(E39:N39,"A") -> 2 | M7: =COUNTIF(E39:N39,"B") -> 0 | N7: =COUNTA(E9:N9) -> 5
E9: UTCID01 | F9: UTCID02 | G9: UTCID03 | H9: UTCID04 | I9: UTCID05
A10: Condition | B10: Input / scenario
D11: Published product is locked for edits | E11: O
D12: Publishing replacement inactivates predecessor | F12: O
D14: Clone creates independent draft and copies only allowed master data | G14: O
D15: Clone accepts editable master data without creating replacement li… | H15: O
D16: Clone rejects duplicate sku before saving | I16: O
A29: Confirm | B29: Expected result
D30: Published product is locked for edits. | E30: O
D31: Publishing replacement inactivates predecessor. | F31: O
D33: Clone creates independent draft and copies only allowed master data. | G33: O
D34: Clone accepts editable master data without creating replacement linea… | H34: O
D36: Clone rejects duplicate sku before saving. | I36: O
A39: Result | B39: Type (N/B/A) | E39: N | F39: N | G39: N | H39: A | I39: A
B40: Pass/Fail (P/F)
B41: Executed Date
B42: Defect ID
